activation_functions/prelu/prelu.v
module ParametricReLU #(parameter WIDTH = 8, ALPHA_WIDTH = 8) (
    input signed [WIDTH-1:0] x_in,              // Input value Q3.5
    input [ALPHA_WIDTH-1:0] alpha,             // Alpha parameter Q0.8 (unsigned)
    input clk,                                 // Clock signal
    input reset,                               // Reset signal
    output reg signed [WIDTH-1:0] y_out        // Output value Q3.5
);


    always @(posedge clk or negedge reset) begin
        if (~reset) begin
            y_out <= 0;  // Reset output
        end else begin
            if (x_in >= 0) begin
                y_out <= x_in;  // Pass through positive input
            end else begin
                y_out <= x_in>>>alpha;//multiplu based on alpha value
            end
        end
    end
endmodule

activation_functions/prelu/prelu_tb.v
module tb_ParametricReLU;

    // Parameters
    parameter WIDTH = 8;
    parameter ALPHA_WIDTH = 8;
    
    // Testbench signals
    reg signed [WIDTH-1:0] x_in;        // Input to PReLU
    reg [ALPHA_WIDTH-1:0] alpha; // Alpha parameter
    reg clk;                            // Clock signal
    reg reset;                          // Reset signal
    wire signed [WIDTH-1:0] y_out;      // Output of PReLU
    integer i;
    
    // Instantiate the Parametric ReLU module
    ParametricReLU #(
        .WIDTH(WIDTH),
        .ALPHA_WIDTH(ALPHA_WIDTH)
    ) prelu_inst (
        .x_in(x_in),
        .alpha(alpha),
        .clk(clk),
        .reset(reset),
        .y_out(y_out)
    );
    
    // Clock generation
   initial begin
    clk = 0;
    forever begin #0.5 clk = ~clk; end
   end  
    
    // Test sequence
    initial begin
        $dumpfile("test_prelu.vcd");
        $dumpvars(0,tb_ParametricReLU);
      $display("Begin Reset");
      reset = 0; 
      repeat(2)@(posedge clk);
      reset = 1;
      $display("End reset"); 
      $display("Testing Prelu Module:");
      $display("  input\t\toutput");
      @(negedge clk)
      alpha = 1; //0.5
      for (i = 0; i < 256; i = i + 1) begin
          x_in = (i - 128); // Test inputs: -128, -96, ..., 127
          @(negedge clk)
          $display("%d\t\t%d\t\t", x_in, y_out);
      end 
        // End simulation
      $finish;
    end
    
endmodule

activation_functions/prelu/test_prelu.vcd
$date
	Tue Dec  3 17:58:10 2024
$end
$version
	Icarus Verilog
$end
$timescale
	1s
$end
$scope module tb_ParametricReLU $end
$var wire 8 ! y_out [7:0] $end
$var reg 8 " alpha [7:0] $end
$var reg 1 # clk $end
$var reg 1 $ reset $end
$var reg 8 % x_in [7:0] $end
$var integer 32 & i [31:0] $end
$scope module prelu_inst $end
$var wire 8 ' alpha [7:0] $end
$var wire 1 # clk $end
$var wire 1 $ reset $end
$var wire 8 ( x_in [7:0] $end
$var reg 8 ) y_out [7:0] $end
$upscope $end
$upscope $end
$enddefinitions $end
#0
$dumpvars
bx )
bx (
bx '
bx &
bx %
0$
0#
bx "
bx !
$end
#1
b0 !
b0 )
1#
#2
0#
#3
bx !
bx )
1$
1#
#4
b10000000 %
b10000000 (
b0 &
b1 "
b1 '
0#
#5
b11000000 !
b11000000 )
1#
#6
b10000001 %
b10000001 (
b1 &
0#
#7
1#
#8
b10000010 %
b10000010 (
b10 &
0#
#9
b11000001 !
b11000001 )
1#
#10
b10000011 %
b10000011 (
b11 &
0#
#11
1#
#12
b10000100 %
b10000100 (
b100 &
0#
#13
b11000010 !
b11000010 )
1#
#14
b10000101 %
b10000101 (
b101 &
0#
#15
1#
#16
b10000110 %
b10000110 (
b110 &
0#
#17
b11000011 !
b11000011 )
1#
#18
b10000111 %
b10000111 (
b111 &
0#
#19
1#
#20
b10001000 %
b10001000 (
b1000 &
0#
#21
b11000100 !
b11000100 )
1#
#22
b10001001 %
b10001001 (
b1001 &
0#
#23
1#
#24
b10001010 %
b10001010 (
b1010 &
0#
#25
b11000101 !
b11000101 )
1#
#26
b10001011 %
b10001011 (
b1011 &
0#
#27
1#
#28
b10001100 %
b10001100 (
b1100 &
0#
#29
b11000110 !
b11000110 )
1#
#30
b10001101 %
b10001101 (
b1101 &
0#
#31
1#
#32
b10001110 %
b10001110 (
b1110 &
0#
#33
b11000111 !
b11000111 )
1#
#34
b10001111 %
b10001111 (
b1111 &
0#
#35
1#
#36
b10010000 %
b10010000 (
b10000 &
0#
#37
b11001000 !
b11001000 )
1#
#38
b10010001 %
b10010001 (
b10001 &
0#
#39
1#
#40
b10010010 %
b10010010 (
b10010 &
0#
#41
b11001001 !
b11001001 )
1#
#42
b10010011 %
b10010011 (
b10011 &
0#
#43
1#
#44
b10010100 %
b10010100 (
b10100 &
0#
#45
b11001010 !
b11001010 )
1#
#46
b10010101 %
b10010101 (
b10101 &
0#
#47
1#
#48
b10010110 %
b10010110 (
b10110 &
0#
#49
b11001011 !
b11001011 )
1#
#50
b10010111 %
b10010111 (
b10111 &
0#
#51
1#
#52
b10011000 %
b10011000 (
b11000 &
0#
#53
b11001100 !
b11001100 )
1#
#54
b10011001 %
b10011001 (
b11001 &
0#
#55
1#
#56
b10011010 %
b10011010 (
b11010 &
0#
#57
b11001101 !
b11001101 )
1#
#58
b10011011 %
b10011011 (
b11011 &
0#
#59
1#
#60
b10011100 %
b10011100 (
b11100 &
0#
#61
b11001110 !
b11001110 )
1#
#62
b10011101 %
b10011101 (
b11101 &
0#
#63
1#
#64
b10011110 %
b10011110 (
b11110 &
0#
#65
b11001111 !
b11001111 )
1#
#66
b10011111 %
b10011111 (
b11111 &
0#
#67
1#
#68
b10100000 %
b10100000 (
b100000 &
0#
#69
b11010000 !
b11010000 )
1#
#70
b10100001 %
b10100001 (
b100001 &
0#
#71
1#
#72
b10100010 %
b10100010 (
b100010 &
0#
#73
b11010001 !
b11010001 )
1#
#74
b10100011 %
b10100011 (
b100011 &
0#
#75
1#
#76
b10100100 %
b10100100 (
b100100 &
0#
#77
b11010010 !
b11010010 )
1#
#78
b10100101 %
b10100101 (
b100101 &
0#
#79
1#
#80
b10100110 %
b10100110 (
b100110 &
0#
#81
b11010011 !
b11010011 )
1#
#82
b10100111 %
b10100111 (
b100111 &
0#
#83
1#
#84
b10101000 %
b10101000 (
b101000 &
0#
#85
b11010100 !
b11010100 )
1#
#86
b10101001 %
b10101001 (
b101001 &
0#
#87
1#
#88
b10101010 %
b10101010 (
b101010 &
0#
#89
b11010101 !
b11010101 )
1#
#90
b10101011 %
b10101011 (
b101011 &
0#
#91
1#
#92
b10101100 %
b10101100 (
b101100 &
0#
#93
b11010110 !
b11010110 )
1#
#94
b10101101 %
b10101101 (
b101101 &
0#
#95
1#
#96
b10101110 %
b10101110 (
b101110 &
0#
#97
b11010111 !
b11010111 )
1#
#98
b10101111 %
b10101111 (
b101111 &
0#
#99
1#
#100
b10110000 %
b10110000 (
b110000 &
0#
#101
b11011000 !
b11011000 )
1#
#102
b10110001 %
b10110001 (
b110001 &
0#
#103
1#
#104
b10110010 %
b10110010 (
b110010 &
0#
#105
b11011001 !
b11011001 )
1#
#106
b10110011 %
b10110011 (
b110011 &
0#
#107
1#
#108
b10110100 %
b10110100 (
b110100 &
0#
#109
b11011010 !
b11011010 )
1#
#110
b10110101 %
b10110101 (
b110101 &
0#
#111
1#
#112
b10110110 %
b10110110 (
b110110 &
0#
#113
b11011011 !
b11011011 )
1#
#114
b10110111 %
b10110111 (
b110111 &
0#
#115
1#
#116
b10111000 %
b10111000 (
b111000 &
0#
#117
b11011100 !
b11011100 )
1#
#118
b10111001 %
b10111001 (
b111001 &
0#
#119
1#
#120
b10111010 %
b10111010 (
b111010 &
0#
#121
b11011101 !
b11011101 )
1#
#122
b10111011 %
b10111011 (
b111011 &
0#
#123
1#
#124
b10111100 %
b10111100 (
b111100 &
0#
#125
b11011110 !
b11011110 )
1#
#126
b10111101 %
b10111101 (
b111101 &
0#
#127
1#
#128
b10111110 %
b10111110 (
b111110 &
0#
#129
b11011111 !
b11011111 )
1#
#130
b10111111 %
b10111111 (
b111111 &
0#
#131
1#
#132
b11000000 %
b11000000 (
b1000000 &
0#
#133
b11100000 !
b11100000 )
1#
#134
b11000001 %
b11000001 (
b1000001 &
0#
#135
1#
#136
b11000010 %
b11000010 (
b1000010 &
0#
#137
b11100001 !
b11100001 )
1#
#138
b11000011 %
b11000011 (
b1000011 &
0#
#139
1#
#140
b11000100 %
b11000100 (
b1000100 &
0#
#141
b11100010 !
b11100010 )
1#
#142
b11000101 %
b11000101 (
b1000101 &
0#
#143
1#
#144
b11000110 %
b11000110 (
b1000110 &
0#
#145
b11100011 !
b11100011 )
1#
#146
b11000111 %
b11000111 (
b1000111 &
0#
#147
1#
#148
b11001000 %
b11001000 (
b1001000 &
0#
#149
b11100100 !
b11100100 )
1#
#150
b11001001 %
b11001001 (
b1001001 &
0#
#151
1#
#152
b11001010 %
b11001010 (
b1001010 &
0#
#153
b11100101 !
b11100101 )
1#
#154
b11001011 %
b11001011 (
b1001011 &
0#
#155
1#
#156
b11001100 %
b11001100 (
b1001100 &
0#
#157
b11100110 !
b11100110 )
1#
#158
b11001101 %
b11001101 (
b1001101 &
0#
#159
1#
#160
b11001110 %
b11001110 (
b1001110 &
0#
#161
b11100111 !
b11100111 )
1#
#162
b11001111 %
b11001111 (
b1001111 &
0#
#163
1#
#164
b11010000 %
b11010000 (
b1010000 &
0#
#165
b11101000 !
b11101000 )
1#
#166
b11010001 %
b11010001 (
b1010001 &
0#
#167
1#
#168
b11010010 %
b11010010 (
b1010010 &
0#
#169
b11101001 !
b11101001 )
1#
#170
b11010011 %
b11010011 (
b1010011 &
0#
#171
1#
#172
b11010100 %
b11010100 (
b1010100 &
0#
#173
b11101010 !
b11101010 )
1#
#174
b11010101 %
b11010101 (
b1010101 &
0#
#175
1#
#176
b11010110 %
b11010110 (
b1010110 &
0#
#177
b11101011 !
b11101011 )
1#
#178
b11010111 %
b11010111 (
b1010111 &
0#
#179
1#
#180
b11011000 %
b11011000 (
b1011000 &
0#
#181
b11101100 !
b11101100 )
1#
#182
b11011001 %
b11011001 (
b1011001 &
0#
#183
1#
#184
b11011010 %
b11011010 (
b1011010 &
0#
#185
b11101101 !
b11101101 )
1#
#186
b11011011 %
b11011011 (
b1011011 &
0#
#187
1#
#188
b11011100 %
b11011100 (
b1011100 &
0#
#189
b11101110 !
b11101110 )
1#
#190
b11011101 %
b11011101 (
b1011101 &
0#
#191
1#
#192
b11011110 %
b11011110 (
b1011110 &
0#
#193
b11101111 !
b11101111 )
1#
#194
b11011111 %
b11011111 (
b1011111 &
0#
#195
1#
#196
b11100000 %
b11100000 (
b1100000 &
0#
#197
b11110000 !
b11110000 )
1#
#198
b11100001 %
b11100001 (
b1100001 &
0#
#199
1#
#200
b11100010 %
b11100010 (
b1100010 &
0#
#201
b11110001 !
b11110001 )
1#
#202
b11100011 %
b11100011 (
b1100011 &
0#
#203
1#
#204
b11100100 %
b11100100 (
b1100100 &
0#
#205
b11110010 !
b11110010 )
1#
#206
b11100101 %
b11100101 (
b1100101 &
0#
#207
1#
#208
b11100110 %
b11100110 (
b1100110 &
0#
#209
b11110011 !
b11110011 )
1#
#210
b11100111 %
b11100111 (
b1100111 &
0#
#211
1#
#212
b11101000 %
b11101000 (
b1101000 &
0#
#213
b11110100 !
b11110100 )
1#
#214
b11101001 %
b11101001 (
b1101001 &
0#
#215
1#
#216
b11101010 %
b11101010 (
b1101010 &
0#
#217
b11110101 !
b11110101 )
1#
#218
b11101011 %
b11101011 (
b1101011 &
0#
#219
1#
#220
b11101100 %
b11101100 (
b1101100 &
0#
#221
b11110110 !
b11110110 )
1#
#222
b11101101 %
b11101101 (
b1101101 &
0#
#223
1#
#224
b11101110 %
b11101110 (
b1101110 &
0#
#225
b11110111 !
b11110111 )
1#
#226
b11101111 %
b11101111 (
b1101111 &
0#
#227
1#
#228
b11110000 %
b11110000 (
b1110000 &
0#
#229
b11111000 !
b11111000 )
1#
#230
b11110001 %
b11110001 (
b1110001 &
0#
#231
1#
#232
b11110010 %
b11110010 (
b1110010 &
0#
#233
b11111001 !
b11111001 )
1#
#234
b11110011 %
b11110011 (
b1110011 &
0#
#235
1#
#236
b11110100 %
b11110100 (
b1110100 &
0#
#237
b11111010 !
b11111010 )
1#
#238
b11110101 %
b11110101 (
b1110101 &
0#
#239
1#
#240
b11110110 %
b11110110 (
b1110110 &
0#
#241
b11111011 !
b11111011 )
1#
#242
b11110111 %
b11110111 (
b1110111 &
0#
#243
1#
#244
b11111000 %
b11111000 (
b1111000 &
0#
#245
b11111100 !
b11111100 )
1#
#246
b11111001 %
b11111001 (
b1111001 &
0#
#247
1#
#248
b11111010 %
b11111010 (
b1111010 &
0#
#249
b11111101 !
b11111101 )
1#
#250
b11111011 %
b11111011 (
b1111011 &
0#
#251
1#
#252
b11111100 %
b11111100 (
b1111100 &
0#
#253
b11111110 !
b11111110 )
1#
#254
b11111101 %
b11111101 (
b1111101 &
0#
#255
1#
#256
b11111110 %
b11111110 (
b1111110 &
0#
#257
b11111111 !
b11111111 )
1#
#258
b11111111 %
b11111111 (
b1111111 &
0#
#259
1#
#260
b0 %
b0 (
b10000000 &
0#
#261
b0 !
b0 )
1#
#262
b1 %
b1 (
b10000001 &
0#
#263
b1 !
b1 )
1#
#264
b10 %
b10 (
b10000010 &
0#
#265
b10 !
b10 )
1#
#266
b11 %
b11 (
b10000011 &
0#
#267
b11 !
b11 )
1#
#268
b100 %
b100 (
b10000100 &
0#
#269
b100 !
b100 )
1#
#270
b101 %
b101 (
b10000101 &
0#
#271
b101 !
b101 )
1#
#272
b110 %
b110 (
b10000110 &
0#
#273
b110 !
b110 )
1#
#274
b111 %
b111 (
b10000111 &
0#
#275
b111 !
b111 )
1#
#276
b1000 %
b1000 (
b10001000 &
0#
#277
b1000 !
b1000 )
1#
#278
b1001 %
b1001 (
b10001001 &
0#
#279
b1001 !
b1001 )
1#
#280
b1010 %
b1010 (
b10001010 &
0#
#281
b1010 !
b1010 )
1#
#282
b1011 %
b1011 (
b10001011 &
0#
#283
b1011 !
b1011 )
1#
#284
b1100 %
b1100 (
b10001100 &
0#
#285
b1100 !
b1100 )
1#
#286
b1101 %
b1101 (
b10001101 &
0#
#287
b1101 !
b1101 )
1#
#288
b1110 %
b1110 (
b10001110 &
0#
#289
b1110 !
b1110 )
1#
#290
b1111 %
b1111 (
b10001111 &
0#
#291
b1111 !
b1111 )
1#
#292
b10000 %
b10000 (
b10010000 &
0#
#293
b10000 !
b10000 )
1#
#294
b10001 %
b10001 (
b10010001 &
0#
#295
b10001 !
b10001 )
1#
#296
b10010 %
b10010 (
b10010010 &
0#
#297
b10010 !
b10010 )
1#
#298
b10011 %
b10011 (
b10010011 &
0#
#299
b10011 !
b10011 )
1#
#300
b10100 %
b10100 (
b10010100 &
0#
#301
b10100 !
b10100 )
1#
#302
b10101 %
b10101 (
b10010101 &
0#
#303
b10101 !
b10101 )
1#
#304
b10110 %
b10110 (
b10010110 &
0#
#305
b10110 !
b10110 )
1#
#306
b10111 %
b10111 (
b10010111 &
0#
#307
b10111 !
b10111 )
1#
#308
b11000 %
b11000 (
b10011000 &
0#
#309
b11000 !
b11000 )
1#
#310
b11001 %
b11001 (
b10011001 &
0#
#311
b11001 !
b11001 )
1#
#312
b11010 %
b11010 (
b10011010 &
0#
#313
b11010 !
b11010 )
1#
#314
b11011 %
b11011 (
b10011011 &
0#
#315
b11011 !
b11011 )
1#
#316
b11100 %
b11100 (
b10011100 &
0#
#317
b11100 !
b11100 )
1#
#318
b11101 %
b11101 (
b10011101 &
0#
#319
b11101 !
b11101 )
1#
#320
b11110 %
b11110 (
b10011110 &
0#
#321
b11110 !
b11110 )
1#
#322
b11111 %
b11111 (
b10011111 &
0#
#323
b11111 !
b11111 )
1#
#324
b100000 %
b100000 (
b10100000 &
0#
#325
b100000 !
b100000 )
1#
#326
b100001 %
b100001 (
b10100001 &
0#
#327
b100001 !
b100001 )
1#
#328
b100010 %
b100010 (
b10100010 &
0#
#329
b100010 !
b100010 )
1#
#330
b100011 %
b100011 (
b10100011 &
0#
#331
b100011 !
b100011 )
1#
#332
b100100 %
b100100 (
b10100100 &
0#
#333
b100100 !
b100100 )
1#
#334
b100101 %
b100101 (
b10100101 &
0#
#335
b100101 !
b100101 )
1#
#336
b100110 %
b100110 (
b10100110 &
0#
#337
b100110 !
b100110 )
1#
#338
b100111 %
b100111 (
b10100111 &
0#
#339
b100111 !
b100111 )
1#
#340
b101000 %
b101000 (
b10101000 &
0#
#341
b101000 !
b101000 )
1#
#342
b101001 %
b101001 (
b10101001 &
0#
#343
b101001 !
b101001 )
1#
#344
b101010 %
b101010 (
b10101010 &
0#
#345
b101010 !
b101010 )
1#
#346
b101011 %
b101011 (
b10101011 &
0#
#347
b101011 !
b101011 )
1#
#348
b101100 %
b101100 (
b10101100 &
0#
#349
b101100 !
b101100 )
1#
#350
b101101 %
b101101 (
b10101101 &
0#
#351
b101101 !
b101101 )
1#
#352
b101110 %
b101110 (
b10101110 &
0#
#353
b101110 !
b101110 )
1#
#354
b101111 %
b101111 (
b10101111 &
0#
#355
b101111 !
b101111 )
1#
#356
b110000 %
b110000 (
b10110000 &
0#
#357
b110000 !
b110000 )
1#
#358
b110001 %
b110001 (
b10110001 &
0#
#359
b110001 !
b110001 )
1#
#360
b110010 %
b110010 (
b10110010 &
0#
#361
b110010 !
b110010 )
1#
#362
b110011 %
b110011 (
b10110011 &
0#
#363
b110011 !
b110011 )
1#
#364
b110100 %
b110100 (
b10110100 &
0#
#365
b110100 !
b110100 )
1#
#366
b110101 %
b110101 (
b10110101 &
0#
#367
b110101 !
b110101 )
1#
#368
b110110 %
b110110 (
b10110110 &
0#
#369
b110110 !
b110110 )
1#
#370
b110111 %
b110111 (
b10110111 &
0#
#371
b110111 !
b110111 )
1#
#372
b111000 %
b111000 (
b10111000 &
0#
#373
b111000 !
b111000 )
1#
#374
b111001 %
b111001 (
b10111001 &
0#
#375
b111001 !
b111001 )
1#
#376
b111010 %
b111010 (
b10111010 &
0#
#377
b111010 !
b111010 )
1#
#378
b111011 %
b111011 (
b10111011 &
0#
#379
b111011 !
b111011 )
1#
#380
b111100 %
b111100 (
b10111100 &
0#
#381
b111100 !
b111100 )
1#
#382
b111101 %
b111101 (
b10111101 &
0#
#383
b111101 !
b111101 )
1#
#384
b111110 %
b111110 (
b10111110 &
0#
#385
b111110 !
b111110 )
1#
#386
b111111 %
b111111 (
b10111111 &
0#
#387
b111111 !
b111111 )
1#
#388
b1000000 %
b1000000 (
b11000000 &
0#
#389
b1000000 !
b1000000 )
1#
#390
b1000001 %
b1000001 (
b11000001 &
0#
#391
b1000001 !
b1000001 )
1#
#392
b1000010 %
b1000010 (
b11000010 &
0#
#393
b1000010 !
b1000010 )
1#
#394
b1000011 %
b1000011 (
b11000011 &
0#
#395
b1000011 !
b1000011 )
1#
#396
b1000100 %
b1000100 (
b11000100 &
0#
#397
b1000100 !
b1000100 )
1#
#398
b1000101 %
b1000101 (
b11000101 &
0#
#399
b1000101 !
b1000101 )
1#
#400
b1000110 %
b1000110 (
b11000110 &
0#
#401
b1000110 !
b1000110 )
1#
#402
b1000111 %
b1000111 (
b11000111 &
0#
#403
b1000111 !
b1000111 )
1#
#404
b1001000 %
b1001000 (
b11001000 &
0#
#405
b1001000 !
b1001000 )
1#
#406
b1001001 %
b1001001 (
b11001001 &
0#
#407
b1001001 !
b1001001 )
1#
#408
b1001010 %
b1001010 (
b11001010 &
0#
#409
b1001010 !
b1001010 )
1#
#410
b1001011 %
b1001011 (
b11001011 &
0#
#411
b1001011 !
b1001011 )
1#
#412
b1001100 %
b1001100 (
b11001100 &
0#
#413
b1001100 !
b1001100 )
1#
#414
b1001101 %
b1001101 (
b11001101 &
0#
#415
b1001101 !
b1001101 )
1#
#416
b1001110 %
b1001110 (
b11001110 &
0#
#417
b1001110 !
b1001110 )
1#
#418
b1001111 %
b1001111 (
b11001111 &
0#
#419
b1001111 !
b1001111 )
1#
#420
b1010000 %
b1010000 (
b11010000 &
0#
#421
b1010000 !
b1010000 )
1#
#422
b1010001 %
b1010001 (
b11010001 &
0#
#423
b1010001 !
b1010001 )
1#
#424
b1010010 %
b1010010 (
b11010010 &
0#
#425
b1010010 !
b1010010 )
1#
#426
b1010011 %
b1010011 (
b11010011 &
0#
#427
b1010011 !
b1010011 )
1#
#428
b1010100 %
b1010100 (
b11010100 &
0#
#429
b1010100 !
b1010100 )
1#
#430
b1010101 %
b1010101 (
b11010101 &
0#
#431
b1010101 !
b1010101 )
1#
#432
b1010110 %
b1010110 (
b11010110 &
0#
#433
b1010110 !
b1010110 )
1#
#434
b1010111 %
b1010111 (
b11010111 &
0#
#435
b1010111 !
b1010111 )
1#
#436
b1011000 %
b1011000 (
b11011000 &
0#
#437
b1011000 !
b1011000 )
1#
#438
b1011001 %
b1011001 (
b11011001 &
0#
#439
b1011001 !
b1011001 )
1#
#440
b1011010 %
b1011010 (
b11011010 &
0#
#441
b1011010 !
b1011010 )
1#
#442
b1011011 %
b1011011 (
b11011011 &
0#
#443
b1011011 !
b1011011 )
1#
#444
b1011100 %
b1011100 (
b11011100 &
0#
#445
b1011100 !
b1011100 )
1#
#446
b1011101 %
b1011101 (
b11011101 &
0#
#447
b1011101 !
b1011101 )
1#
#448
b1011110 %
b1011110 (
b11011110 &
0#
#449
b1011110 !
b1011110 )
1#
#450
b1011111 %
b1011111 (
b11011111 &
0#
#451
b1011111 !
b1011111 )
1#
#452
b1100000 %
b1100000 (
b11100000 &
0#
#453
b1100000 !
b1100000 )
1#
#454
b1100001 %
b1100001 (
b11100001 &
0#
#455
b1100001 !
b1100001 )
1#
#456
b1100010 %
b1100010 (
b11100010 &
0#
#457
b1100010 !
b1100010 )
1#
#458
b1100011 %
b1100011 (
b11100011 &
0#
#459
b1100011 !
b1100011 )
1#
#460
b1100100 %
b1100100 (
b11100100 &
0#
#461
b1100100 !
b1100100 )
1#
#462
b1100101 %
b1100101 (
b11100101 &
0#
#463
b1100101 !
b1100101 )
1#
#464
b1100110 %
b1100110 (
b11100110 &
0#
#465
b1100110 !
b1100110 )
1#
#466
b1100111 %
b1100111 (
b11100111 &
0#
#467
b1100111 !
b1100111 )
1#
#468
b1101000 %
b1101000 (
b11101000 &
0#
#469
b1101000 !
b1101000 )
1#
#470
b1101001 %
b1101001 (
b11101001 &
0#
#471
b1101001 !
b1101001 )
1#
#472
b1101010 %
b1101010 (
b11101010 &
0#
#473
b1101010 !
b1101010 )
1#
#474
b1101011 %
b1101011 (
b11101011 &
0#
#475
b1101011 !
b1101011 )
1#
#476
b1101100 %
b1101100 (
b11101100 &
0#
#477
b1101100 !
b1101100 )
1#
#478
b1101101 %
b1101101 (
b11101101 &
0#
#479
b1101101 !
b1101101 )
1#
#480
b1101110 %
b1101110 (
b11101110 &
0#
#481
b1101110 !
b1101110 )
1#
#482
b1101111 %
b1101111 (
b11101111 &
0#
#483
b1101111 !
b1101111 )
1#
#484
b1110000 %
b1110000 (
b11110000 &
0#
#485
b1110000 !
b1110000 )
1#
#486
b1110001 %
b1110001 (
b11110001 &
0#
#487
b1110001 !
b1110001 )
1#
#488
b1110010 %
b1110010 (
b11110010 &
0#
#489
b1110010 !
b1110010 )
1#
#490
b1110011 %
b1110011 (
b11110011 &
0#
#491
b1110011 !
b1110011 )
1#
#492
b1110100 %
b1110100 (
b11110100 &
0#
#493
b1110100 !
b1110100 )
1#
#494
b1110101 %
b1110101 (
b11110101 &
0#
#495
b1110101 !
b1110101 )
1#
#496
b1110110 %
b1110110 (
b11110110 &
0#
#497
b1110110 !
b1110110 )
1#
#498
b1110111 %
b1110111 (
b11110111 &
0#
#499
b1110111 !
b1110111 )
1#
#500
b1111000 %
b1111000 (
b11111000 &
0#
#501
b1111000 !
b1111000 )
1#
#502
b1111001 %
b1111001 (
b11111001 &
0#
#503
b1111001 !
b1111001 )
1#
#504
b1111010 %
b1111010 (
b11111010 &
0#
#505
b1111010 !
b1111010 )
1#
#506
b1111011 %
b1111011 (
b11111011 &
0#
#507
b1111011 !
b1111011 )
1#
#508
b1111100 %
b1111100 (
b11111100 &
0#
#509
b1111100 !
b1111100 )
1#
#510
b1111101 %
b1111101 (
b11111101 &
0#
#511
b1111101 !
b1111101 )
1#
#512
b1111110 %
b1111110 (
b11111110 &
0#
#513
b1111110 !
b1111110 )
1#
#514
b1111111 %
b1111111 (
b11111111 &
0#
#515
b1111111 !
b1111111 )
1#
#516
b100000000 &
0#
