activation_functions/sigmoid/lut_based.v
module sigmoid_lut (
    input clk,
    input reset,
    input signed [7:0] x_in,  // Q3.5 input (-4 to 4)
    output reg [7:0] y_out    // Q0.8 output (0 to 1)
);

     reg [7:0] LUT [255:0];

    //registering output
    always @(posedge clk or negedge reset) begin
      if(~reset) begin
        y_out <= 0;
      end
      else begin
        y_out <= LUT['sd128+x_in];
      end
    end 


    always @(posedge clk or negedge reset) begin
      LUT[0]  <= 5; LUT[1]  <= 5; LUT[2]  <= 5; LUT[3]  <= 5; LUT[4]  <= 5; LUT[5]  <= 5;
      LUT[6]  <= 6; LUT[7]  <= 6; LUT[8]  <= 6; LUT[9]  <= 6; LUT[10] <= 6; LUT[11] <= 6;
      LUT[12] <= 7; LUT[13] <= 7; LUT[14] <= 7; LUT[15] <= 7; LUT[16] <= 8; LUT[17] <= 8;
      LUT[18] <= 8; LUT[19] <= 8; LUT[20] <= 8; LUT[21] <= 9; LUT[22] <= 9; LUT[23] <= 9;
      LUT[24] <= 10; LUT[25] <= 10; LUT[26] <= 10; LUT[27] <= 10; LUT[28] <= 11; LUT[29] <= 11;
      LUT[30] <= 11; LUT[31] <= 12; LUT[32] <= 12; LUT[33] <= 13; LUT[34] <= 13; LUT[35] <= 13;
      LUT[36] <= 14; LUT[37] <= 14; LUT[38] <= 15; LUT[39] <= 15; LUT[40] <= 15; LUT[41] <= 16;
      LUT[42] <= 16; LUT[43] <= 17; LUT[44] <= 17; LUT[45] <= 18; LUT[46] <= 18; LUT[47] <= 19;
      LUT[48] <= 19; LUT[49] <= 20; LUT[50] <= 21; LUT[51] <= 21; LUT[52] <= 22; LUT[53] <= 22;
      LUT[54] <= 23; LUT[55] <= 24; LUT[56] <= 24; LUT[57] <= 25; LUT[58] <= 26; LUT[59] <= 27;
      LUT[60] <= 27; LUT[61] <= 28; LUT[62] <= 29; LUT[63] <= 30; LUT[64] <= 31; LUT[65] <= 31;
      LUT[66] <= 32; LUT[67] <= 33; LUT[68] <= 34; LUT[69] <= 35; LUT[70] <= 36; LUT[71] <= 37;
      LUT[72] <= 38; LUT[73] <= 39; LUT[74] <= 40; LUT[75] <= 41; LUT[76] <= 42; LUT[77] <= 43;
      LUT[78] <= 44; LUT[79] <= 46; LUT[80] <= 47; LUT[81] <= 48; LUT[82] <= 49; LUT[83] <= 50;
      LUT[84] <= 52; LUT[85] <= 53; LUT[86] <= 54; LUT[87] <= 56; LUT[88] <= 57; LUT[89] <= 58;
      LUT[90] <= 60; LUT[91] <= 61; LUT[92] <= 63; LUT[93] <= 64; LUT[94] <= 66; LUT[95] <= 67;
      LUT[96] <= 69; LUT[97] <= 70; LUT[98] <= 72; LUT[99] <= 74; LUT[100] <= 75; LUT[101] <= 77;
      LUT[102] <= 79; LUT[103] <= 80; LUT[104] <= 82; LUT[105] <= 84; LUT[106] <= 86; LUT[107] <= 87;
      LUT[108] <= 89; LUT[109] <= 91; LUT[110] <= 93; LUT[111] <= 95; LUT[112] <= 97; LUT[113] <= 99;
      LUT[114] <= 100; LUT[115] <= 102; LUT[116] <= 104; LUT[117] <= 106; LUT[118] <= 108; LUT[119] <= 110;
      LUT[120] <= 112; LUT[121] <= 114; LUT[122] <= 116; LUT[123] <= 118; LUT[124] <= 120; LUT[125] <= 122;
      LUT[126] <= 124; LUT[127] <= 126; LUT[128] <= 128; LUT[129] <= 130; LUT[130] <= 132; LUT[131] <= 134;
      LUT[132] <= 136; LUT[133] <= 138; LUT[134] <= 140; LUT[135] <= 142; LUT[136] <= 144; LUT[137] <= 146;
      LUT[138] <= 148; LUT[139] <= 150; LUT[140] <= 152; LUT[141] <= 154; LUT[142] <= 156; LUT[143] <= 157;
      LUT[144] <= 159; LUT[145] <= 161; LUT[146] <= 163; LUT[147] <= 165; LUT[148] <= 167; LUT[149] <= 169;
      LUT[150] <= 170; LUT[151] <= 172; LUT[152] <= 174; LUT[153] <= 176; LUT[154] <= 177; LUT[155] <= 179;
      LUT[156] <= 181; LUT[157] <= 182; LUT[158] <= 184; LUT[159] <= 186; LUT[160] <= 187; LUT[161] <= 189;
      LUT[162] <= 190; LUT[163] <= 192; LUT[164] <= 193; LUT[165] <= 195; LUT[166] <= 196; LUT[167] <= 198;
      LUT[168] <= 199; LUT[169] <= 200; LUT[170] <= 202; LUT[171] <= 203; LUT[172] <= 204; LUT[173] <= 206;
      LUT[174] <= 207; LUT[175] <= 208; LUT[176] <= 209; LUT[177] <= 210; LUT[178] <= 212; LUT[179] <= 213;
      LUT[180] <= 214; LUT[181] <= 215; LUT[182] <= 216; LUT[183] <= 217; LUT[184] <= 218; LUT[185] <= 219;
      LUT[186] <= 220; LUT[187] <= 221; LUT[188] <= 222; LUT[189] <= 223; LUT[190] <= 224; LUT[191] <= 225;
      LUT[192] <= 225; LUT[193] <= 226; LUT[194] <= 227; LUT[195] <= 228; LUT[196] <= 229; LUT[197] <= 229;
      LUT[198] <= 230; LUT[199] <= 231; LUT[200] <= 232; LUT[201] <= 232; LUT[202] <= 233; LUT[203] <= 234;
      LUT[204] <= 234; LUT[205] <= 235; LUT[206] <= 235; LUT[207] <= 236; LUT[208] <= 237; LUT[209] <= 237;
      LUT[210] <= 238; LUT[211] <= 238; LUT[212] <= 239; LUT[213] <= 239; LUT[214] <= 240; LUT[215] <= 240;
      LUT[216] <= 241; LUT[217] <= 241; LUT[218] <= 241; LUT[219] <= 242; LUT[220] <= 242; LUT[221] <= 243;
      LUT[222] <= 243; LUT[223] <= 243; LUT[224] <= 244; LUT[225] <= 244; LUT[226] <= 245; LUT[227] <= 245;
      LUT[228] <= 245; LUT[229] <= 246; LUT[230] <= 246; LUT[231] <= 246; LUT[232] <= 246; LUT[233] <= 247;
      LUT[234] <= 247; LUT[235] <= 247; LUT[236] <= 248; LUT[237] <= 248; LUT[238] <= 248; LUT[239] <= 248;
      LUT[240] <= 248; LUT[241] <= 249; LUT[242] <= 249; LUT[243] <= 249; LUT[244] <= 250; LUT[245] <= 250;
      LUT[246] <= 250; LUT[247] <= 250; LUT[248] <= 250; LUT[249] <= 250; LUT[250] <= 251; LUT[251] <= 251;
      LUT[252] <= 251; LUT[253] <= 251; LUT[254] <= 251; LUT[255] <= 251;
    end

endmodule

activation_functions/sigmoid/piecewise_linear.v
module sigmoid_piecewise (
    input clk,
    input reset,
    input signed [7:0] x_in,  // Q3.5 input (-4 to 4)
    output reg [7:0] y_out    // Q0.8 output (0 to 1)
);

    // Precomputed constants (Q0.8 format for slopes and offsets)
    // Now the slopes are scaled as powers of 2 to avoid multiplication
    // Each slope is represented as shift constants

    // Slope for -4 to -2 (a = 0.03125 -> shift by 5)
    localparam signed [7:0] SHIFT_1 = 1;    
    localparam signed [7:0] OFFSET_1 = 8'd5;  // Offset for -4 to -2 (b = 0.0 -> Q0.8 = 5)

    // Slope for -2 to -1 (a = 0.125 -> shift by 3)
    localparam signed [7:0] SHIFT_2 = 0;    
    localparam signed [7:0] OFFSET_2 = 8'd32;  // Offset for -2 to -1 (b = 0.125 -> Q0.8 = 32)

    // Slope for -1 to 1 (a = 0.25 -> shift by 2)
    localparam signed [7:0] SHIFT_3 = 1;   
    localparam signed [7:0] OFFSET_3 = 8'd69;  // Offset for -1 to 1 (b = 0.375 -> Q0.8 = 96)

    // Slope for 1 to 2 (a = 0.125 -> shift by 3)
    localparam signed [7:0] SHIFT_4 = 0;    
    localparam signed [7:0] OFFSET_4 = 8'd187; // Offset for 1 to 2 (b = 0.625 -> Q0.8 = 160)

    // Slope for 2 to 4 (a = 0.03125 -> shift by 5)
    localparam signed [7:0] SHIFT_5 = 1;    
    localparam signed [7:0] OFFSET_5 = 8'd225; // Offset for 2 to 4 (b = 0.75 -> Q0.8 = 192)
   
    reg [7:0] y_s;

    //registering output
    always @(posedge clk or negedge reset) begin
      if(~reset) begin
        y_out <= 0;
      end
      else begin
        y_out <= y_s;
      end
    end 

    always @(*) begin
        if (x_in <= -128) begin
            y_s = 8'd0;  // Output saturates to 0 for x <= -4
        end else if (x_in >= 127) begin
            y_s = 8'd255; // Output saturates to 1 for x >= 4
        end else if (x_in < -64) begin  // Segment 1: -4 to -2
            y_s = ((x_in + 128) >>> SHIFT_1) + OFFSET_1;
        end else if (x_in < -32) begin  // Segment 2: -2 to -1
            y_s = ((x_in + 64) >>> SHIFT_2) + OFFSET_2;
        end else if (x_in < 32) begin  // Segment 3: -1 to 1
            y_s = ((x_in + 32) <<< SHIFT_3) + OFFSET_3;
        end else if (x_in < 64) begin  // Segment 4: 1 to 2
            y_s = ((x_in - 32) >>> SHIFT_4) + OFFSET_4;
        end else begin  // Segment 5: 2 to 4
            y_s = ((x_in - 64) >>> SHIFT_5) + OFFSET_5;
        end
    end
endmodule

activation_functions/sigmoid/sigmoid_tb.v
module test_sigmoid;
    reg signed [7:0] x;
    wire [7:0] y_piecewise, y_lut;
    integer i;
    reg reset;
    reg clk;

    sigmoid_piecewise instance_piecewise (
        .x_in(x),
        .y_out(y_piecewise),
        .clk(clk),
        .reset(reset)
    );

    sigmoid_lut instance_lut (
        .x_in(x),
        .y_out(y_lut),
        .clk(clk),
        .reset(reset)
    );

   //clock generation
   initial begin
    clk = 0;
    forever begin #0.5 clk = ~clk; end
   end   
   

    initial begin
      $dumpfile("test_sigmoid.vcd");
      $dumpvars(0,test_sigmoid);

      $display("Begin Reset");
      reset = 0; 
      repeat(2)@(posedge clk);
      reset = 1;
      $display("End reset");

      $display("Testing Sigmoid Module:");
      $display("  x\t\tLUT\t\tPieceWise Linear");
      @(negedge clk)
      for (i = 0; i < 256; i = i + 1) begin
          x = (i - 128); // Test inputs: -128, -96, ..., 127
          @(negedge clk)
          $display("%d\t\t%d\t\t%d\t\t", x, y_lut, y_piecewise);
      end 
        $finish;
    end
endmodule

activation_functions/sigmoid/test_sigmoid.vcd
$date
	Thu Nov 28 23:22:31 2024
$end
$version
	Icarus Verilog
$end
$timescale
	1s
$end
$scope module test_sigmoid $end
$var wire 8 ! y_piecewise [7:0] $end
$var wire 8 " y_lut [7:0] $end
$var reg 1 # clk $end
$var reg 1 $ reset $end
$var reg 8 % x [7:0] $end
$var integer 32 & i [31:0] $end
$scope module instance_lut $end
$var wire 1 # clk $end
$var wire 1 $ reset $end
$var wire 8 ' x_in [7:0] $end
$var reg 8 ( y_out [7:0] $end
$upscope $end
$scope module instance_piecewise $end
$var wire 1 # clk $end
$var wire 1 $ reset $end
$var wire 8 ) x_in [7:0] $end
$var reg 8 * y_out [7:0] $end
$var reg 8 + y_s [7:0] $end
$upscope $end
$upscope $end
$enddefinitions $end
#0
$dumpvars
bx +
b0 *
bx )
b0 (
bx '
bx &
bx %
0$
0#
b0 "
b0 !
$end
#1
1#
#2
0#
#3
bx !
bx *
bx "
bx (
1$
1#
#4
b0 +
b10000000 %
b10000000 '
b10000000 )
b0 &
0#
#5
b101 "
b101 (
b0 !
b0 *
1#
#6
b101 +
b10000001 %
b10000001 '
b10000001 )
b1 &
0#
#7
b101 !
b101 *
1#
#8
b10000010 %
b10000010 '
b10000010 )
b10 &
0#
#9
1#
#10
b10000011 %
b10000011 '
b10000011 )
b11 &
0#
#11
1#
#12
b110 +
b10000100 %
b10000100 '
b10000100 )
b100 &
0#
#13
b110 !
b110 *
1#
#14
b10000101 %
b10000101 '
b10000101 )
b101 &
0#
#15
1#
#16
b10000110 %
b10000110 '
b10000110 )
b110 &
0#
#17
b110 "
b110 (
1#
#18
b10000111 %
b10000111 '
b10000111 )
b111 &
0#
#19
1#
#20
b111 +
b10001000 %
b10001000 '
b10001000 )
b1000 &
0#
#21
b111 !
b111 *
1#
#22
b10001001 %
b10001001 '
b10001001 )
b1001 &
0#
#23
1#
#24
b10001010 %
b10001010 '
b10001010 )
b1010 &
0#
#25
1#
#26
b10001011 %
b10001011 '
b10001011 )
b1011 &
0#
#27
1#
#28
b1000 +
b10001100 %
b10001100 '
b10001100 )
b1100 &
0#
#29
b111 "
b111 (
b1000 !
b1000 *
1#
#30
b10001101 %
b10001101 '
b10001101 )
b1101 &
0#
#31
1#
#32
b10001110 %
b10001110 '
b10001110 )
b1110 &
0#
#33
1#
#34
b10001111 %
b10001111 '
b10001111 )
b1111 &
0#
#35
1#
#36
b1001 +
b10010000 %
b10010000 '
b10010000 )
b10000 &
0#
#37
b1000 "
b1000 (
b1001 !
b1001 *
1#
#38
b10010001 %
b10010001 '
b10010001 )
b10001 &
0#
#39
1#
#40
b10010010 %
b10010010 '
b10010010 )
b10010 &
0#
#41
1#
#42
b10010011 %
b10010011 '
b10010011 )
b10011 &
0#
#43
1#
#44
b1010 +
b10010100 %
b10010100 '
b10010100 )
b10100 &
0#
#45
b1010 !
b1010 *
1#
#46
b10010101 %
b10010101 '
b10010101 )
b10101 &
0#
#47
b1001 "
b1001 (
1#
#48
b10010110 %
b10010110 '
b10010110 )
b10110 &
0#
#49
1#
#50
b10010111 %
b10010111 '
b10010111 )
b10111 &
0#
#51
1#
#52
b1011 +
b10011000 %
b10011000 '
b10011000 )
b11000 &
0#
#53
b1010 "
b1010 (
b1011 !
b1011 *
1#
#54
b10011001 %
b10011001 '
b10011001 )
b11001 &
0#
#55
1#
#56
b10011010 %
b10011010 '
b10011010 )
b11010 &
0#
#57
1#
#58
b10011011 %
b10011011 '
b10011011 )
b11011 &
0#
#59
1#
#60
b1100 +
b10011100 %
b10011100 '
b10011100 )
b11100 &
0#
#61
b1011 "
b1011 (
b1100 !
b1100 *
1#
#62
b10011101 %
b10011101 '
b10011101 )
b11101 &
0#
#63
1#
#64
b10011110 %
b10011110 '
b10011110 )
b11110 &
0#
#65
1#
#66
b10011111 %
b10011111 '
b10011111 )
b11111 &
0#
#67
b1100 "
b1100 (
1#
#68
b1101 +
b10100000 %
b10100000 '
b10100000 )
b100000 &
0#
#69
b1101 !
b1101 *
1#
#70
b10100001 %
b10100001 '
b10100001 )
b100001 &
0#
#71
b1101 "
b1101 (
1#
#72
b10100010 %
b10100010 '
b10100010 )
b100010 &
0#
#73
1#
#74
b10100011 %
b10100011 '
b10100011 )
b100011 &
0#
#75
1#
#76
b1110 +
b10100100 %
b10100100 '
b10100100 )
b100100 &
0#
#77
b1110 "
b1110 (
b1110 !
b1110 *
1#
#78
b10100101 %
b10100101 '
b10100101 )
b100101 &
0#
#79
1#
#80
b10100110 %
b10100110 '
b10100110 )
b100110 &
0#
#81
b1111 "
b1111 (
1#
#82
b10100111 %
b10100111 '
b10100111 )
b100111 &
0#
#83
1#
#84
b1111 +
b10101000 %
b10101000 '
b10101000 )
b101000 &
0#
#85
b1111 !
b1111 *
1#
#86
b10101001 %
b10101001 '
b10101001 )
b101001 &
0#
#87
b10000 "
b10000 (
1#
#88
b10101010 %
b10101010 '
b10101010 )
b101010 &
0#
#89
1#
#90
b10101011 %
b10101011 '
b10101011 )
b101011 &
0#
#91
b10001 "
b10001 (
1#
#92
b10000 +
b10101100 %
b10101100 '
b10101100 )
b101100 &
0#
#93
b10000 !
b10000 *
1#
#94
b10101101 %
b10101101 '
b10101101 )
b101101 &
0#
#95
b10010 "
b10010 (
1#
#96
b10101110 %
b10101110 '
b10101110 )
b101110 &
0#
#97
1#
#98
b10101111 %
b10101111 '
b10101111 )
b101111 &
0#
#99
b10011 "
b10011 (
1#
#100
b10001 +
b10110000 %
b10110000 '
b10110000 )
b110000 &
0#
#101
b10001 !
b10001 *
1#
#102
b10110001 %
b10110001 '
b10110001 )
b110001 &
0#
#103
b10100 "
b10100 (
1#
#104
b10110010 %
b10110010 '
b10110010 )
b110010 &
0#
#105
b10101 "
b10101 (
1#
#106
b10110011 %
b10110011 '
b10110011 )
b110011 &
0#
#107
1#
#108
b10010 +
b10110100 %
b10110100 '
b10110100 )
b110100 &
0#
#109
b10110 "
b10110 (
b10010 !
b10010 *
1#
#110
b10110101 %
b10110101 '
b10110101 )
b110101 &
0#
#111
1#
#112
b10110110 %
b10110110 '
b10110110 )
b110110 &
0#
#113
b10111 "
b10111 (
1#
#114
b10110111 %
b10110111 '
b10110111 )
b110111 &
0#
#115
b11000 "
b11000 (
1#
#116
b10011 +
b10111000 %
b10111000 '
b10111000 )
b111000 &
0#
#117
b10011 !
b10011 *
1#
#118
b10111001 %
b10111001 '
b10111001 )
b111001 &
0#
#119
b11001 "
b11001 (
1#
#120
b10111010 %
b10111010 '
b10111010 )
b111010 &
0#
#121
b11010 "
b11010 (
1#
#122
b10111011 %
b10111011 '
b10111011 )
b111011 &
0#
#123
b11011 "
b11011 (
1#
#124
b10100 +
b10111100 %
b10111100 '
b10111100 )
b111100 &
0#
#125
b10100 !
b10100 *
1#
#126
b10111101 %
b10111101 '
b10111101 )
b111101 &
0#
#127
b11100 "
b11100 (
1#
#128
b10111110 %
b10111110 '
b10111110 )
b111110 &
0#
#129
b11101 "
b11101 (
1#
#130
b10111111 %
b10111111 '
b10111111 )
b111111 &
0#
#131
b11110 "
b11110 (
1#
#132
b100000 +
b11000000 %
b11000000 '
b11000000 )
b1000000 &
0#
#133
b11111 "
b11111 (
b100000 !
b100000 *
1#
#134
b11000001 %
b11000001 '
b11000001 )
b1000001 &
0#
#135
1#
#136
b100001 +
b11000010 %
b11000010 '
b11000010 )
b1000010 &
0#
#137
b100000 "
b100000 (
b100001 !
b100001 *
1#
#138
b11000011 %
b11000011 '
b11000011 )
b1000011 &
0#
#139
b100001 "
b100001 (
1#
#140
b100010 +
b11000100 %
b11000100 '
b11000100 )
b1000100 &
0#
#141
b100010 "
b100010 (
b100010 !
b100010 *
1#
#142
b11000101 %
b11000101 '
b11000101 )
b1000101 &
0#
#143
b100011 "
b100011 (
1#
#144
b100011 +
b11000110 %
b11000110 '
b11000110 )
b1000110 &
0#
#145
b100100 "
b100100 (
b100011 !
b100011 *
1#
#146
b11000111 %
b11000111 '
b11000111 )
b1000111 &
0#
#147
b100101 "
b100101 (
1#
#148
b100100 +
b11001000 %
b11001000 '
b11001000 )
b1001000 &
0#
#149
b100110 "
b100110 (
b100100 !
b100100 *
1#
#150
b11001001 %
b11001001 '
b11001001 )
b1001001 &
0#
#151
b100111 "
b100111 (
1#
#152
b100101 +
b11001010 %
b11001010 '
b11001010 )
b1001010 &
0#
#153
b101000 "
b101000 (
b100101 !
b100101 *
1#
#154
b11001011 %
b11001011 '
b11001011 )
b1001011 &
0#
#155
b101001 "
b101001 (
1#
#156
b100110 +
b11001100 %
b11001100 '
b11001100 )
b1001100 &
0#
#157
b101010 "
b101010 (
b100110 !
b100110 *
1#
#158
b11001101 %
b11001101 '
b11001101 )
b1001101 &
0#
#159
b101011 "
b101011 (
1#
#160
b100111 +
b11001110 %
b11001110 '
b11001110 )
b1001110 &
0#
#161
b101100 "
b101100 (
b100111 !
b100111 *
1#
#162
b11001111 %
b11001111 '
b11001111 )
b1001111 &
0#
#163
b101110 "
b101110 (
1#
#164
b101000 +
b11010000 %
b11010000 '
b11010000 )
b1010000 &
0#
#165
b101111 "
b101111 (
b101000 !
b101000 *
1#
#166
b11010001 %
b11010001 '
b11010001 )
b1010001 &
0#
#167
b110000 "
b110000 (
1#
#168
b101001 +
b11010010 %
b11010010 '
b11010010 )
b1010010 &
0#
#169
b110001 "
b110001 (
b101001 !
b101001 *
1#
#170
b11010011 %
b11010011 '
b11010011 )
b1010011 &
0#
#171
b110010 "
b110010 (
1#
#172
b101010 +
b11010100 %
b11010100 '
b11010100 )
b1010100 &
0#
#173
b110100 "
b110100 (
b101010 !
b101010 *
1#
#174
b11010101 %
b11010101 '
b11010101 )
b1010101 &
0#
#175
b110101 "
b110101 (
1#
#176
b101011 +
b11010110 %
b11010110 '
b11010110 )
b1010110 &
0#
#177
b110110 "
b110110 (
b101011 !
b101011 *
1#
#178
b11010111 %
b11010111 '
b11010111 )
b1010111 &
0#
#179
b111000 "
b111000 (
1#
#180
b101100 +
b11011000 %
b11011000 '
b11011000 )
b1011000 &
0#
#181
b111001 "
b111001 (
b101100 !
b101100 *
1#
#182
b11011001 %
b11011001 '
b11011001 )
b1011001 &
0#
#183
b111010 "
b111010 (
1#
#184
b101101 +
b11011010 %
b11011010 '
b11011010 )
b1011010 &
0#
#185
b111100 "
b111100 (
b101101 !
b101101 *
1#
#186
b11011011 %
b11011011 '
b11011011 )
b1011011 &
0#
#187
b111101 "
b111101 (
1#
#188
b101110 +
b11011100 %
b11011100 '
b11011100 )
b1011100 &
0#
#189
b111111 "
b111111 (
b101110 !
b101110 *
1#
#190
b11011101 %
b11011101 '
b11011101 )
b1011101 &
0#
#191
b1000000 "
b1000000 (
1#
#192
b101111 +
b11011110 %
b11011110 '
b11011110 )
b1011110 &
0#
#193
b1000010 "
b1000010 (
b101111 !
b101111 *
1#
#194
b11011111 %
b11011111 '
b11011111 )
b1011111 &
0#
#195
b1000011 "
b1000011 (
1#
#196
b1000101 +
b11100000 %
b11100000 '
b11100000 )
b1100000 &
0#
#197
b1000101 "
b1000101 (
b1000101 !
b1000101 *
1#
#198
b1000111 +
b11100001 %
b11100001 '
b11100001 )
b1100001 &
0#
#199
b1000111 !
b1000111 *
b1000110 "
b1000110 (
1#
#200
b1001001 +
b11100010 %
b11100010 '
b11100010 )
b1100010 &
0#
#201
b1001000 "
b1001000 (
b1001001 !
b1001001 *
1#
#202
b1001011 +
b11100011 %
b11100011 '
b11100011 )
b1100011 &
0#
#203
b1001011 !
b1001011 *
b1001010 "
b1001010 (
1#
#204
b1001101 +
b11100100 %
b11100100 '
b11100100 )
b1100100 &
0#
#205
b1001011 "
b1001011 (
b1001101 !
b1001101 *
1#
#206
b1001111 +
b11100101 %
b11100101 '
b11100101 )
b1100101 &
0#
#207
b1001111 !
b1001111 *
b1001101 "
b1001101 (
1#
#208
b1010001 +
b11100110 %
b11100110 '
b11100110 )
b1100110 &
0#
#209
b1001111 "
b1001111 (
b1010001 !
b1010001 *
1#
#210
b1010011 +
b11100111 %
b11100111 '
b11100111 )
b1100111 &
0#
#211
b1010011 !
b1010011 *
b1010000 "
b1010000 (
1#
#212
b1010101 +
b11101000 %
b11101000 '
b11101000 )
b1101000 &
0#
#213
b1010010 "
b1010010 (
b1010101 !
b1010101 *
1#
#214
b1010111 +
b11101001 %
b11101001 '
b11101001 )
b1101001 &
0#
#215
b1010111 !
b1010111 *
b1010100 "
b1010100 (
1#
#216
b1011001 +
b11101010 %
b11101010 '
b11101010 )
b1101010 &
0#
#217
b1010110 "
b1010110 (
b1011001 !
b1011001 *
1#
#218
b1011011 +
b11101011 %
b11101011 '
b11101011 )
b1101011 &
0#
#219
b1011011 !
b1011011 *
b1010111 "
b1010111 (
1#
#220
b1011101 +
b11101100 %
b11101100 '
b11101100 )
b1101100 &
0#
#221
b1011001 "
b1011001 (
b1011101 !
b1011101 *
1#
#222
b1011111 +
b11101101 %
b11101101 '
b11101101 )
b1101101 &
0#
#223
b1011111 !
b1011111 *
b1011011 "
b1011011 (
1#
#224
b1100001 +
b11101110 %
b11101110 '
b11101110 )
b1101110 &
0#
#225
b1011101 "
b1011101 (
b1100001 !
b1100001 *
1#
#226
b1100011 +
b11101111 %
b11101111 '
b11101111 )
b1101111 &
0#
#227
b1100011 !
b1100011 *
b1011111 "
b1011111 (
1#
#228
b1100101 +
b11110000 %
b11110000 '
b11110000 )
b1110000 &
0#
#229
b1100001 "
b1100001 (
b1100101 !
b1100101 *
1#
#230
b1100111 +
b11110001 %
b11110001 '
b11110001 )
b1110001 &
0#
#231
b1100111 !
b1100111 *
b1100011 "
b1100011 (
1#
#232
b1101001 +
b11110010 %
b11110010 '
b11110010 )
b1110010 &
0#
#233
b1100100 "
b1100100 (
b1101001 !
b1101001 *
1#
#234
b1101011 +
b11110011 %
b11110011 '
b11110011 )
b1110011 &
0#
#235
b1101011 !
b1101011 *
b1100110 "
b1100110 (
1#
#236
b1101101 +
b11110100 %
b11110100 '
b11110100 )
b1110100 &
0#
#237
b1101000 "
b1101000 (
b1101101 !
b1101101 *
1#
#238
b1101111 +
b11110101 %
b11110101 '
b11110101 )
b1110101 &
0#
#239
b1101111 !
b1101111 *
b1101010 "
b1101010 (
1#
#240
b1110001 +
b11110110 %
b11110110 '
b11110110 )
b1110110 &
0#
#241
b1101100 "
b1101100 (
b1110001 !
b1110001 *
1#
#242
b1110011 +
b11110111 %
b11110111 '
b11110111 )
b1110111 &
0#
#243
b1110011 !
b1110011 *
b1101110 "
b1101110 (
1#
#244
b1110101 +
b11111000 %
b11111000 '
b11111000 )
b1111000 &
0#
#245
b1110000 "
b1110000 (
b1110101 !
b1110101 *
1#
#246
b1110111 +
b11111001 %
b11111001 '
b11111001 )
b1111001 &
0#
#247
b1110111 !
b1110111 *
b1110010 "
b1110010 (
1#
#248
b1111001 +
b11111010 %
b11111010 '
b11111010 )
b1111010 &
0#
#249
b1110100 "
b1110100 (
b1111001 !
b1111001 *
1#
#250
b1111011 +
b11111011 %
b11111011 '
b11111011 )
b1111011 &
0#
#251
b1111011 !
b1111011 *
b1110110 "
b1110110 (
1#
#252
b1111101 +
b11111100 %
b11111100 '
b11111100 )
b1111100 &
0#
#253
b1111000 "
b1111000 (
b1111101 !
b1111101 *
1#
#254
b1111111 +
b11111101 %
b11111101 '
b11111101 )
b1111101 &
0#
#255
b1111111 !
b1111111 *
b1111010 "
b1111010 (
1#
#256
b10000001 +
b11111110 %
b11111110 '
b11111110 )
b1111110 &
0#
#257
b1111100 "
b1111100 (
b10000001 !
b10000001 *
1#
#258
b10000011 +
b11111111 %
b11111111 '
b11111111 )
b1111111 &
0#
#259
b10000011 !
b10000011 *
b1111110 "
b1111110 (
1#
#260
b10000101 +
b0 %
b0 '
b0 )
b10000000 &
0#
#261
b10000000 "
b10000000 (
b10000101 !
b10000101 *
1#
#262
b10000111 +
b1 %
b1 '
b1 )
b10000001 &
0#
#263
b10000111 !
b10000111 *
b10000010 "
b10000010 (
1#
#264
b10001001 +
b10 %
b10 '
b10 )
b10000010 &
0#
#265
b10000100 "
b10000100 (
b10001001 !
b10001001 *
1#
#266
b10001011 +
b11 %
b11 '
b11 )
b10000011 &
0#
#267
b10001011 !
b10001011 *
b10000110 "
b10000110 (
1#
#268
b10001101 +
b100 %
b100 '
b100 )
b10000100 &
0#
#269
b10001000 "
b10001000 (
b10001101 !
b10001101 *
1#
#270
b10001111 +
b101 %
b101 '
b101 )
b10000101 &
0#
#271
b10001111 !
b10001111 *
b10001010 "
b10001010 (
1#
#272
b10010001 +
b110 %
b110 '
b110 )
b10000110 &
0#
#273
b10001100 "
b10001100 (
b10010001 !
b10010001 *
1#
#274
b10010011 +
b111 %
b111 '
b111 )
b10000111 &
0#
#275
b10010011 !
b10010011 *
b10001110 "
b10001110 (
1#
#276
b10010101 +
b1000 %
b1000 '
b1000 )
b10001000 &
0#
#277
b10010000 "
b10010000 (
b10010101 !
b10010101 *
1#
#278
b10010111 +
b1001 %
b1001 '
b1001 )
b10001001 &
0#
#279
b10010111 !
b10010111 *
b10010010 "
b10010010 (
1#
#280
b10011001 +
b1010 %
b1010 '
b1010 )
b10001010 &
0#
#281
b10010100 "
b10010100 (
b10011001 !
b10011001 *
1#
#282
b10011011 +
b1011 %
b1011 '
b1011 )
b10001011 &
0#
#283
b10011011 !
b10011011 *
b10010110 "
b10010110 (
1#
#284
b10011101 +
b1100 %
b1100 '
b1100 )
b10001100 &
0#
#285
b10011000 "
b10011000 (
b10011101 !
b10011101 *
1#
#286
b10011111 +
b1101 %
b1101 '
b1101 )
b10001101 &
0#
#287
b10011111 !
b10011111 *
b10011010 "
b10011010 (
1#
#288
b10100001 +
b1110 %
b1110 '
b1110 )
b10001110 &
0#
#289
b10011100 "
b10011100 (
b10100001 !
b10100001 *
1#
#290
b10100011 +
b1111 %
b1111 '
b1111 )
b10001111 &
0#
#291
b10100011 !
b10100011 *
b10011101 "
b10011101 (
1#
#292
b10100101 +
b10000 %
b10000 '
b10000 )
b10010000 &
0#
#293
b10011111 "
b10011111 (
b10100101 !
b10100101 *
1#
#294
b10100111 +
b10001 %
b10001 '
b10001 )
b10010001 &
0#
#295
b10100111 !
b10100111 *
b10100001 "
b10100001 (
1#
#296
b10101001 +
b10010 %
b10010 '
b10010 )
b10010010 &
0#
#297
b10100011 "
b10100011 (
b10101001 !
b10101001 *
1#
#298
b10101011 +
b10011 %
b10011 '
b10011 )
b10010011 &
0#
#299
b10101011 !
b10101011 *
b10100101 "
b10100101 (
1#
#300
b10101101 +
b10100 %
b10100 '
b10100 )
b10010100 &
0#
#301
b10100111 "
b10100111 (
b10101101 !
b10101101 *
1#
#302
b10101111 +
b10101 %
b10101 '
b10101 )
b10010101 &
0#
#303
b10101111 !
b10101111 *
b10101001 "
b10101001 (
1#
#304
b10110001 +
b10110 %
b10110 '
b10110 )
b10010110 &
0#
#305
b10101010 "
b10101010 (
b10110001 !
b10110001 *
1#
#306
b10110011 +
b10111 %
b10111 '
b10111 )
b10010111 &
0#
#307
b10110011 !
b10110011 *
b10101100 "
b10101100 (
1#
#308
b10110101 +
b11000 %
b11000 '
b11000 )
b10011000 &
0#
#309
b10101110 "
b10101110 (
b10110101 !
b10110101 *
1#
#310
b10110111 +
b11001 %
b11001 '
b11001 )
b10011001 &
0#
#311
b10110111 !
b10110111 *
b10110000 "
b10110000 (
1#
#312
b10111001 +
b11010 %
b11010 '
b11010 )
b10011010 &
0#
#313
b10110001 "
b10110001 (
b10111001 !
b10111001 *
1#
#314
b10111011 +
b11011 %
b11011 '
b11011 )
b10011011 &
0#
#315
b10111011 !
b10111011 *
b10110011 "
b10110011 (
1#
#316
b10111101 +
b11100 %
b11100 '
b11100 )
b10011100 &
0#
#317
b10110101 "
b10110101 (
b10111101 !
b10111101 *
1#
#318
b10111111 +
b11101 %
b11101 '
b11101 )
b10011101 &
0#
#319
b10111111 !
b10111111 *
b10110110 "
b10110110 (
1#
