activation_functions/sigmoid/polynomial_approximation.v
module sigmoid_poly (
    input clk,
    input reset,
    input signed [7:0] x_in,  // Q3.5 input (-4 to 4)
    output reg [7:0] y_out    // Q0.8 output (0 to 1)
);

    // Internal registers for intermediate calculations
    reg signed [15:0] x_scaled;      // Q3.13 (scaled input)
    reg signed [15:0] x_squared;     // Q6.10 (x^2 intermediate)
    reg signed [15:0] x_cubed;       // Q9.7 (x^3 intermediate)
    reg signed [15:0] poly_result;   // Q0.16 (polynomial result)

    //combinational output
    reg[7:0] y_s;

    always @(*) begin
       // Scale input to Q3.13 (shift left by 8)
       x_scaled = {x_in, 8'b0};

       // Compute x^2 in Q6.10
       x_squared = (x_scaled * x_scaled) >>> 16;

       // Compute x^3 in Q9.7
       x_cubed = (x_squared * x_scaled) >>> 16;

       // Evaluate polynomial in Q0.16
       poly_result = 16'h2000 + (x_scaled >>> 2) - (x_cubed >>> 5);

       // Convert to Q0.8 for output (truncate)
       y_s = poly_result[15:8];
    end

    always @(posedge clk or negedge reset) begin
      if(~reset) begin
        y_out <= 0;
      end
      else begin
        y_out <= y_s;
      end
    end 

endmodule

activation_functions/sigmoid/lut_based.v
module sigmoid_lut (
    input clk,
    input reset,
    input signed [7:0] x_in,  // Q3.5 input (-4 to 4)
    output reg [7:0] y_out    // Q0.8 output (0 to 1)
);

     reg [7:0] LUT [255:0];

    //registering output
    always @(posedge clk or negedge reset) begin
      if(~reset) begin
        y_out <= 0;
      end
      else begin
        y_out <= LUT['sd128+x_in];
      end
    end 


    always @(posedge clk or negedge reset) begin
      LUT[0]  <= 5; LUT[1]  <= 5; LUT[2]  <= 5; LUT[3]  <= 5; LUT[4]  <= 5; LUT[5]  <= 5;
      LUT[6]  <= 6; LUT[7]  <= 6; LUT[8]  <= 6; LUT[9]  <= 6; LUT[10] <= 6; LUT[11] <= 6;
      LUT[12] <= 7; LUT[13] <= 7; LUT[14] <= 7; LUT[15] <= 7; LUT[16] <= 8; LUT[17] <= 8;
      LUT[18] <= 8; LUT[19] <= 8; LUT[20] <= 8; LUT[21] <= 9; LUT[22] <= 9; LUT[23] <= 9;
      LUT[24] <= 10; LUT[25] <= 10; LUT[26] <= 10; LUT[27] <= 10; LUT[28] <= 11; LUT[29] <= 11;
      LUT[30] <= 11; LUT[31] <= 12; LUT[32] <= 12; LUT[33] <= 13; LUT[34] <= 13; LUT[35] <= 13;
      LUT[36] <= 14; LUT[37] <= 14; LUT[38] <= 15; LUT[39] <= 15; LUT[40] <= 15; LUT[41] <= 16;
      LUT[42] <= 16; LUT[43] <= 17; LUT[44] <= 17; LUT[45] <= 18; LUT[46] <= 18; LUT[47] <= 19;
      LUT[48] <= 19; LUT[49] <= 20; LUT[50] <= 21; LUT[51] <= 21; LUT[52] <= 22; LUT[53] <= 22;
      LUT[54] <= 23; LUT[55] <= 24; LUT[56] <= 24; LUT[57] <= 25; LUT[58] <= 26; LUT[59] <= 27;
      LUT[60] <= 27; LUT[61] <= 28; LUT[62] <= 29; LUT[63] <= 30; LUT[64] <= 31; LUT[65] <= 31;
      LUT[66] <= 32; LUT[67] <= 33; LUT[68] <= 34; LUT[69] <= 35; LUT[70] <= 36; LUT[71] <= 37;
      LUT[72] <= 38; LUT[73] <= 39; LUT[74] <= 40; LUT[75] <= 41; LUT[76] <= 42; LUT[77] <= 43;
      LUT[78] <= 44; LUT[79] <= 46; LUT[80] <= 47; LUT[81] <= 48; LUT[82] <= 49; LUT[83] <= 50;
      LUT[84] <= 52; LUT[85] <= 53; LUT[86] <= 54; LUT[87] <= 56; LUT[88] <= 57; LUT[89] <= 58;
      LUT[90] <= 60; LUT[91] <= 61; LUT[92] <= 63; LUT[93] <= 64; LUT[94] <= 66; LUT[95] <= 67;
      LUT[96] <= 69; LUT[97] <= 70; LUT[98] <= 72; LUT[99] <= 74; LUT[100] <= 75; LUT[101] <= 77;
      LUT[102] <= 79; LUT[103] <= 80; LUT[104] <= 82; LUT[105] <= 84; LUT[106] <= 86; LUT[107] <= 87;
      LUT[108] <= 89; LUT[109] <= 91; LUT[110] <= 93; LUT[111] <= 95; LUT[112] <= 97; LUT[113] <= 99;
      LUT[114] <= 100; LUT[115] <= 102; LUT[116] <= 104; LUT[117] <= 106; LUT[118] <= 108; LUT[119] <= 110;
      LUT[120] <= 112; LUT[121] <= 114; LUT[122] <= 116; LUT[123] <= 118; LUT[124] <= 120; LUT[125] <= 122;
      LUT[126] <= 124; LUT[127] <= 126; LUT[128] <= 128; LUT[129] <= 130; LUT[130] <= 132; LUT[131] <= 134;
      LUT[132] <= 136; LUT[133] <= 138; LUT[134] <= 140; LUT[135] <= 142; LUT[136] <= 144; LUT[137] <= 146;
      LUT[138] <= 148; LUT[139] <= 150; LUT[140] <= 152; LUT[141] <= 154; LUT[142] <= 156; LUT[143] <= 157;
      LUT[144] <= 159; LUT[145] <= 161; LUT[146] <= 163; LUT[147] <= 165; LUT[148] <= 167; LUT[149] <= 169;
      LUT[150] <= 170; LUT[151] <= 172; LUT[152] <= 174; LUT[153] <= 176; LUT[154] <= 177; LUT[155] <= 179;
      LUT[156] <= 181; LUT[157] <= 182; LUT[158] <= 184; LUT[159] <= 186; LUT[160] <= 187; LUT[161] <= 189;
      LUT[162] <= 190; LUT[163] <= 192; LUT[164] <= 193; LUT[165] <= 195; LUT[166] <= 196; LUT[167] <= 198;
      LUT[168] <= 199; LUT[169] <= 200; LUT[170] <= 202; LUT[171] <= 203; LUT[172] <= 204; LUT[173] <= 206;
      LUT[174] <= 207; LUT[175] <= 208; LUT[176] <= 209; LUT[177] <= 210; LUT[178] <= 212; LUT[179] <= 213;
      LUT[180] <= 214; LUT[181] <= 215; LUT[182] <= 216; LUT[183] <= 217; LUT[184] <= 218; LUT[185] <= 219;
      LUT[186] <= 220; LUT[187] <= 221; LUT[188] <= 222; LUT[189] <= 223; LUT[190] <= 224; LUT[191] <= 225;
      LUT[192] <= 225; LUT[193] <= 226; LUT[194] <= 227; LUT[195] <= 228; LUT[196] <= 229; LUT[197] <= 229;
      LUT[198] <= 230; LUT[199] <= 231; LUT[200] <= 232; LUT[201] <= 232; LUT[202] <= 233; LUT[203] <= 234;
      LUT[204] <= 234; LUT[205] <= 235; LUT[206] <= 235; LUT[207] <= 236; LUT[208] <= 237; LUT[209] <= 237;
      LUT[210] <= 238; LUT[211] <= 238; LUT[212] <= 239; LUT[213] <= 239; LUT[214] <= 240; LUT[215] <= 240;
      LUT[216] <= 241; LUT[217] <= 241; LUT[218] <= 241; LUT[219] <= 242; LUT[220] <= 242; LUT[221] <= 243;
      LUT[222] <= 243; LUT[223] <= 243; LUT[224] <= 244; LUT[225] <= 244; LUT[226] <= 245; LUT[227] <= 245;
      LUT[228] <= 245; LUT[229] <= 246; LUT[230] <= 246; LUT[231] <= 246; LUT[232] <= 246; LUT[233] <= 247;
      LUT[234] <= 247; LUT[235] <= 247; LUT[236] <= 248; LUT[237] <= 248; LUT[238] <= 248; LUT[239] <= 248;
      LUT[240] <= 248; LUT[241] <= 249; LUT[242] <= 249; LUT[243] <= 249; LUT[244] <= 250; LUT[245] <= 250;
      LUT[246] <= 250; LUT[247] <= 250; LUT[248] <= 250; LUT[249] <= 250; LUT[250] <= 251; LUT[251] <= 251;
      LUT[252] <= 251; LUT[253] <= 251; LUT[254] <= 251; LUT[255] <= 251;
    end

endmodule

activation_functions/sigmoid/piecewise_linear.v
module sigmoid_piecewise (
    input clk,
    input reset,
    input signed [7:0] x_in,  // Q3.5 input (-4 to 4)
    output reg [7:0] y_out    // Q0.8 output (0 to 1)
);

    // Precomputed constants (Q0.8 format for slopes and offsets)
    // Now the slopes are scaled as powers of 2 to avoid multiplication
    // Each slope is represented as shift constants

    // Slope for -4 to -2 (a = 0.03125 -> shift by 5)
    localparam signed [7:0] SHIFT_1 = 1;    
    localparam signed [7:0] OFFSET_1 = 8'd5;  // Offset for -4 to -2 (b = 0.0 -> Q0.8 = 5)

    // Slope for -2 to -1 (a = 0.125 -> shift by 3)
    localparam signed [7:0] SHIFT_2 = 0;    
    localparam signed [7:0] OFFSET_2 = 8'd32;  // Offset for -2 to -1 (b = 0.125 -> Q0.8 = 32)

    // Slope for -1 to 1 (a = 0.25 -> shift by 2)
    localparam signed [7:0] SHIFT_3 = 1;   
    localparam signed [7:0] OFFSET_3 = 8'd69;  // Offset for -1 to 1 (b = 0.375 -> Q0.8 = 96)

    // Slope for 1 to 2 (a = 0.125 -> shift by 3)
    localparam signed [7:0] SHIFT_4 = 0;    
    localparam signed [7:0] OFFSET_4 = 8'd187; // Offset for 1 to 2 (b = 0.625 -> Q0.8 = 160)

    // Slope for 2 to 4 (a = 0.03125 -> shift by 5)
    localparam signed [7:0] SHIFT_5 = 1;    
    localparam signed [7:0] OFFSET_5 = 8'd225; // Offset for 2 to 4 (b = 0.75 -> Q0.8 = 192)
   
    reg [7:0] y_s;

    //registering output
    always @(posedge clk or negedge reset) begin
      if(~reset) begin
        y_out <= 0;
      end
      else begin
        y_out <= y_s;
      end
    end 

    always @(*) begin
        if (x_in <= -128) begin
            y_s = 8'd0;  // Output saturates to 0 for x <= -4
        end else if (x_in >= 127) begin
            y_s = 8'd255; // Output saturates to 1 for x >= 4
        end else if (x_in < -64) begin  // Segment 1: -4 to -2
            y_s = ((x_in + 128) >>> SHIFT_1) + OFFSET_1;
        end else if (x_in < -32) begin  // Segment 2: -2 to -1
            y_s = ((x_in + 64) >>> SHIFT_2) + OFFSET_2;
        end else if (x_in < 32) begin  // Segment 3: -1 to 1
            y_s = ((x_in + 32) <<< SHIFT_3) + OFFSET_3;
        end else if (x_in < 64) begin  // Segment 4: 1 to 2
            y_s = ((x_in - 32) >>> SHIFT_4) + OFFSET_4;
        end else begin  // Segment 5: 2 to 4
            y_s = ((x_in - 64) >>> SHIFT_5) + OFFSET_5;
        end
    end
endmodule

activation_functions/sigmoid/sigmoid_tb.v
module test_sigmoid;
    reg signed [7:0] x;
    wire [7:0] y_piecewise, y_lut, y_poly;
    integer i;
    reg reset;
    reg clk;

    sigmoid_piecewise instance_piecewise (
        .x_in(x),
        .y_out(y_piecewise),
        .clk(clk),
        .reset(reset)
    );

    sigmoid_lut instance_lut (
        .x_in(x),
        .y_out(y_lut),
        .clk(clk),
        .reset(reset)
    );

    sigmoid_poly instance_poly (
        .x_in(x),
        .y_out(y_poly),
        .clk(clk),
        .reset(reset)
    );

   //clock generation
   initial begin
    clk = 0;
    forever begin #0.5 clk = ~clk; end
   end   
   

    initial begin
      $dumpfile("test_sigmoid.vcd");
      $dumpvars(0,test_sigmoid);

      $display("Begin Reset");
      reset = 0; 
      repeat(2)@(posedge clk);
      reset = 1;
      $display("End reset");

      $display("Testing Sigmoid Module:");
      $display("  x\t\tLUT\t\tPieceWise Linear\t\t");
      @(negedge clk)
      for (i = 0; i < 256; i = i + 1) begin
          x = (i - 128); // Test inputs: -128, -96, ..., 127
          @(negedge clk)
          $display("%d\t\t%d\t\t%d\t\t", x, y_lut, y_piecewise);
      end 
        $finish;
    end
endmodule

activation_functions/sigmoid/test_sigmoid.vcd
$date
	Tue Dec  3 22:55:31 2024
$end
$version
	Icarus Verilog
$end
$timescale
	1s
$end
$scope module test_sigmoid $end
$var wire 8 ! y_poly [7:0] $end
$var wire 8 " y_piecewise [7:0] $end
$var wire 8 # y_lut [7:0] $end
$var reg 1 $ clk $end
$var reg 1 % reset $end
$var reg 8 & x [7:0] $end
$var integer 32 ' i [31:0] $end
$scope module instance_lut $end
$var wire 1 $ clk $end
$var wire 1 % reset $end
$var wire 8 ( x_in [7:0] $end
$var reg 8 ) y_out [7:0] $end
$upscope $end
$scope module instance_piecewise $end
$var wire 1 $ clk $end
$var wire 1 % reset $end
$var wire 8 * x_in [7:0] $end
$var reg 8 + y_out [7:0] $end
$var reg 8 , y_s [7:0] $end
$upscope $end
$scope module instance_poly $end
$var wire 1 $ clk $end
$var wire 1 % reset $end
$var wire 8 - x_in [7:0] $end
$var reg 16 . poly_result [15:0] $end
$var reg 16 / x_cubed [15:0] $end
$var reg 16 0 x_scaled [15:0] $end
$var reg 16 1 x_squared [15:0] $end
$var reg 8 2 y_out [7:0] $end
$var reg 8 3 y_s [7:0] $end
$upscope $end
$upscope $end
$enddefinitions $end
#0
$dumpvars
bx 3
b0 2
bx 1
bx 0
bx /
bx .
bx -
bx ,
b0 +
bx *
b0 )
bx (
bx '
bx &
0%
0$
b0 #
b0 "
b0 !
$end
#1
1$
#2
0$
#3
bx "
bx +
bx #
bx )
bx !
bx 2
1%
1$
#4
b0 ,
b1000000 3
b100000000000000 .
b0 /
b0 1
b1000000000000000 0
b10000000 &
b10000000 (
b10000000 *
b10000000 -
b0 '
0$
#5
b1000000 !
b1000000 2
b101 #
b101 )
b0 "
b0 +
1$
#6
b101 ,
b100000001000000 .
b1000000100000000 0
b10000001 &
b10000001 (
b10000001 *
b10000001 -
b1 '
0$
#7
b101 "
b101 +
1$
#8
b110 ,
b100000010000000 .
b1000001000000000 0
b10000010 &
b10000010 (
b10000010 *
b10000010 -
b10 '
0$
#9
b110 "
b110 +
1$
#10
b100000011000000 .
b1000001100000000 0
b10000011 &
b10000011 (
b10000011 *
b10000011 -
b11 '
0$
#11
1$
#12
b111 ,
b1000001 3
b100000100000000 .
b1000010000000000 0
b10000100 &
b10000100 (
b10000100 *
b10000100 -
b100 '
0$
#13
b1000001 !
b1000001 2
b111 "
b111 +
1$
#14
b100000101000000 .
b1000010100000000 0
b10000101 &
b10000101 (
b10000101 *
b10000101 -
b101 '
0$
#15
1$
#16
b1000 ,
b100000110000000 .
b1000011000000000 0
b10000110 &
b10000110 (
b10000110 *
b10000110 -
b110 '
0$
#17
b110 #
b110 )
b1000 "
b1000 +
1$
#18
b100000111000000 .
b1000011100000000 0
b10000111 &
b10000111 (
b10000111 *
b10000111 -
b111 '
0$
#19
1$
#20
b1001 ,
b1000010 3
b100001000000000 .
b1000100000000000 0
b10001000 &
b10001000 (
b10001000 *
b10001000 -
b1000 '
0$
#21
b1000010 !
b1000010 2
b1001 "
b1001 +
1$
#22
b100001001000000 .
b1000100100000000 0
b10001001 &
b10001001 (
b10001001 *
b10001001 -
b1001 '
0$
#23
1$
#24
b1010 ,
b100001010000000 .
b1000101000000000 0
b10001010 &
b10001010 (
b10001010 *
b10001010 -
b1010 '
0$
#25
b1010 "
b1010 +
1$
#26
b100001011000000 .
b1000101100000000 0
b10001011 &
b10001011 (
b10001011 *
b10001011 -
b1011 '
0$
#27
1$
#28
b1011 ,
b1000011 3
b100001100000000 .
b1000110000000000 0
b10001100 &
b10001100 (
b10001100 *
b10001100 -
b1100 '
0$
#29
b1000011 !
b1000011 2
b111 #
b111 )
b1011 "
b1011 +
1$
#30
b100001101000000 .
b1000110100000000 0
b10001101 &
b10001101 (
b10001101 *
b10001101 -
b1101 '
0$
#31
1$
#32
b1100 ,
b100001110000000 .
b1000111000000000 0
b10001110 &
b10001110 (
b10001110 *
b10001110 -
b1110 '
0$
#33
b1100 "
b1100 +
1$
#34
b100001111000000 .
b1000111100000000 0
b10001111 &
b10001111 (
b10001111 *
b10001111 -
b1111 '
0$
#35
1$
#36
b1101 ,
b1000100 3
b100010000000000 .
b1001000000000000 0
b10010000 &
b10010000 (
b10010000 *
b10010000 -
b10000 '
0$
#37
b1000100 !
b1000100 2
b1000 #
b1000 )
b1101 "
b1101 +
1$
#38
b100010001000000 .
b1001000100000000 0
b10010001 &
b10010001 (
b10010001 *
b10010001 -
b10001 '
0$
#39
1$
#40
b1110 ,
b100010010000000 .
b1001001000000000 0
b10010010 &
b10010010 (
b10010010 *
b10010010 -
b10010 '
0$
#41
b1110 "
b1110 +
1$
#42
b100010011000000 .
b1001001100000000 0
b10010011 &
b10010011 (
b10010011 *
b10010011 -
b10011 '
0$
#43
1$
#44
b1111 ,
b1000101 3
b100010100000000 .
b1001010000000000 0
b10010100 &
b10010100 (
b10010100 *
b10010100 -
b10100 '
0$
#45
b1000101 !
b1000101 2
b1111 "
b1111 +
1$
#46
b100010101000000 .
b1001010100000000 0
b10010101 &
b10010101 (
b10010101 *
b10010101 -
b10101 '
0$
#47
b1001 #
b1001 )
1$
#48
b10000 ,
b100010110000000 .
b1001011000000000 0
b10010110 &
b10010110 (
b10010110 *
b10010110 -
b10110 '
0$
#49
b10000 "
b10000 +
1$
#50
b100010111000000 .
b1001011100000000 0
b10010111 &
b10010111 (
b10010111 *
b10010111 -
b10111 '
0$
#51
1$
#52
b10001 ,
b1000110 3
b100011000000000 .
b1001100000000000 0
b10011000 &
b10011000 (
b10011000 *
b10011000 -
b11000 '
0$
#53
b1000110 !
b1000110 2
b1010 #
b1010 )
b10001 "
b10001 +
1$
#54
b100011001000000 .
b1001100100000000 0
b10011001 &
b10011001 (
b10011001 *
b10011001 -
b11001 '
0$
#55
1$
#56
b10010 ,
b100011010000000 .
b1001101000000000 0
b10011010 &
b10011010 (
b10011010 *
b10011010 -
b11010 '
0$
#57
b10010 "
b10010 +
1$
#58
b100011011000000 .
b1001101100000000 0
b10011011 &
b10011011 (
b10011011 *
b10011011 -
b11011 '
0$
#59
1$
#60
b10011 ,
b1000111 3
b100011100000000 .
b1001110000000000 0
b10011100 &
b10011100 (
b10011100 *
b10011100 -
b11100 '
0$
#61
b1000111 !
b1000111 2
b1011 #
b1011 )
b10011 "
b10011 +
1$
#62
b100011101000000 .
b1001110100000000 0
b10011101 &
b10011101 (
b10011101 *
b10011101 -
b11101 '
0$
#63
1$
#64
b10100 ,
b100011110000000 .
b1001111000000000 0
b10011110 &
b10011110 (
b10011110 *
b10011110 -
b11110 '
0$
#65
b10100 "
b10100 +
1$
#66
b100011111000000 .
b1001111100000000 0
b10011111 &
b10011111 (
b10011111 *
b10011111 -
b11111 '
0$
#67
b1100 #
b1100 )
1$
#68
b10101 ,
b1001000 3
b100100000000000 .
b1010000000000000 0
b10100000 &
b10100000 (
b10100000 *
b10100000 -
b100000 '
0$
#69
b1001000 !
b1001000 2
b10101 "
b10101 +
1$
#70
b100100001000000 .
b1010000100000000 0
b10100001 &
b10100001 (
b10100001 *
b10100001 -
b100001 '
0$
#71
b1101 #
b1101 )
1$
#72
b10110 ,
b100100010000000 .
b1010001000000000 0
b10100010 &
b10100010 (
b10100010 *
b10100010 -
b100010 '
0$
#73
b10110 "
b10110 +
1$
#74
b100100011000000 .
b1010001100000000 0
b10100011 &
b10100011 (
b10100011 *
b10100011 -
b100011 '
0$
#75
1$
#76
b10111 ,
b1001001 3
b100100100000000 .
b1010010000000000 0
b10100100 &
b10100100 (
b10100100 *
b10100100 -
b100100 '
0$
#77
b1001001 !
b1001001 2
b1110 #
b1110 )
b10111 "
b10111 +
1$
#78
b100100101000000 .
b1010010100000000 0
b10100101 &
b10100101 (
b10100101 *
b10100101 -
b100101 '
0$
#79
1$
#80
b11000 ,
b100100110000000 .
b1010011000000000 0
b10100110 &
b10100110 (
b10100110 *
b10100110 -
b100110 '
0$
#81
b1111 #
b1111 )
b11000 "
b11000 +
1$
#82
b100100111000000 .
b1010011100000000 0
b10100111 &
b10100111 (
b10100111 *
b10100111 -
b100111 '
0$
#83
1$
#84
b11001 ,
b1001010 3
b100101000000000 .
b1010100000000000 0
b10101000 &
b10101000 (
b10101000 *
b10101000 -
b101000 '
0$
#85
b1001010 !
b1001010 2
b11001 "
b11001 +
1$
#86
b100101001000000 .
b1010100100000000 0
b10101001 &
b10101001 (
b10101001 *
b10101001 -
b101001 '
0$
#87
b10000 #
b10000 )
1$
#88
b11010 ,
b100101010000000 .
b1010101000000000 0
b10101010 &
b10101010 (
b10101010 *
b10101010 -
b101010 '
0$
#89
b11010 "
b11010 +
1$
#90
b100101011000000 .
b1010101100000000 0
b10101011 &
b10101011 (
b10101011 *
b10101011 -
b101011 '
0$
#91
b10001 #
b10001 )
1$
#92
b11011 ,
b1001011 3
b100101100000000 .
b1010110000000000 0
b10101100 &
b10101100 (
b10101100 *
b10101100 -
b101100 '
0$
#93
b1001011 !
b1001011 2
b11011 "
b11011 +
1$
#94
b100101101000000 .
b1010110100000000 0
b10101101 &
b10101101 (
b10101101 *
b10101101 -
b101101 '
0$
#95
b10010 #
b10010 )
1$
#96
b11100 ,
b100101110000000 .
b1010111000000000 0
b10101110 &
b10101110 (
b10101110 *
b10101110 -
b101110 '
0$
#97
b11100 "
b11100 +
1$
#98
b100101111000000 .
b1010111100000000 0
b10101111 &
b10101111 (
b10101111 *
b10101111 -
b101111 '
0$
#99
b10011 #
b10011 )
1$
#100
b11101 ,
b1001100 3
b100110000000000 .
b1011000000000000 0
b10110000 &
b10110000 (
b10110000 *
b10110000 -
b110000 '
0$
#101
b1001100 !
b1001100 2
b11101 "
b11101 +
1$
#102
b100110001000000 .
b1011000100000000 0
b10110001 &
b10110001 (
b10110001 *
b10110001 -
b110001 '
0$
#103
b10100 #
b10100 )
1$
#104
b11110 ,
b100110010000000 .
b1011001000000000 0
b10110010 &
b10110010 (
b10110010 *
b10110010 -
b110010 '
0$
#105
b10101 #
b10101 )
b11110 "
b11110 +
1$
#106
b100110011000000 .
b1011001100000000 0
b10110011 &
b10110011 (
b10110011 *
b10110011 -
b110011 '
0$
#107
1$
#108
b11111 ,
b1001101 3
b100110100000000 .
b1011010000000000 0
b10110100 &
b10110100 (
b10110100 *
b10110100 -
b110100 '
0$
#109
b1001101 !
b1001101 2
b10110 #
b10110 )
b11111 "
b11111 +
1$
#110
b100110101000000 .
b1011010100000000 0
b10110101 &
b10110101 (
b10110101 *
b10110101 -
b110101 '
0$
#111
1$
#112
b100000 ,
b100110110000000 .
b1011011000000000 0
b10110110 &
b10110110 (
b10110110 *
b10110110 -
b110110 '
0$
#113
b10111 #
b10111 )
b100000 "
b100000 +
1$
#114
b100110111000000 .
b1011011100000000 0
b10110111 &
b10110111 (
b10110111 *
b10110111 -
b110111 '
0$
#115
b11000 #
b11000 )
1$
#116
b100001 ,
b1001110 3
b100111000000000 .
b1011100000000000 0
b10111000 &
b10111000 (
b10111000 *
b10111000 -
b111000 '
0$
#117
b1001110 !
b1001110 2
b100001 "
b100001 +
1$
#118
b100111001000000 .
b1011100100000000 0
b10111001 &
b10111001 (
b10111001 *
b10111001 -
b111001 '
0$
#119
b11001 #
b11001 )
1$
#120
b100010 ,
b100111010000000 .
b1011101000000000 0
b10111010 &
b10111010 (
b10111010 *
b10111010 -
b111010 '
0$
#121
b11010 #
b11010 )
b100010 "
b100010 +
1$
#122
b100111011000000 .
b1011101100000000 0
b10111011 &
b10111011 (
b10111011 *
b10111011 -
b111011 '
0$
#123
b11011 #
b11011 )
1$
#124
b100011 ,
b1001111 3
b100111100000000 .
b1011110000000000 0
b10111100 &
b10111100 (
b10111100 *
b10111100 -
b111100 '
0$
#125
b1001111 !
b1001111 2
b100011 "
b100011 +
1$
#126
b100111101000000 .
b1011110100000000 0
b10111101 &
b10111101 (
b10111101 *
b10111101 -
b111101 '
0$
#127
b11100 #
b11100 )
1$
#128
b100100 ,
b100111110000000 .
b1011111000000000 0
b10111110 &
b10111110 (
b10111110 *
b10111110 -
b111110 '
0$
#129
b11101 #
b11101 )
b100100 "
b100100 +
1$
#130
b100111111000000 .
b1011111100000000 0
b10111111 &
b10111111 (
b10111111 *
b10111111 -
b111111 '
0$
#131
b11110 #
b11110 )
1$
#132
b100000 ,
b1010000 3
b101000000000000 .
b1100000000000000 0
b11000000 &
b11000000 (
b11000000 *
b11000000 -
b1000000 '
0$
#133
b1010000 !
b1010000 2
b11111 #
b11111 )
b100000 "
b100000 +
1$
#134
b100001 ,
b101000001000000 .
b1100000100000000 0
b11000001 &
b11000001 (
b11000001 *
b11000001 -
b1000001 '
0$
#135
b100001 "
b100001 +
1$
#136
b100010 ,
b101000010000000 .
b1100001000000000 0
b11000010 &
b11000010 (
b11000010 *
b11000010 -
b1000010 '
0$
#137
b100000 #
b100000 )
b100010 "
b100010 +
1$
#138
b100011 ,
b101000011000000 .
b1100001100000000 0
b11000011 &
b11000011 (
b11000011 *
b11000011 -
b1000011 '
0$
#139
b100011 "
b100011 +
b100001 #
b100001 )
1$
#140
b100100 ,
b1010001 3
b101000100000000 .
b1100010000000000 0
b11000100 &
b11000100 (
b11000100 *
b11000100 -
b1000100 '
0$
#141
b1010001 !
b1010001 2
b100010 #
b100010 )
b100100 "
b100100 +
1$
#142
b100101 ,
b101000101000000 .
b1100010100000000 0
b11000101 &
b11000101 (
b11000101 *
b11000101 -
b1000101 '
0$
#143
b100101 "
b100101 +
b100011 #
b100011 )
1$
#144
b100110 ,
b101000110000000 .
b1100011000000000 0
b11000110 &
b11000110 (
b11000110 *
b11000110 -
b1000110 '
0$
#145
b100100 #
b100100 )
b100110 "
b100110 +
1$
#146
b100111 ,
b101000111000000 .
b1100011100000000 0
b11000111 &
b11000111 (
b11000111 *
b11000111 -
b1000111 '
0$
#147
b100111 "
b100111 +
b100101 #
b100101 )
1$
#148
b101000 ,
b1010010 3
b101001000000000 .
b1100100000000000 0
b11001000 &
b11001000 (
b11001000 *
b11001000 -
b1001000 '
0$
#149
b1010010 !
b1010010 2
b100110 #
b100110 )
b101000 "
b101000 +
1$
#150
b101001 ,
b101001001000000 .
b1100100100000000 0
b11001001 &
b11001001 (
b11001001 *
b11001001 -
b1001001 '
0$
#151
b101001 "
b101001 +
b100111 #
b100111 )
1$
#152
b101010 ,
b101001010000000 .
b1100101000000000 0
b11001010 &
b11001010 (
b11001010 *
b11001010 -
b1001010 '
0$
#153
b101000 #
b101000 )
b101010 "
b101010 +
1$
#154
b101011 ,
b101001011000000 .
b1100101100000000 0
b11001011 &
b11001011 (
b11001011 *
b11001011 -
b1001011 '
0$
#155
b101011 "
b101011 +
b101001 #
b101001 )
1$
#156
b101100 ,
b1010011 3
b101001100000000 .
b1100110000000000 0
b11001100 &
b11001100 (
b11001100 *
b11001100 -
b1001100 '
0$
#157
b1010011 !
b1010011 2
b101010 #
b101010 )
b101100 "
b101100 +
1$
#158
b101101 ,
b101001101000000 .
b1100110100000000 0
b11001101 &
b11001101 (
b11001101 *
b11001101 -
b1001101 '
0$
#159
b101101 "
b101101 +
b101011 #
b101011 )
1$
#160
b101110 ,
b101001110000000 .
b1100111000000000 0
b11001110 &
b11001110 (
b11001110 *
b11001110 -
b1001110 '
0$
#161
b101100 #
b101100 )
b101110 "
b101110 +
1$
#162
b101111 ,
b101001111000000 .
b1100111100000000 0
b11001111 &
b11001111 (
b11001111 *
b11001111 -
b1001111 '
0$
#163
b101111 "
b101111 +
b101110 #
b101110 )
1$
#164
b110000 ,
b1010100 3
b101010000000000 .
b1101000000000000 0
b11010000 &
b11010000 (
b11010000 *
b11010000 -
b1010000 '
0$
#165
b1010100 !
b1010100 2
b101111 #
b101111 )
b110000 "
b110000 +
1$
#166
b110001 ,
b101010001000000 .
b1101000100000000 0
b11010001 &
b11010001 (
b11010001 *
b11010001 -
b1010001 '
0$
#167
b110001 "
b110001 +
b110000 #
b110000 )
1$
#168
b110010 ,
b101010010000000 .
b1101001000000000 0
b11010010 &
b11010010 (
b11010010 *
b11010010 -
b1010010 '
0$
#169
b110001 #
b110001 )
b110010 "
b110010 +
1$
#170
b110011 ,
b101010011000000 .
b1101001100000000 0
b11010011 &
b11010011 (
b11010011 *
b11010011 -
b1010011 '
0$
#171
b110011 "
b110011 +
b110010 #
b110010 )
1$
#172
b110100 ,
b1010101 3
b101010100000000 .
b1101010000000000 0
b11010100 &
b11010100 (
b11010100 *
b11010100 -
b1010100 '
0$
#173
b1010101 !
b1010101 2
b110100 #
b110100 )
b110100 "
b110100 +
1$
#174
b110101 ,
b101010101000000 .
b1101010100000000 0
b11010101 &
b11010101 (
b11010101 *
b11010101 -
b1010101 '
0$
#175
b110101 "
b110101 +
b110101 #
b110101 )
1$
#176
b110110 ,
b101010110000000 .
b1101011000000000 0
b11010110 &
b11010110 (
b11010110 *
b11010110 -
b1010110 '
0$
#177
b110110 #
b110110 )
b110110 "
b110110 +
1$
#178
b110111 ,
b101010111000000 .
b1101011100000000 0
b11010111 &
b11010111 (
b11010111 *
b11010111 -
b1010111 '
0$
#179
b110111 "
b110111 +
b111000 #
b111000 )
1$
#180
b111000 ,
b1010110 3
b101011000000000 .
b1101100000000000 0
b11011000 &
b11011000 (
b11011000 *
b11011000 -
b1011000 '
0$
#181
b1010110 !
b1010110 2
b111001 #
b111001 )
b111000 "
b111000 +
1$
#182
b111001 ,
b101011001000000 .
b1101100100000000 0
b11011001 &
b11011001 (
b11011001 *
b11011001 -
b1011001 '
0$
#183
b111001 "
b111001 +
b111010 #
b111010 )
1$
#184
b111010 ,
b101011010000000 .
b1101101000000000 0
b11011010 &
b11011010 (
b11011010 *
b11011010 -
b1011010 '
0$
#185
b111100 #
b111100 )
b111010 "
b111010 +
1$
#186
b111011 ,
b101011011000000 .
b1101101100000000 0
b11011011 &
b11011011 (
b11011011 *
b11011011 -
b1011011 '
0$
#187
b111011 "
b111011 +
b111101 #
b111101 )
1$
#188
b111100 ,
b1010111 3
b101011100000000 .
b1101110000000000 0
b11011100 &
b11011100 (
b11011100 *
b11011100 -
b1011100 '
0$
#189
b1010111 !
b1010111 2
b111111 #
b111111 )
b111100 "
b111100 +
1$
#190
b111101 ,
b101011101000000 .
b1101110100000000 0
b11011101 &
b11011101 (
b11011101 *
b11011101 -
b1011101 '
0$
#191
b111101 "
b111101 +
b1000000 #
b1000000 )
1$
#192
b111110 ,
b101011110000000 .
b1101111000000000 0
b11011110 &
b11011110 (
b11011110 *
b11011110 -
b1011110 '
0$
#193
b1000010 #
b1000010 )
b111110 "
b111110 +
1$
#194
b111111 ,
b101011111000000 .
b1101111100000000 0
b11011111 &
b11011111 (
b11011111 *
b11011111 -
b1011111 '
0$
