activation_functions/sigmoid/piecewise_linear.v
module sigmoid_piecewise (
    input clk,
    input reset,
    input signed [7:0] x_in,  // Q3.5 input (-4 to 4)
    output reg [7:0] y_out    // Q0.8 output (0 to 1)
);

    // Precomputed constants (Q0.8 format for slopes and offsets)
    // Now the slopes are scaled as powers of 2 to avoid multiplication
    // Each slope is represented as shift constants

    // Slope for -4 to -2 (a = 0.03125 -> shift by 5)
    localparam signed [7:0] SHIFT_1 = 2;    // 2^2 for slope = 0.25
    localparam signed [7:0] OFFSET_1 = 8'd5;  // Offset for -4 to -2 (b = 0.0 -> Q0.8 = 5)

    // Slope for -2 to -1 (a = 0.125 -> shift by 3)
    localparam signed [7:0] SHIFT_2 = 1;    // 2^1 for slope = 0.5
    localparam signed [7:0] OFFSET_2 = 8'd32;  // Offset for -2 to -1 (b = 0.125 -> Q0.8 = 32)

    // Slope for -1 to 1 (a = 0.25 -> shift by 2)
    localparam signed [7:0] SHIFT_3 = 1;    // 2^1 for slope = 2
    localparam signed [7:0] OFFSET_3 = 8'd69;  // Offset for -1 to 1 (b = 0.375 -> Q0.8 = 96)

    // Slope for 1 to 2 (a = 0.125 -> shift by 3)
    localparam signed [7:0] SHIFT_4 = 1;    // 2^1 for slope = 0.5
    localparam signed [7:0] OFFSET_4 = 8'd187; // Offset for 1 to 2 (b = 0.625 -> Q0.8 = 160)

    // Slope for 2 to 4 (a = 0.03125 -> shift by 5)
    localparam signed [7:0] SHIFT_5 = 2;    // 2^2 for slope = 0.125
    localparam signed [7:0] OFFSET_5 = 8'd225; // Offset for 2 to 4 (b = 0.75 -> Q0.8 = 192)
   
    reg [7:0] y_s;

    //registering output
    always @(posedge clk or negedge reset) begin
      if(~reset) begin
        y_out <= 0;
      end
      else begin
        y_out <= y_s;
      end
    end 

    always @(*) begin
        if (x_in <= -128) begin
            y_s = 8'd0;  // Output saturates to 0 for x <= -4
        end else if (x_in >= 127) begin
            y_s = 8'd255; // Output saturates to 1 for x >= 4
        end else if (x_in < -64) begin  // Segment 1: -4 to -2
            y_s = ((x_in + 128) >>> SHIFT_1) + OFFSET_1;
        end else if (x_in < -32) begin  // Segment 2: -2 to -1
            y_s = ((x_in + 64) >>> SHIFT_2) + OFFSET_2;
        end else if (x_in < 32) begin  // Segment 3: -1 to 1
            y_s = ((x_in + 32) <<< SHIFT_3) + OFFSET_3;
        end else if (x_in < 64) begin  // Segment 4: 1 to 2
            y_s = ((x_in - 32) >>> SHIFT_4) + OFFSET_4;
        end else begin  // Segment 5: 2 to 4
            y_s = ((x_in - 64) >>> SHIFT_5) + OFFSET_5;
        end
    end
endmodule

activation_functions/sigmoid/sigmoid_tb.v
module test_sigmoid;
    reg signed [7:0] x;
    wire [7:0] y;
    integer i;
    reg reset;
    reg clk;

    sigmoid_piecewise instance_piecewise (
        .x_in(x),
        .y_out(y),
        .clk(clk),
        .reset(reset)
    );

   //clock generation
   initial begin
    clk = 0;
    forever begin #0.5 clk = ~clk; end
   end   
   

    initial begin
      $dumpfile("test_sigmoid.vcd");
      $dumpvars(0,test_sigmoid);

      $display("Begin Reset");
      reset = 0; 
      repeat(2)@(posedge clk);
      reset = 1;
      $display("End reset");

      $display("Testing Sigmoid Module:");
      $display("  x\tPieceWise Linear");
      @(negedge clk)
      for (i = 0; i < 256; i = i + 1) begin
          x = (i - 128); // Test inputs: -128, -96, ..., 127
          @(negedge clk)
          $display("%d\t\t%d\t\t", x, y);
      end 
        $finish;
    end
endmodule

activation_functions/sigmoid/test_sigmoid.vcd
$date
	Thu Nov 28 22:59:12 2024
$end
$version
	Icarus Verilog
$end
$timescale
	1s
$end
$scope module test_sigmoid $end
$var wire 8 ! y [7:0] $end
$var reg 1 " clk $end
$var reg 1 # reset $end
$var reg 8 $ x [7:0] $end
$var integer 32 % i [31:0] $end
$scope module instance_piecewise $end
$var wire 1 " clk $end
$var wire 1 # reset $end
$var wire 8 & x_in [7:0] $end
$var reg 8 ' y_out [7:0] $end
$var reg 8 ( y_s [7:0] $end
$upscope $end
$upscope $end
$enddefinitions $end
#0
$dumpvars
bx (
b0 '
bx &
bx %
bx $
0#
0"
b0 !
$end
#1
1"
#2
0"
#3
bx !
bx '
1#
1"
#4
b0 (
b10000000 $
b10000000 &
b0 %
0"
#5
b0 !
b0 '
1"
#6
b101 (
b10000001 $
b10000001 &
b1 %
0"
#7
b101 !
b101 '
1"
#8
b10000010 $
b10000010 &
b10 %
0"
#9
1"
#10
b10000011 $
b10000011 &
b11 %
0"
#11
1"
#12
b110 (
b10000100 $
b10000100 &
b100 %
0"
#13
b110 !
b110 '
1"
#14
b10000101 $
b10000101 &
b101 %
0"
#15
1"
#16
b10000110 $
b10000110 &
b110 %
0"
#17
1"
#18
b10000111 $
b10000111 &
b111 %
0"
#19
1"
#20
b111 (
b10001000 $
b10001000 &
b1000 %
0"
#21
b111 !
b111 '
1"
#22
b10001001 $
b10001001 &
b1001 %
0"
#23
1"
#24
b10001010 $
b10001010 &
b1010 %
0"
#25
1"
#26
b10001011 $
b10001011 &
b1011 %
0"
#27
1"
#28
b1000 (
b10001100 $
b10001100 &
b1100 %
0"
#29
b1000 !
b1000 '
1"
#30
b10001101 $
b10001101 &
b1101 %
0"
#31
1"
#32
b10001110 $
b10001110 &
b1110 %
0"
#33
1"
#34
b10001111 $
b10001111 &
b1111 %
0"
#35
1"
#36
b1001 (
b10010000 $
b10010000 &
b10000 %
0"
#37
b1001 !
b1001 '
1"
#38
b10010001 $
b10010001 &
b10001 %
0"
#39
1"
#40
b10010010 $
b10010010 &
b10010 %
0"
#41
1"
#42
b10010011 $
b10010011 &
b10011 %
0"
#43
1"
#44
b1010 (
b10010100 $
b10010100 &
b10100 %
0"
#45
b1010 !
b1010 '
1"
#46
b10010101 $
b10010101 &
b10101 %
0"
#47
1"
#48
b10010110 $
b10010110 &
b10110 %
0"
#49
1"
#50
b10010111 $
b10010111 &
b10111 %
0"
#51
1"
#52
b1011 (
b10011000 $
b10011000 &
b11000 %
0"
#53
b1011 !
b1011 '
1"
#54
b10011001 $
b10011001 &
b11001 %
0"
#55
1"
#56
b10011010 $
b10011010 &
b11010 %
0"
#57
1"
#58
b10011011 $
b10011011 &
b11011 %
0"
#59
1"
#60
b1100 (
b10011100 $
b10011100 &
b11100 %
0"
#61
b1100 !
b1100 '
1"
#62
b10011101 $
b10011101 &
b11101 %
0"
#63
1"
#64
b10011110 $
b10011110 &
b11110 %
0"
#65
1"
#66
b10011111 $
b10011111 &
b11111 %
0"
#67
1"
#68
b1101 (
b10100000 $
b10100000 &
b100000 %
0"
#69
b1101 !
b1101 '
1"
#70
b10100001 $
b10100001 &
b100001 %
0"
#71
1"
#72
b10100010 $
b10100010 &
b100010 %
0"
#73
1"
#74
b10100011 $
b10100011 &
b100011 %
0"
#75
1"
#76
b1110 (
b10100100 $
b10100100 &
b100100 %
0"
#77
b1110 !
b1110 '
1"
#78
b10100101 $
b10100101 &
b100101 %
0"
#79
1"
#80
b10100110 $
b10100110 &
b100110 %
0"
#81
1"
#82
b10100111 $
b10100111 &
b100111 %
0"
#83
1"
#84
b1111 (
b10101000 $
b10101000 &
b101000 %
0"
#85
b1111 !
b1111 '
1"
#86
b10101001 $
b10101001 &
b101001 %
0"
#87
1"
#88
b10101010 $
b10101010 &
b101010 %
0"
#89
1"
#90
b10101011 $
b10101011 &
b101011 %
0"
#91
1"
#92
b10000 (
b10101100 $
b10101100 &
b101100 %
0"
#93
b10000 !
b10000 '
1"
#94
b10101101 $
b10101101 &
b101101 %
0"
#95
1"
#96
b10101110 $
b10101110 &
b101110 %
0"
#97
1"
#98
b10101111 $
b10101111 &
b101111 %
0"
#99
1"
#100
b10001 (
b10110000 $
b10110000 &
b110000 %
0"
#101
b10001 !
b10001 '
1"
#102
b10110001 $
b10110001 &
b110001 %
0"
#103
1"
#104
b10110010 $
b10110010 &
b110010 %
0"
#105
1"
#106
b10110011 $
b10110011 &
b110011 %
0"
#107
1"
#108
b10010 (
b10110100 $
b10110100 &
b110100 %
0"
#109
b10010 !
b10010 '
1"
#110
b10110101 $
b10110101 &
b110101 %
0"
#111
1"
#112
b10110110 $
b10110110 &
b110110 %
0"
#113
1"
#114
b10110111 $
b10110111 &
b110111 %
0"
#115
1"
#116
b10011 (
b10111000 $
b10111000 &
b111000 %
0"
#117
b10011 !
b10011 '
1"
#118
b10111001 $
b10111001 &
b111001 %
0"
#119
1"
#120
b10111010 $
b10111010 &
b111010 %
0"
#121
1"
#122
b10111011 $
b10111011 &
b111011 %
0"
#123
1"
#124
b10100 (
b10111100 $
b10111100 &
b111100 %
0"
#125
b10100 !
b10100 '
1"
#126
b10111101 $
b10111101 &
b111101 %
0"
#127
1"
#128
b10111110 $
b10111110 &
b111110 %
0"
#129
1"
#130
b10111111 $
b10111111 &
b111111 %
0"
#131
1"
#132
b100000 (
b11000000 $
b11000000 &
b1000000 %
0"
#133
b100000 !
b100000 '
1"
#134
b11000001 $
b11000001 &
b1000001 %
0"
#135
1"
#136
b100001 (
b11000010 $
b11000010 &
b1000010 %
0"
#137
b100001 !
b100001 '
1"
#138
b11000011 $
b11000011 &
b1000011 %
0"
#139
1"
#140
b100010 (
b11000100 $
b11000100 &
b1000100 %
0"
#141
b100010 !
b100010 '
1"
#142
b11000101 $
b11000101 &
b1000101 %
0"
#143
1"
#144
b100011 (
b11000110 $
b11000110 &
b1000110 %
0"
#145
b100011 !
b100011 '
1"
#146
b11000111 $
b11000111 &
b1000111 %
0"
#147
1"
#148
b100100 (
b11001000 $
b11001000 &
b1001000 %
0"
#149
b100100 !
b100100 '
1"
#150
b11001001 $
b11001001 &
b1001001 %
0"
#151
1"
#152
b100101 (
b11001010 $
b11001010 &
b1001010 %
0"
#153
b100101 !
b100101 '
1"
#154
b11001011 $
b11001011 &
b1001011 %
0"
#155
1"
#156
b100110 (
b11001100 $
b11001100 &
b1001100 %
0"
#157
b100110 !
b100110 '
1"
#158
b11001101 $
b11001101 &
b1001101 %
0"
#159
1"
#160
b100111 (
b11001110 $
b11001110 &
b1001110 %
0"
#161
b100111 !
b100111 '
1"
#162
b11001111 $
b11001111 &
b1001111 %
0"
#163
1"
#164
b101000 (
b11010000 $
b11010000 &
b1010000 %
0"
#165
b101000 !
b101000 '
1"
#166
b11010001 $
b11010001 &
b1010001 %
0"
#167
1"
#168
b101001 (
b11010010 $
b11010010 &
b1010010 %
0"
#169
b101001 !
b101001 '
1"
#170
b11010011 $
b11010011 &
b1010011 %
0"
#171
1"
#172
b101010 (
b11010100 $
b11010100 &
b1010100 %
0"
#173
b101010 !
b101010 '
1"
#174
b11010101 $
b11010101 &
b1010101 %
0"
#175
1"
#176
b101011 (
b11010110 $
b11010110 &
b1010110 %
0"
#177
b101011 !
b101011 '
1"
#178
b11010111 $
b11010111 &
b1010111 %
0"
#179
1"
#180
b101100 (
b11011000 $
b11011000 &
b1011000 %
0"
#181
b101100 !
b101100 '
1"
#182
b11011001 $
b11011001 &
b1011001 %
0"
#183
1"
#184
b101101 (
b11011010 $
b11011010 &
b1011010 %
0"
#185
b101101 !
b101101 '
1"
#186
b11011011 $
b11011011 &
b1011011 %
0"
#187
1"
#188
b101110 (
b11011100 $
b11011100 &
b1011100 %
0"
#189
b101110 !
b101110 '
1"
#190
b11011101 $
b11011101 &
b1011101 %
0"
#191
1"
#192
b101111 (
b11011110 $
b11011110 &
b1011110 %
0"
#193
b101111 !
b101111 '
1"
#194
b11011111 $
b11011111 &
b1011111 %
0"
#195
1"
#196
b1000101 (
b11100000 $
b11100000 &
b1100000 %
0"
#197
b1000101 !
b1000101 '
1"
#198
b1000111 (
b11100001 $
b11100001 &
b1100001 %
0"
#199
b1000111 !
b1000111 '
1"
#200
b1001001 (
b11100010 $
b11100010 &
b1100010 %
0"
#201
b1001001 !
b1001001 '
1"
#202
b1001011 (
b11100011 $
b11100011 &
b1100011 %
0"
#203
b1001011 !
b1001011 '
1"
#204
b1001101 (
b11100100 $
b11100100 &
b1100100 %
0"
#205
b1001101 !
b1001101 '
1"
#206
b1001111 (
b11100101 $
b11100101 &
b1100101 %
0"
#207
b1001111 !
b1001111 '
1"
#208
b1010001 (
b11100110 $
b11100110 &
b1100110 %
0"
#209
b1010001 !
b1010001 '
1"
#210
b1010011 (
b11100111 $
b11100111 &
b1100111 %
0"
#211
b1010011 !
b1010011 '
1"
#212
b1010101 (
b11101000 $
b11101000 &
b1101000 %
0"
#213
b1010101 !
b1010101 '
1"
#214
b1010111 (
b11101001 $
b11101001 &
b1101001 %
0"
#215
b1010111 !
b1010111 '
1"
#216
b1011001 (
b11101010 $
b11101010 &
b1101010 %
0"
#217
b1011001 !
b1011001 '
1"
#218
b1011011 (
b11101011 $
b11101011 &
b1101011 %
0"
#219
b1011011 !
b1011011 '
1"
#220
b1011101 (
b11101100 $
b11101100 &
b1101100 %
0"
#221
b1011101 !
b1011101 '
1"
#222
b1011111 (
b11101101 $
b11101101 &
b1101101 %
0"
#223
b1011111 !
b1011111 '
1"
#224
b1100001 (
b11101110 $
b11101110 &
b1101110 %
0"
#225
b1100001 !
b1100001 '
1"
#226
b1100011 (
b11101111 $
b11101111 &
b1101111 %
0"
#227
b1100011 !
b1100011 '
1"
#228
b1100101 (
b11110000 $
b11110000 &
b1110000 %
0"
#229
b1100101 !
b1100101 '
1"
#230
b1100111 (
b11110001 $
b11110001 &
b1110001 %
0"
#231
b1100111 !
b1100111 '
1"
#232
b1101001 (
b11110010 $
b11110010 &
b1110010 %
0"
#233
b1101001 !
b1101001 '
1"
#234
b1101011 (
b11110011 $
b11110011 &
b1110011 %
0"
#235
b1101011 !
b1101011 '
1"
#236
b1101101 (
b11110100 $
b11110100 &
b1110100 %
0"
#237
b1101101 !
b1101101 '
1"
#238
b1101111 (
b11110101 $
b11110101 &
b1110101 %
0"
#239
b1101111 !
b1101111 '
1"
#240
b1110001 (
b11110110 $
b11110110 &
b1110110 %
0"
#241
b1110001 !
b1110001 '
1"
#242
b1110011 (
b11110111 $
b11110111 &
b1110111 %
0"
#243
b1110011 !
b1110011 '
1"
#244
b1110101 (
b11111000 $
b11111000 &
b1111000 %
0"
#245
b1110101 !
b1110101 '
1"
#246
b1110111 (
b11111001 $
b11111001 &
b1111001 %
0"
#247
b1110111 !
b1110111 '
1"
#248
b1111001 (
b11111010 $
b11111010 &
b1111010 %
0"
#249
b1111001 !
b1111001 '
1"
#250
b1111011 (
b11111011 $
b11111011 &
b1111011 %
0"
#251
b1111011 !
b1111011 '
1"
#252
b1111101 (
b11111100 $
b11111100 &
b1111100 %
0"
#253
b1111101 !
b1111101 '
1"
#254
b1111111 (
b11111101 $
b11111101 &
b1111101 %
0"
#255
b1111111 !
b1111111 '
1"
#256
b10000001 (
b11111110 $
b11111110 &
b1111110 %
0"
#257
b10000001 !
b10000001 '
1"
#258
b10000011 (
b11111111 $
b11111111 &
b1111111 %
0"
#259
b10000011 !
b10000011 '
1"
#260
b10000101 (
b0 $
b0 &
b10000000 %
0"
#261
b10000101 !
b10000101 '
1"
#262
b10000111 (
b1 $
b1 &
b10000001 %
0"
#263
b10000111 !
b10000111 '
1"
#264
b10001001 (
b10 $
b10 &
b10000010 %
0"
#265
b10001001 !
b10001001 '
1"
#266
b10001011 (
b11 $
b11 &
b10000011 %
0"
#267
b10001011 !
b10001011 '
1"
#268
b10001101 (
b100 $
b100 &
b10000100 %
0"
#269
b10001101 !
b10001101 '
1"
#270
b10001111 (
b101 $
b101 &
b10000101 %
0"
#271
b10001111 !
b10001111 '
1"
#272
b10010001 (
b110 $
b110 &
b10000110 %
0"
#273
b10010001 !
b10010001 '
1"
#274
b10010011 (
b111 $
b111 &
b10000111 %
0"
#275
b10010011 !
b10010011 '
1"
#276
b10010101 (
b1000 $
b1000 &
b10001000 %
0"
#277
b10010101 !
b10010101 '
1"
#278
b10010111 (
b1001 $
b1001 &
b10001001 %
0"
#279
b10010111 !
b10010111 '
1"
#280
b10011001 (
b1010 $
b1010 &
b10001010 %
0"
#281
b10011001 !
b10011001 '
1"
#282
b10011011 (
b1011 $
b1011 &
b10001011 %
0"
#283
b10011011 !
b10011011 '
1"
#284
b10011101 (
b1100 $
b1100 &
b10001100 %
0"
#285
b10011101 !
b10011101 '
1"
#286
b10011111 (
b1101 $
b1101 &
b10001101 %
0"
#287
b10011111 !
b10011111 '
1"
#288
b10100001 (
b1110 $
b1110 &
b10001110 %
0"
#289
b10100001 !
b10100001 '
1"
#290
b10100011 (
b1111 $
b1111 &
b10001111 %
0"
#291
b10100011 !
b10100011 '
1"
#292
b10100101 (
b10000 $
b10000 &
b10010000 %
0"
#293
b10100101 !
b10100101 '
1"
#294
b10100111 (
b10001 $
b10001 &
b10010001 %
0"
#295
b10100111 !
b10100111 '
1"
#296
b10101001 (
b10010 $
b10010 &
b10010010 %
0"
#297
b10101001 !
b10101001 '
1"
#298
b10101011 (
b10011 $
b10011 &
b10010011 %
0"
#299
b10101011 !
b10101011 '
1"
#300
b10101101 (
b10100 $
b10100 &
b10010100 %
0"
#301
b10101101 !
b10101101 '
1"
#302
b10101111 (
b10101 $
b10101 &
b10010101 %
0"
#303
b10101111 !
b10101111 '
1"
#304
b10110001 (
b10110 $
b10110 &
b10010110 %
0"
#305
b10110001 !
b10110001 '
1"
#306
b10110011 (
b10111 $
b10111 &
b10010111 %
0"
#307
b10110011 !
b10110011 '
1"
#308
b10110101 (
b11000 $
b11000 &
b10011000 %
0"
#309
b10110101 !
b10110101 '
1"
#310
b10110111 (
b11001 $
b11001 &
b10011001 %
0"
#311
b10110111 !
b10110111 '
1"
#312
b10111001 (
b11010 $
b11010 &
b10011010 %
0"
#313
b10111001 !
b10111001 '
1"
#314
b10111011 (
b11011 $
b11011 &
b10011011 %
0"
#315
b10111011 !
b10111011 '
1"
#316
b10111101 (
b11100 $
b11100 &
b10011100 %
0"
#317
b10111101 !
b10111101 '
1"
#318
b10111111 (
b11101 $
b11101 &
b10011101 %
0"
#319
b10111111 !
b10111111 '
1"
#320
b11000001 (
b11110 $
b11110 &
b10011110 %
0"
#321
b11000001 !
b11000001 '
1"
#322
b11000011 (
b11111 $
b11111 &
b10011111 %
0"
#323
b11000011 !
b11000011 '
1"
#324
b10111011 (
b100000 $
b100000 &
b10100000 %
0"
#325
b10111011 !
b10111011 '
1"
#326
b100001 $
b100001 &
b10100001 %
0"
#327
1"
#328
b10111100 (
b100010 $
b100010 &
b10100010 %
0"
#329
b10111100 !
b10111100 '
1"
#330
b100011 $
b100011 &
b10100011 %
0"
#331
1"
#332
b10111101 (
b100100 $
b100100 &
b10100100 %
0"
#333
b10111101 !
b10111101 '
1"
#334
b100101 $
b100101 &
b10100101 %
0"
#335
1"
#336
b10111110 (
b100110 $
b100110 &
b10100110 %
0"
#337
b10111110 !
b10111110 '
1"
#338
b100111 $
b100111 &
b10100111 %
0"
#339
1"
#340
b10111111 (
b101000 $
b101000 &
b10101000 %
0"
#341
b10111111 !
b10111111 '
1"
#342
b101001 $
b101001 &
b10101001 %
0"
#343
1"
#344
b11000000 (
b101010 $
b101010 &
b10101010 %
0"
#345
b11000000 !
b11000000 '
1"
#346
b101011 $
b101011 &
b10101011 %
0"
#347
1"
#348
b11000001 (
b101100 $
b101100 &
b10101100 %
0"
#349
b11000001 !
b11000001 '
1"
#350
b101101 $
b101101 &
b10101101 %
0"
#351
1"
#352
b11000010 (
b101110 $
b101110 &
b10101110 %
0"
#353
b11000010 !
b11000010 '
1"
#354
b101111 $
b101111 &
b10101111 %
0"
#355
1"
#356
b11000011 (
b110000 $
b110000 &
b10110000 %
0"
#357
b11000011 !
b11000011 '
1"
#358
b110001 $
b110001 &
b10110001 %
0"
#359
1"
#360
b11000100 (
b110010 $
b110010 &
b10110010 %
0"
#361
b11000100 !
b11000100 '
1"
#362
b110011 $
b110011 &
b10110011 %
0"
#363
1"
#364
b11000101 (
b110100 $
b110100 &
b10110100 %
0"
#365
b11000101 !
b11000101 '
1"
#366
b110101 $
b110101 &
b10110101 %
0"
#367
1"
#368
b11000110 (
b110110 $
b110110 &
b10110110 %
0"
#369
b11000110 !
b11000110 '
1"
#370
b110111 $
b110111 &
b10110111 %
0"
#371
1"
#372
b11000111 (
b111000 $
b111000 &
b10111000 %
0"
#373
b11000111 !
b11000111 '
1"
#374
b111001 $
b111001 &
b10111001 %
0"
#375
1"
#376
b11001000 (
b111010 $
b111010 &
b10111010 %
0"
#377
b11001000 !
b11001000 '
1"
#378
b111011 $
b111011 &
b10111011 %
0"
#379
1"
#380
b11001001 (
b111100 $
b111100 &
b10111100 %
0"
#381
b11001001 !
b11001001 '
1"
#382
b111101 $
b111101 &
b10111101 %
0"
#383
1"
#384
b11001010 (
b111110 $
b111110 &
b10111110 %
0"
#385
b11001010 !
b11001010 '
1"
#386
b111111 $
b111111 &
b10111111 %
0"
#387
1"
#388
b11100001 (
b1000000 $
b1000000 &
b11000000 %
0"
#389
b11100001 !
b11100001 '
1"
#390
b1000001 $
b1000001 &
b11000001 %
0"
#391
1"
#392
b1000010 $
b1000010 &
b11000010 %
0"
#393
1"
#394
b1000011 $
b1000011 &
b11000011 %
0"
#395
1"
#396
b11100010 (
b1000100 $
b1000100 &
b11000100 %
0"
#397
b11100010 !
b11100010 '
1"
#398
b1000101 $
b1000101 &
b11000101 %
0"
#399
1"
#400
b1000110 $
b1000110 &
b11000110 %
0"
#401
1"
#402
b1000111 $
b1000111 &
b11000111 %
0"
#403
1"
#404
b11100011 (
b1001000 $
b1001000 &
b11001000 %
0"
#405
b11100011 !
b11100011 '
1"
#406
b1001001 $
b1001001 &
b11001001 %
0"
#407
1"
#408
b1001010 $
b1001010 &
b11001010 %
0"
#409
1"
#410
b1001011 $
b1001011 &
b11001011 %
0"
#411
1"
#412
b11100100 (
b1001100 $
b1001100 &
b11001100 %
0"
#413
b11100100 !
b11100100 '
1"
#414
b1001101 $
b1001101 &
b11001101 %
0"
#415
1"
#416
b1001110 $
b1001110 &
b11001110 %
0"
#417
1"
#418
b1001111 $
b1001111 &
b11001111 %
0"
#419
1"
#420
b11100101 (
b1010000 $
b1010000 &
b11010000 %
0"
#421
b11100101 !
b11100101 '
1"
#422
b1010001 $
b1010001 &
b11010001 %
0"
#423
1"
#424
b1010010 $
b1010010 &
b11010010 %
0"
#425
1"
#426
b1010011 $
b1010011 &
b11010011 %
0"
#427
1"
#428
b11100110 (
b1010100 $
b1010100 &
b11010100 %
0"
#429
b11100110 !
b11100110 '
1"
#430
b1010101 $
b1010101 &
b11010101 %
0"
#431
1"
#432
b1010110 $
b1010110 &
b11010110 %
0"
#433
1"
#434
b1010111 $
b1010111 &
b11010111 %
0"
#435
1"
#436
b11100111 (
b1011000 $
b1011000 &
b11011000 %
0"
#437
b11100111 !
b11100111 '
1"
#438
b1011001 $
b1011001 &
b11011001 %
0"
#439
1"
#440
b1011010 $
b1011010 &
b11011010 %
0"
#441
1"
#442
b1011011 $
b1011011 &
b11011011 %
0"
#443
1"
#444
b11101000 (
b1011100 $
b1011100 &
b11011100 %
0"
#445
b11101000 !
b11101000 '
1"
#446
b1011101 $
b1011101 &
b11011101 %
0"
#447
1"
#448
b1011110 $
b1011110 &
b11011110 %
0"
#449
1"
#450
b1011111 $
b1011111 &
b11011111 %
0"
#451
1"
#452
b11101001 (
b1100000 $
b1100000 &
b11100000 %
0"
#453
b11101001 !
b11101001 '
1"
#454
b1100001 $
b1100001 &
b11100001 %
0"
#455
1"
#456
b1100010 $
b1100010 &
b11100010 %
0"
#457
1"
#458
b1100011 $
b1100011 &
b11100011 %
0"
#459
1"
#460
b11101010 (
b1100100 $
b1100100 &
b11100100 %
0"
#461
b11101010 !
b11101010 '
1"
#462
b1100101 $
b1100101 &
b11100101 %
0"
#463
1"
#464
b1100110 $
b1100110 &
b11100110 %
0"
#465
1"
#466
b1100111 $
b1100111 &
b11100111 %
0"
#467
1"
#468
b11101011 (
b1101000 $
b1101000 &
b11101000 %
0"
#469
b11101011 !
b11101011 '
1"
#470
b1101001 $
b1101001 &
b11101001 %
0"
#471
1"
#472
b1101010 $
b1101010 &
b11101010 %
0"
#473
1"
#474
b1101011 $
b1101011 &
b11101011 %
0"
#475
1"
#476
b11101100 (
b1101100 $
b1101100 &
b11101100 %
0"
#477
b11101100 !
b11101100 '
1"
#478
b1101101 $
b1101101 &
b11101101 %
0"
#479
1"
#480
b1101110 $
b1101110 &
b11101110 %
0"
#481
1"
#482
b1101111 $
b1101111 &
b11101111 %
0"
#483
1"
#484
b11101101 (
b1110000 $
b1110000 &
b11110000 %
0"
#485
b11101101 !
b11101101 '
1"
#486
b1110001 $
b1110001 &
b11110001 %
0"
#487
1"
#488
b1110010 $
b1110010 &
b11110010 %
0"
#489
1"
#490
b1110011 $
b1110011 &
b11110011 %
0"
#491
1"
#492
b11101110 (
b1110100 $
b1110100 &
b11110100 %
0"
#493
b11101110 !
b11101110 '
1"
#494
b1110101 $
b1110101 &
b11110101 %
0"
#495
1"
#496
b1110110 $
b1110110 &
b11110110 %
0"
#497
1"
#498
b1110111 $
b1110111 &
b11110111 %
0"
#499
1"
#500
b11101111 (
b1111000 $
b1111000 &
b11111000 %
0"
#501
b11101111 !
b11101111 '
1"
#502
b1111001 $
b1111001 &
b11111001 %
0"
#503
1"
#504
b1111010 $
b1111010 &
b11111010 %
0"
#505
1"
#506
b1111011 $
b1111011 &
b11111011 %
0"
#507
1"
#508
b11110000 (
b1111100 $
b1111100 &
b11111100 %
0"
#509
b11110000 !
b11110000 '
1"
#510
b1111101 $
b1111101 &
b11111101 %
0"
#511
1"
#512
b1111110 $
b1111110 &
b11111110 %
0"
#513
1"
#514
b11111111 (
b1111111 $
b1111111 &
b11111111 %
0"
#515
b11111111 !
b11111111 '
1"
#516
b100000000 %
0"
