activation_functions/gelu/lut_based_gelu.v
module gelu_lut (
    input clk,
    input reset,
    input signed [7:0] x_in,  // Q3.5 input (-4 to 4)
    output reg signed [7:0] y_out    // Q3.5 output (-4 to 4)
);

     reg signed [7:0] LUT [255:0];

    //registering output
    always @(posedge clk or negedge reset) begin
      if(~reset) begin
        y_out <= 0;
      end
      else begin
        y_out <= LUT['sd128+x_in];
      end
    end 


    always @(posedge clk or negedge reset) begin
      LUT[0]<=0;
      LUT[1]<=0;
      LUT[2]<=0;
      LUT[3]<=0;
      LUT[4]<=0;
      LUT[5]<=0;
      LUT[6]<=0;
      LUT[7]<=0;
      LUT[8]<=0;
      LUT[9]<=0;
      LUT[10]<=0;
      LUT[11]<=0;
      LUT[12]<=0;
      LUT[13]<=0;
      LUT[14]<=0;
      LUT[15]<=0;
      LUT[16]<=0;
      LUT[17]<=0;
      LUT[18]<=0;
      LUT[19]<=0;
      LUT[20]<=0;
      LUT[21]<=0;
      LUT[22]<=0;
      LUT[23]<=0;
      LUT[24]<=0;
      LUT[25]<=0;
      LUT[26]<=0;
      LUT[27]<=0;
      LUT[28]<=0;
      LUT[29]<=0;
      LUT[30]<=0;
      LUT[31]<=0;
      LUT[32]<=0;
      LUT[33]<=0;
      LUT[34]<=0;
      LUT[35]<=0;
      LUT[36]<=0;
      LUT[37]<=0;
      LUT[38]<=0;
      LUT[39]<=0;
      LUT[40]<=0;
      LUT[41]<=0;
      LUT[42]<=0;
      LUT[43]<=0;
      LUT[44]<=0;
      LUT[45]<=0;
      LUT[46]<=0;
      LUT[47]<=0;
      LUT[48]<=0;
      LUT[49]<=-1;
      LUT[50]<=-1;
      LUT[51]<=-1;
      LUT[52]<=-1;
      LUT[53]<=-1;
      LUT[54]<=-1;
      LUT[55]<=-1;
      LUT[56]<=-1;
      LUT[57]<=-1;
      LUT[58]<=-1;
      LUT[59]<=-1;
      LUT[60]<=-1;
      LUT[61]<=-1;
      LUT[62]<=-1;
      LUT[63]<=-1;
      LUT[64]<=-1;
      LUT[65]<=-2;
      LUT[66]<=-2;
      LUT[67]<=-2;
      LUT[68]<=-2;
      LUT[69]<=-2;
      LUT[70]<=-2;
      LUT[71]<=-2;
      LUT[72]<=-2;
      LUT[73]<=-2;
      LUT[74]<=-2;
      LUT[75]<=-3;
      LUT[76]<=-3;
      LUT[77]<=-3;
      LUT[78]<=-3;
      LUT[79]<=-3;
      LUT[80]<=-3;
      LUT[81]<=-3;
      LUT[82]<=-3;
      LUT[83]<=-4;
      LUT[84]<=-4;
      LUT[85]<=-4;
      LUT[86]<=-4;
      LUT[87]<=-4;
      LUT[88]<=-4;
      LUT[89]<=-4;
      LUT[90]<=-4;
      LUT[91]<=-5;
      LUT[92]<=-5;
      LUT[93]<=-5;
      LUT[94]<=-5;
      LUT[95]<=-5;
      LUT[96]<=-5;
      LUT[97]<=-5;
      LUT[98]<=-5;
      LUT[99]<=-5;
      LUT[100]<=-5;
      LUT[101]<=-5;
      LUT[102]<=-5;
      LUT[103]<=-5;
      LUT[104]<=-5;
      LUT[105]<=-5;
      LUT[106]<=-5;
      LUT[107]<=-5;
      LUT[108]<=-5;
      LUT[109]<=-5;
      LUT[110]<=-5;
      LUT[111]<=-5;
      LUT[112]<=-5;
      LUT[113]<=-5;
      LUT[114]<=-5;
      LUT[115]<=-4;
      LUT[116]<=-4;
      LUT[117]<=-4;
      LUT[118]<=-4;
      LUT[119]<=-4;
      LUT[120]<=-3;
      LUT[121]<=-3;
      LUT[122]<=-3;
      LUT[123]<=-2;
      LUT[124]<=-2;
      LUT[125]<=-1;
      LUT[126]<=-1;
      LUT[127]<=0;
      LUT[128]<=0;
      LUT[129]<=1;
      LUT[130]<=1;
      LUT[131]<=2;
      LUT[132]<=2;
      LUT[133]<=3;
      LUT[134]<=3;
      LUT[135]<=4;
      LUT[136]<=5;
      LUT[137]<=5;
      LUT[138]<=6;
      LUT[139]<=7;
      LUT[140]<=8;
      LUT[141]<=9;
      LUT[142]<=9;
      LUT[143]<=10;
      LUT[144]<=11;
      LUT[145]<=12;
      LUT[146]<=13;
      LUT[147]<=14;
      LUT[148]<=15;
      LUT[149]<=16;
      LUT[150]<=17;
      LUT[151]<=18;
      LUT[152]<=19;
      LUT[153]<=20;
      LUT[154]<=21;
      LUT[155]<=22;
      LUT[156]<=23;
      LUT[157]<=24;
      LUT[158]<=25;
      LUT[159]<=26;
      LUT[160]<=27;
      LUT[161]<=28;
      LUT[162]<=29;
      LUT[163]<=30;
      LUT[164]<=31;
      LUT[165]<=32;
      LUT[166]<=34;
      LUT[167]<=35;
      LUT[168]<=36;
      LUT[169]<=37;
      LUT[170]<=38;
      LUT[171]<=39;
      LUT[172]<=40;
      LUT[173]<=41;
      LUT[174]<=43;
      LUT[175]<=44;
      LUT[176]<=45;
      LUT[177]<=46;
      LUT[178]<=47;
      LUT[179]<=48;
      LUT[180]<=49;
      LUT[181]<=50;
      LUT[182]<=52;
      LUT[183]<=53;
      LUT[184]<=54;
      LUT[185]<=55;
      LUT[186]<=56;
      LUT[187]<=57;
      LUT[188]<=58;
      LUT[189]<=59;
      LUT[190]<=60;
      LUT[191]<=61;
      LUT[192]<=63;
      LUT[193]<=64;
      LUT[194]<=65;
      LUT[195]<=66;
      LUT[196]<=67;
      LUT[197]<=68;
      LUT[198]<=69;
      LUT[199]<=70;
      LUT[200]<=71;
      LUT[201]<=72;
      LUT[202]<=73;
      LUT[203]<=74;
      LUT[204]<=75;
      LUT[205]<=76;
      LUT[206]<=77;
      LUT[207]<=78;
      LUT[208]<=80;
      LUT[209]<=81;
      LUT[210]<=82;
      LUT[211]<=83;
      LUT[212]<=84;
      LUT[213]<=85;
      LUT[214]<=86;
      LUT[215]<=87;
      LUT[216]<=88;
      LUT[217]<=89;
      LUT[218]<=90;
      LUT[219]<=91;
      LUT[220]<=92;
      LUT[221]<=93;
      LUT[222]<=94;
      LUT[223]<=95;
      LUT[224]<=96;
      LUT[225]<=97;
      LUT[226]<=98;
      LUT[227]<=99;
      LUT[228]<=100;
      LUT[229]<=101;
      LUT[230]<=102;
      LUT[231]<=103;
      LUT[232]<=104;
      LUT[233]<=105;
      LUT[234]<=106;
      LUT[235]<=107;
      LUT[236]<=108;
      LUT[237]<=109;
      LUT[238]<=110;
      LUT[239]<=111;
      LUT[240]<=112;
      LUT[241]<=113;
      LUT[242]<=114;
      LUT[243]<=115;
      LUT[244]<=116;
      LUT[245]<=117;
      LUT[246]<=118;
      LUT[247]<=119;
      LUT[248]<=120;
      LUT[249]<=121;
      LUT[250]<=122;
      LUT[251]<=123;
      LUT[252]<=124;
      LUT[253]<=125;
      LUT[254]<=126;
      LUT[255]<=127;
      LUT[255]<=127;
    end

endmodule

activation_functions/gelu/piecewise_linear_gelu.v
module gelu_piecewise (
    input clk,
    input reset,
    input signed [7:0] x_in,  // Q3.5 input (-4 to 4)
    output reg signed [7:0] y_out // Q0.7 output (-128 to 127)
);

    // Constants for the piecewise linear approximation (using shifts and adds)
    //for range -2.5 to -0.5 
    localparam signed [7:0] SHIFT_1 = 4;   
    localparam signed [7:0] OFFSET_1 = -8'd1;

    localparam signed [7:0] SHIFT_2 = 2;    
    localparam signed [7:0] OFFSET_2 = -8'd5;  

    always @(posedge clk or negedge reset) begin
        if (~reset) begin
            y_out <= 8'd0;  // Reset to 0
        end else begin
            // Piecewise function for tanh approximation
            if (x_in <= -80) begin //x<-2.5
                y_out <= 0; 
            end else if (x_in < -16) begin //x< -0.5
                y_out <= OFFSET_1 - ((x_in + 80) >>> SHIFT_1); // Use shift to approximate slope
            end else if (x_in < 0) begin
                y_out <= ((x_in + 16) >>> SHIFT_2) + OFFSET_2; // Use shift to approximate slope
            end else begin
                y_out <= x_in;  // x>0
            end
        end
    end
endmodule

activation_functions/gelu/gelu_tb.v
module test_gelu;
    reg signed [7:0] x;
    wire signed [7:0] y_piecewise, y_lut;
    integer i;
    reg reset;
    reg clk;

    gelu_piecewise instance_piecewise (
        .x_in(x),
        .y_out(y_piecewise),
        .clk(clk),
        .reset(reset)
    );

    gelu_lut instance_lut (
        .x_in(x),
        .y_out(y_lut),
        .clk(clk),
        .reset(reset)
    );


   //clock generation
   initial begin
    clk = 0;
    forever begin #0.5 clk = ~clk; end
   end   
   

    initial begin
      $dumpfile("test_tanh.vcd");
      $dumpvars(0,test_gelu);

      $display("Begin Reset");
      reset = 0; 
      repeat(2)@(posedge clk);
      reset = 1;
      $display("End reset");

      $display("Testing Tanh Module:");
      $display("  x\t\tLUT\t\tPieceWise Linear");
      @(negedge clk)
      for (i = 0; i < 256; i = i + 1) begin
          x = (i - 128); // Test inputs: -128, -96, ..., 127
          @(negedge clk)
          $display("%d\t\t%d\t\t%d\t\t", x, y_lut, y_piecewise);
      end 
        $finish;
    end

endmodule

activation_functions/gelu/test_tanh.vcd
$date
	Mon Dec  2 21:26:57 2024
$end
$version
	Icarus Verilog
$end
$timescale
	1s
$end
$scope module test_gelu $end
$var wire 8 ! y_piecewise [7:0] $end
$var wire 8 " y_lut [7:0] $end
$var reg 1 # clk $end
$var reg 1 $ reset $end
$var reg 8 % x [7:0] $end
$var integer 32 & i [31:0] $end
$scope module instance_lut $end
$var wire 1 # clk $end
$var wire 1 $ reset $end
$var wire 8 ' x_in [7:0] $end
$var reg 8 ( y_out [7:0] $end
$upscope $end
$scope module instance_piecewise $end
$var wire 1 # clk $end
$var wire 1 $ reset $end
$var wire 8 ) x_in [7:0] $end
$var reg 8 * y_out [7:0] $end
$upscope $end
$upscope $end
$enddefinitions $end
#0
$dumpvars
bx *
bx )
b0 (
bx '
bx &
bx %
0$
0#
b0 "
bx !
$end
#1
b0 !
b0 *
1#
#2
0#
#3
bx "
bx (
bx !
bx *
1$
1#
#4
b10000000 %
b10000000 '
b10000000 )
b0 &
0#
#5
b0 "
b0 (
b0 !
b0 *
1#
#6
b10000001 %
b10000001 '
b10000001 )
b1 &
0#
#7
1#
#8
b10000010 %
b10000010 '
b10000010 )
b10 &
0#
#9
1#
#10
b10000011 %
b10000011 '
b10000011 )
b11 &
0#
#11
1#
#12
b10000100 %
b10000100 '
b10000100 )
b100 &
0#
#13
1#
#14
b10000101 %
b10000101 '
b10000101 )
b101 &
0#
#15
1#
#16
b10000110 %
b10000110 '
b10000110 )
b110 &
0#
#17
1#
#18
b10000111 %
b10000111 '
b10000111 )
b111 &
0#
#19
1#
#20
b10001000 %
b10001000 '
b10001000 )
b1000 &
0#
#21
1#
#22
b10001001 %
b10001001 '
b10001001 )
b1001 &
0#
#23
1#
#24
b10001010 %
b10001010 '
b10001010 )
b1010 &
0#
#25
1#
#26
b10001011 %
b10001011 '
b10001011 )
b1011 &
0#
#27
1#
#28
b10001100 %
b10001100 '
b10001100 )
b1100 &
0#
#29
1#
#30
b10001101 %
b10001101 '
b10001101 )
b1101 &
0#
#31
1#
#32
b10001110 %
b10001110 '
b10001110 )
b1110 &
0#
#33
1#
#34
b10001111 %
b10001111 '
b10001111 )
b1111 &
0#
#35
1#
#36
b10010000 %
b10010000 '
b10010000 )
b10000 &
0#
#37
1#
#38
b10010001 %
b10010001 '
b10010001 )
b10001 &
0#
#39
1#
#40
b10010010 %
b10010010 '
b10010010 )
b10010 &
0#
#41
1#
#42
b10010011 %
b10010011 '
b10010011 )
b10011 &
0#
#43
1#
#44
b10010100 %
b10010100 '
b10010100 )
b10100 &
0#
#45
1#
#46
b10010101 %
b10010101 '
b10010101 )
b10101 &
0#
#47
1#
#48
b10010110 %
b10010110 '
b10010110 )
b10110 &
0#
#49
1#
#50
b10010111 %
b10010111 '
b10010111 )
b10111 &
0#
#51
1#
#52
b10011000 %
b10011000 '
b10011000 )
b11000 &
0#
#53
1#
#54
b10011001 %
b10011001 '
b10011001 )
b11001 &
0#
#55
1#
#56
b10011010 %
b10011010 '
b10011010 )
b11010 &
0#
#57
1#
#58
b10011011 %
b10011011 '
b10011011 )
b11011 &
0#
#59
1#
#60
b10011100 %
b10011100 '
b10011100 )
b11100 &
0#
#61
1#
#62
b10011101 %
b10011101 '
b10011101 )
b11101 &
0#
#63
1#
#64
b10011110 %
b10011110 '
b10011110 )
b11110 &
0#
#65
1#
#66
b10011111 %
b10011111 '
b10011111 )
b11111 &
0#
#67
1#
#68
b10100000 %
b10100000 '
b10100000 )
b100000 &
0#
#69
1#
#70
b10100001 %
b10100001 '
b10100001 )
b100001 &
0#
#71
1#
#72
b10100010 %
b10100010 '
b10100010 )
b100010 &
0#
#73
1#
#74
b10100011 %
b10100011 '
b10100011 )
b100011 &
0#
#75
1#
#76
b10100100 %
b10100100 '
b10100100 )
b100100 &
0#
#77
1#
#78
b10100101 %
b10100101 '
b10100101 )
b100101 &
0#
#79
1#
#80
b10100110 %
b10100110 '
b10100110 )
b100110 &
0#
#81
1#
#82
b10100111 %
b10100111 '
b10100111 )
b100111 &
0#
#83
1#
#84
b10101000 %
b10101000 '
b10101000 )
b101000 &
0#
#85
1#
#86
b10101001 %
b10101001 '
b10101001 )
b101001 &
0#
#87
1#
#88
b10101010 %
b10101010 '
b10101010 )
b101010 &
0#
#89
1#
#90
b10101011 %
b10101011 '
b10101011 )
b101011 &
0#
#91
1#
#92
b10101100 %
b10101100 '
b10101100 )
b101100 &
0#
#93
1#
#94
b10101101 %
b10101101 '
b10101101 )
b101101 &
0#
#95
1#
#96
b10101110 %
b10101110 '
b10101110 )
b101110 &
0#
#97
1#
#98
b10101111 %
b10101111 '
b10101111 )
b101111 &
0#
#99
1#
#100
b10110000 %
b10110000 '
b10110000 )
b110000 &
0#
#101
1#
#102
b10110001 %
b10110001 '
b10110001 )
b110001 &
0#
#103
b11111111 "
b11111111 (
b11111111 !
b11111111 *
1#
#104
b10110010 %
b10110010 '
b10110010 )
b110010 &
0#
#105
1#
#106
b10110011 %
b10110011 '
b10110011 )
b110011 &
0#
#107
1#
#108
b10110100 %
b10110100 '
b10110100 )
b110100 &
0#
#109
1#
#110
b10110101 %
b10110101 '
b10110101 )
b110101 &
0#
#111
1#
#112
b10110110 %
b10110110 '
b10110110 )
b110110 &
0#
#113
1#
#114
b10110111 %
b10110111 '
b10110111 )
b110111 &
0#
#115
1#
#116
b10111000 %
b10111000 '
b10111000 )
b111000 &
0#
#117
1#
#118
b10111001 %
b10111001 '
b10111001 )
b111001 &
0#
#119
1#
#120
b10111010 %
b10111010 '
b10111010 )
b111010 &
0#
#121
1#
#122
b10111011 %
b10111011 '
b10111011 )
b111011 &
0#
#123
1#
#124
b10111100 %
b10111100 '
b10111100 )
b111100 &
0#
#125
1#
#126
b10111101 %
b10111101 '
b10111101 )
b111101 &
0#
#127
1#
#128
b10111110 %
b10111110 '
b10111110 )
b111110 &
0#
#129
1#
#130
b10111111 %
b10111111 '
b10111111 )
b111111 &
0#
#131
1#
#132
b11000000 %
b11000000 '
b11000000 )
b1000000 &
0#
#133
b11111110 !
b11111110 *
1#
#134
b11000001 %
b11000001 '
b11000001 )
b1000001 &
0#
#135
b11111110 "
b11111110 (
1#
#136
b11000010 %
b11000010 '
b11000010 )
b1000010 &
0#
#137
1#
#138
b11000011 %
b11000011 '
b11000011 )
b1000011 &
0#
#139
1#
#140
b11000100 %
b11000100 '
b11000100 )
b1000100 &
0#
#141
1#
#142
b11000101 %
b11000101 '
b11000101 )
b1000101 &
0#
#143
1#
#144
b11000110 %
b11000110 '
b11000110 )
b1000110 &
0#
#145
1#
#146
b11000111 %
b11000111 '
b11000111 )
b1000111 &
0#
#147
1#
#148
b11001000 %
b11001000 '
b11001000 )
b1001000 &
0#
#149
1#
#150
b11001001 %
b11001001 '
b11001001 )
b1001001 &
0#
#151
1#
#152
b11001010 %
b11001010 '
b11001010 )
b1001010 &
0#
#153
1#
#154
b11001011 %
b11001011 '
b11001011 )
b1001011 &
0#
#155
b11111101 "
b11111101 (
1#
#156
b11001100 %
b11001100 '
b11001100 )
b1001100 &
0#
#157
1#
#158
b11001101 %
b11001101 '
b11001101 )
b1001101 &
0#
#159
1#
#160
b11001110 %
b11001110 '
b11001110 )
b1001110 &
0#
#161
1#
#162
b11001111 %
b11001111 '
b11001111 )
b1001111 &
0#
#163
1#
#164
b11010000 %
b11010000 '
b11010000 )
b1010000 &
0#
#165
b11111101 !
b11111101 *
1#
#166
b11010001 %
b11010001 '
b11010001 )
b1010001 &
0#
#167
1#
#168
b11010010 %
b11010010 '
b11010010 )
b1010010 &
0#
#169
1#
#170
b11010011 %
b11010011 '
b11010011 )
b1010011 &
0#
#171
b11111100 "
b11111100 (
1#
#172
b11010100 %
b11010100 '
b11010100 )
b1010100 &
0#
#173
1#
#174
b11010101 %
b11010101 '
b11010101 )
b1010101 &
0#
#175
1#
#176
b11010110 %
b11010110 '
b11010110 )
b1010110 &
0#
#177
1#
#178
b11010111 %
b11010111 '
b11010111 )
b1010111 &
0#
#179
1#
#180
b11011000 %
b11011000 '
b11011000 )
b1011000 &
0#
#181
1#
#182
b11011001 %
b11011001 '
b11011001 )
b1011001 &
0#
#183
1#
#184
b11011010 %
b11011010 '
b11011010 )
b1011010 &
0#
#185
1#
#186
b11011011 %
b11011011 '
b11011011 )
b1011011 &
0#
#187
b11111011 "
b11111011 (
1#
#188
b11011100 %
b11011100 '
b11011100 )
b1011100 &
0#
#189
1#
#190
b11011101 %
b11011101 '
b11011101 )
b1011101 &
0#
#191
1#
#192
b11011110 %
b11011110 '
b11011110 )
b1011110 &
0#
#193
1#
#194
b11011111 %
b11011111 '
b11011111 )
b1011111 &
0#
#195
1#
#196
b11100000 %
b11100000 '
b11100000 )
b1100000 &
0#
#197
b11111100 !
b11111100 *
1#
#198
b11100001 %
b11100001 '
b11100001 )
b1100001 &
0#
#199
1#
#200
b11100010 %
b11100010 '
b11100010 )
b1100010 &
0#
#201
1#
#202
b11100011 %
b11100011 '
b11100011 )
b1100011 &
0#
#203
1#
#204
b11100100 %
b11100100 '
b11100100 )
b1100100 &
0#
#205
1#
#206
b11100101 %
b11100101 '
b11100101 )
b1100101 &
0#
#207
1#
#208
b11100110 %
b11100110 '
b11100110 )
b1100110 &
0#
#209
1#
#210
b11100111 %
b11100111 '
b11100111 )
b1100111 &
0#
#211
1#
#212
b11101000 %
b11101000 '
b11101000 )
b1101000 &
0#
#213
1#
#214
b11101001 %
b11101001 '
b11101001 )
b1101001 &
0#
#215
1#
#216
b11101010 %
b11101010 '
b11101010 )
b1101010 &
0#
#217
1#
#218
b11101011 %
b11101011 '
b11101011 )
b1101011 &
0#
#219
1#
#220
b11101100 %
b11101100 '
b11101100 )
b1101100 &
0#
#221
1#
#222
b11101101 %
b11101101 '
b11101101 )
b1101101 &
0#
#223
1#
#224
b11101110 %
b11101110 '
b11101110 )
b1101110 &
0#
#225
1#
#226
b11101111 %
b11101111 '
b11101111 )
b1101111 &
0#
#227
1#
#228
b11110000 %
b11110000 '
b11110000 )
b1110000 &
0#
#229
b11111011 !
b11111011 *
1#
#230
b11110001 %
b11110001 '
b11110001 )
b1110001 &
0#
#231
1#
#232
b11110010 %
b11110010 '
b11110010 )
b1110010 &
0#
#233
1#
#234
b11110011 %
b11110011 '
b11110011 )
b1110011 &
0#
#235
b11111100 "
b11111100 (
1#
#236
b11110100 %
b11110100 '
b11110100 )
b1110100 &
0#
#237
b11111100 !
b11111100 *
1#
#238
b11110101 %
b11110101 '
b11110101 )
b1110101 &
0#
#239
1#
#240
b11110110 %
b11110110 '
b11110110 )
b1110110 &
0#
#241
1#
#242
b11110111 %
b11110111 '
b11110111 )
b1110111 &
0#
#243
1#
#244
b11111000 %
b11111000 '
b11111000 )
b1111000 &
0#
#245
b11111101 "
b11111101 (
b11111101 !
b11111101 *
1#
#246
b11111001 %
b11111001 '
b11111001 )
b1111001 &
0#
#247
1#
#248
b11111010 %
b11111010 '
b11111010 )
b1111010 &
0#
#249
1#
#250
b11111011 %
b11111011 '
b11111011 )
b1111011 &
0#
#251
b11111110 "
b11111110 (
1#
#252
b11111100 %
b11111100 '
b11111100 )
b1111100 &
0#
#253
b11111110 !
b11111110 *
1#
#254
b11111101 %
b11111101 '
b11111101 )
b1111101 &
0#
#255
b11111111 "
b11111111 (
1#
#256
b11111110 %
b11111110 '
b11111110 )
b1111110 &
0#
#257
1#
#258
b11111111 %
b11111111 '
b11111111 )
b1111111 &
0#
#259
b0 "
b0 (
1#
#260
b0 %
b0 '
b0 )
b10000000 &
0#
#261
b0 !
b0 *
1#
#262
b1 %
b1 '
b1 )
b10000001 &
0#
#263
b1 "
b1 (
b1 !
b1 *
1#
#264
b10 %
b10 '
b10 )
b10000010 &
0#
#265
b10 !
b10 *
1#
#266
b11 %
b11 '
b11 )
b10000011 &
0#
#267
b10 "
b10 (
b11 !
b11 *
1#
#268
b100 %
b100 '
b100 )
b10000100 &
0#
#269
b100 !
b100 *
1#
#270
b101 %
b101 '
b101 )
b10000101 &
0#
#271
b11 "
b11 (
b101 !
b101 *
1#
#272
b110 %
b110 '
b110 )
b10000110 &
0#
#273
b110 !
b110 *
1#
#274
b111 %
b111 '
b111 )
b10000111 &
0#
#275
b100 "
b100 (
b111 !
b111 *
1#
#276
b1000 %
b1000 '
b1000 )
b10001000 &
0#
#277
b101 "
b101 (
b1000 !
b1000 *
1#
#278
b1001 %
b1001 '
b1001 )
b10001001 &
0#
#279
b1001 !
b1001 *
1#
#280
b1010 %
b1010 '
b1010 )
b10001010 &
0#
#281
b110 "
b110 (
b1010 !
b1010 *
1#
#282
b1011 %
b1011 '
b1011 )
b10001011 &
0#
#283
b111 "
b111 (
b1011 !
b1011 *
1#
#284
b1100 %
b1100 '
b1100 )
b10001100 &
0#
#285
b1000 "
b1000 (
b1100 !
b1100 *
1#
#286
b1101 %
b1101 '
b1101 )
b10001101 &
0#
#287
b1001 "
b1001 (
b1101 !
b1101 *
1#
#288
b1110 %
b1110 '
b1110 )
b10001110 &
0#
#289
b1110 !
b1110 *
1#
#290
b1111 %
b1111 '
b1111 )
b10001111 &
0#
#291
b1010 "
b1010 (
b1111 !
b1111 *
1#
#292
b10000 %
b10000 '
b10000 )
b10010000 &
0#
#293
b1011 "
b1011 (
b10000 !
b10000 *
1#
#294
b10001 %
b10001 '
b10001 )
b10010001 &
0#
#295
b1100 "
b1100 (
b10001 !
b10001 *
1#
#296
b10010 %
b10010 '
b10010 )
b10010010 &
0#
#297
b1101 "
b1101 (
b10010 !
b10010 *
1#
#298
b10011 %
b10011 '
b10011 )
b10010011 &
0#
#299
b1110 "
b1110 (
b10011 !
b10011 *
1#
#300
b10100 %
b10100 '
b10100 )
b10010100 &
0#
#301
b1111 "
b1111 (
b10100 !
b10100 *
1#
#302
b10101 %
b10101 '
b10101 )
b10010101 &
0#
#303
b10000 "
b10000 (
b10101 !
b10101 *
1#
#304
b10110 %
b10110 '
b10110 )
b10010110 &
0#
#305
b10001 "
b10001 (
b10110 !
b10110 *
1#
#306
b10111 %
b10111 '
b10111 )
b10010111 &
0#
#307
b10010 "
b10010 (
b10111 !
b10111 *
1#
#308
b11000 %
b11000 '
b11000 )
b10011000 &
0#
#309
b10011 "
b10011 (
b11000 !
b11000 *
1#
#310
b11001 %
b11001 '
b11001 )
b10011001 &
0#
#311
b10100 "
b10100 (
b11001 !
b11001 *
1#
#312
b11010 %
b11010 '
b11010 )
b10011010 &
0#
#313
b10101 "
b10101 (
b11010 !
b11010 *
1#
#314
b11011 %
b11011 '
b11011 )
b10011011 &
0#
#315
b10110 "
b10110 (
b11011 !
b11011 *
1#
#316
b11100 %
b11100 '
b11100 )
b10011100 &
0#
#317
b10111 "
b10111 (
b11100 !
b11100 *
1#
#318
b11101 %
b11101 '
b11101 )
b10011101 &
0#
#319
b11000 "
b11000 (
b11101 !
b11101 *
1#
#320
b11110 %
b11110 '
b11110 )
b10011110 &
0#
#321
b11001 "
b11001 (
b11110 !
b11110 *
1#
#322
b11111 %
b11111 '
b11111 )
b10011111 &
0#
#323
b11010 "
b11010 (
b11111 !
b11111 *
1#
#324
b100000 %
b100000 '
b100000 )
b10100000 &
0#
#325
b11011 "
b11011 (
b100000 !
b100000 *
1#
#326
b100001 %
b100001 '
b100001 )
b10100001 &
0#
#327
b11100 "
b11100 (
b100001 !
b100001 *
1#
#328
b100010 %
b100010 '
b100010 )
b10100010 &
0#
#329
b11101 "
b11101 (
b100010 !
b100010 *
1#
#330
b100011 %
b100011 '
b100011 )
b10100011 &
0#
#331
b11110 "
b11110 (
b100011 !
b100011 *
1#
#332
b100100 %
b100100 '
b100100 )
b10100100 &
0#
#333
b11111 "
b11111 (
b100100 !
b100100 *
1#
#334
b100101 %
b100101 '
b100101 )
b10100101 &
0#
#335
b100000 "
b100000 (
b100101 !
b100101 *
1#
#336
b100110 %
b100110 '
b100110 )
b10100110 &
0#
#337
b100010 "
b100010 (
b100110 !
b100110 *
1#
#338
b100111 %
b100111 '
b100111 )
b10100111 &
0#
#339
b100011 "
b100011 (
b100111 !
b100111 *
1#
#340
b101000 %
b101000 '
b101000 )
b10101000 &
0#
#341
b100100 "
b100100 (
b101000 !
b101000 *
1#
#342
b101001 %
b101001 '
b101001 )
b10101001 &
0#
#343
b100101 "
b100101 (
b101001 !
b101001 *
1#
#344
b101010 %
b101010 '
b101010 )
b10101010 &
0#
#345
b100110 "
b100110 (
b101010 !
b101010 *
1#
#346
b101011 %
b101011 '
b101011 )
b10101011 &
0#
#347
b100111 "
b100111 (
b101011 !
b101011 *
1#
#348
b101100 %
b101100 '
b101100 )
b10101100 &
0#
#349
b101000 "
b101000 (
b101100 !
b101100 *
1#
#350
b101101 %
b101101 '
b101101 )
b10101101 &
0#
#351
b101001 "
b101001 (
b101101 !
b101101 *
1#
#352
b101110 %
b101110 '
b101110 )
b10101110 &
0#
#353
b101011 "
b101011 (
b101110 !
b101110 *
1#
#354
b101111 %
b101111 '
b101111 )
b10101111 &
0#
#355
b101100 "
b101100 (
b101111 !
b101111 *
1#
#356
b110000 %
b110000 '
b110000 )
b10110000 &
0#
#357
b101101 "
b101101 (
b110000 !
b110000 *
1#
#358
b110001 %
b110001 '
b110001 )
b10110001 &
0#
#359
b101110 "
b101110 (
b110001 !
b110001 *
1#
#360
b110010 %
b110010 '
b110010 )
b10110010 &
0#
#361
b101111 "
b101111 (
b110010 !
b110010 *
1#
#362
b110011 %
b110011 '
b110011 )
b10110011 &
0#
#363
b110000 "
b110000 (
b110011 !
b110011 *
1#
#364
b110100 %
b110100 '
b110100 )
b10110100 &
0#
#365
b110001 "
b110001 (
b110100 !
b110100 *
1#
#366
b110101 %
b110101 '
b110101 )
b10110101 &
0#
#367
b110010 "
b110010 (
b110101 !
b110101 *
1#
#368
b110110 %
b110110 '
b110110 )
b10110110 &
0#
#369
b110100 "
b110100 (
b110110 !
b110110 *
1#
#370
b110111 %
b110111 '
b110111 )
b10110111 &
0#
#371
b110101 "
b110101 (
b110111 !
b110111 *
1#
#372
b111000 %
b111000 '
b111000 )
b10111000 &
0#
#373
b110110 "
b110110 (
b111000 !
b111000 *
1#
#374
b111001 %
b111001 '
b111001 )
b10111001 &
0#
#375
b110111 "
b110111 (
b111001 !
b111001 *
1#
#376
b111010 %
b111010 '
b111010 )
b10111010 &
0#
#377
b111000 "
b111000 (
b111010 !
b111010 *
1#
#378
b111011 %
b111011 '
b111011 )
b10111011 &
0#
#379
b111001 "
b111001 (
b111011 !
b111011 *
1#
#380
b111100 %
b111100 '
b111100 )
b10111100 &
0#
#381
b111010 "
b111010 (
b111100 !
b111100 *
1#
#382
b111101 %
b111101 '
b111101 )
b10111101 &
0#
#383
b111011 "
b111011 (
b111101 !
b111101 *
1#
#384
b111110 %
b111110 '
b111110 )
b10111110 &
0#
#385
b111100 "
b111100 (
b111110 !
b111110 *
1#
#386
b111111 %
b111111 '
b111111 )
b10111111 &
0#
#387
b111101 "
b111101 (
b111111 !
b111111 *
1#
#388
b1000000 %
b1000000 '
b1000000 )
b11000000 &
0#
#389
b111111 "
b111111 (
b1000000 !
b1000000 *
1#
#390
b1000001 %
b1000001 '
b1000001 )
b11000001 &
0#
#391
b1000000 "
b1000000 (
b1000001 !
b1000001 *
1#
#392
b1000010 %
b1000010 '
b1000010 )
b11000010 &
0#
#393
b1000001 "
b1000001 (
b1000010 !
b1000010 *
1#
#394
b1000011 %
b1000011 '
b1000011 )
b11000011 &
0#
#395
b1000010 "
b1000010 (
b1000011 !
b1000011 *
1#
#396
b1000100 %
b1000100 '
b1000100 )
b11000100 &
0#
#397
b1000011 "
b1000011 (
b1000100 !
b1000100 *
1#
#398
b1000101 %
b1000101 '
b1000101 )
b11000101 &
0#
#399
b1000100 "
b1000100 (
b1000101 !
b1000101 *
1#
#400
b1000110 %
b1000110 '
b1000110 )
b11000110 &
0#
#401
b1000101 "
b1000101 (
b1000110 !
b1000110 *
1#
#402
b1000111 %
b1000111 '
b1000111 )
b11000111 &
0#
#403
b1000110 "
b1000110 (
b1000111 !
b1000111 *
1#
#404
b1001000 %
b1001000 '
b1001000 )
b11001000 &
0#
#405
b1000111 "
b1000111 (
b1001000 !
b1001000 *
1#
#406
b1001001 %
b1001001 '
b1001001 )
b11001001 &
0#
#407
b1001000 "
b1001000 (
b1001001 !
b1001001 *
1#
#408
b1001010 %
b1001010 '
b1001010 )
b11001010 &
0#
#409
b1001001 "
b1001001 (
b1001010 !
b1001010 *
1#
#410
b1001011 %
b1001011 '
b1001011 )
b11001011 &
0#
#411
b1001010 "
b1001010 (
b1001011 !
b1001011 *
1#
#412
b1001100 %
b1001100 '
b1001100 )
b11001100 &
0#
#413
b1001011 "
b1001011 (
b1001100 !
b1001100 *
1#
#414
b1001101 %
b1001101 '
b1001101 )
b11001101 &
0#
#415
b1001100 "
b1001100 (
b1001101 !
b1001101 *
1#
#416
b1001110 %
b1001110 '
b1001110 )
b11001110 &
0#
