activation_functions/sigmoid/piecewise_linear.v
module sigmoid_piecewise (
    input clk,
    input reset,
    input signed [7:0] x_in,  // Q3.5 input (-4 to 4)
    output reg [7:0] y_out    // Q0.8 output (0 to 1)
);

    // Precomputed constants (Q0.8 format for slopes and offsets)
    // Now the slopes are scaled as powers of 2 to avoid multiplication
    // Each slope is represented as shift constants

    // Slope for -4 to -2 (a = 0.03125 -> shift by 5)
    localparam signed [7:0] SHIFT_1 = 1;    
    localparam signed [7:0] OFFSET_1 = 8'd5;  // Offset for -4 to -2 (b = 0.0 -> Q0.8 = 5)

    // Slope for -2 to -1 (a = 0.125 -> shift by 3)
    localparam signed [7:0] SHIFT_2 = 0;    
    localparam signed [7:0] OFFSET_2 = 8'd32;  // Offset for -2 to -1 (b = 0.125 -> Q0.8 = 32)

    // Slope for -1 to 1 (a = 0.25 -> shift by 2)
    localparam signed [7:0] SHIFT_3 = 1;   
    localparam signed [7:0] OFFSET_3 = 8'd69;  // Offset for -1 to 1 (b = 0.375 -> Q0.8 = 96)

    // Slope for 1 to 2 (a = 0.125 -> shift by 3)
    localparam signed [7:0] SHIFT_4 = 0;    
    localparam signed [7:0] OFFSET_4 = 8'd187; // Offset for 1 to 2 (b = 0.625 -> Q0.8 = 160)

    // Slope for 2 to 4 (a = 0.03125 -> shift by 5)
    localparam signed [7:0] SHIFT_5 = 1;    
    localparam signed [7:0] OFFSET_5 = 8'd225; // Offset for 2 to 4 (b = 0.75 -> Q0.8 = 192)
   
    reg [7:0] y_s;

    //registering output
    always @(posedge clk or negedge reset) begin
      if(~reset) begin
        y_out <= 0;
      end
      else begin
        y_out <= y_s;
      end
    end 

    always @(*) begin
        if (x_in <= -128) begin
            y_s = 8'd0;  // Output saturates to 0 for x <= -4
        end else if (x_in >= 127) begin
            y_s = 8'd255; // Output saturates to 1 for x >= 4
        end else if (x_in < -64) begin  // Segment 1: -4 to -2
            y_s = ((x_in + 128) >>> SHIFT_1) + OFFSET_1;
        end else if (x_in < -32) begin  // Segment 2: -2 to -1
            y_s = ((x_in + 64) >>> SHIFT_2) + OFFSET_2;
        end else if (x_in < 32) begin  // Segment 3: -1 to 1
            y_s = ((x_in + 32) <<< SHIFT_3) + OFFSET_3;
        end else if (x_in < 64) begin  // Segment 4: 1 to 2
            y_s = ((x_in - 32) >>> SHIFT_4) + OFFSET_4;
        end else begin  // Segment 5: 2 to 4
            y_s = ((x_in - 64) >>> SHIFT_5) + OFFSET_5;
        end
    end
endmodule

activation_functions/tanh/tanh_using_sigmoid.v
module tanh_using_sigmoid (
    input clk,
    input reset,
    input signed [7:0] x_in,      // Q3.5 input
    output reg signed [7:0] y_out    // Q0.7 output
);
    wire signed [7:0] scaled_input;  // Q3.5 scaled input
    wire signed [7:0] sigmoid_out;  // Q0.8 output of sigmoid
    wire signed [8:0] scaled_sigmoid; // Q1.8 intermediate scaling
    wire signed [7:0] tanh_temp;     // Q0.8 temporary result

    wire signed [7:0] y_s;

    // Scale input (x_in * 2)
    assign scaled_input = x_in <<< 1; // Multiply by 2, maintain Q3.5

    // Pass scaled_input to sigmoid
    sigmoid_piecewise u1 (
        .x_in(scaled_input),
        .clk(clk),
        .reset(reset), 
        .y_out(sigmoid_out)
    );

    // Scale sigmoid output (sigmoid_out * 2) -> Q1.8
    assign scaled_sigmoid = {sigmoid_out, 1'b0}; // Multiply by 2 (Q0.8 to Q1.8)

    // Subtract 1 to shift the range [-1, 1]
    assign tanh_temp = scaled_sigmoid[8:1] - 8'd128; // Convert to Q0.7 and subtract 1

    // Assign final result
    assign y_s = tanh_temp;
    
    

    //register the output
    always @(*) begin
      if(x_in <= -64) begin
        y_out = -8'd128;
      end else if(x_in >= 64) begin
        y_out = 8'd127;
      end
      else begin
        y_out = y_s;
      end
    end 

endmodule

activation_functions/gelu/gelu_using_tanh.v
module gelu_using_tanh (
    input clk,
    input reset,
    input signed [7:0] x_in,  // Q3.5 input (-4 to 4)
    output reg signed [7:0] y_out // Q3.5 output (-4 to 4)
);

    // Parameters for fixed-point scaling in Q3.5
    localparam signed [7:0] SQRT_2_PI = 8'd25;   // ? sqrt(2/pi) scaled to Q3.5
    localparam signed [7:0] COEFF = 8'd1;        // ? 0.044715 scaled to Q3.5

    wire signed [7:0] x_cube;       // x^3 in Q3.5
    wire signed [7:0] tanh_input;   // Input to the tanh block in Q3.5
    wire signed [7:0] tanh_output;  // Output from the tanh block in Q0.7
    reg signed [7:0] scaled_tanh;   // tanh_output scaled to Q3.5
    reg signed [7:0] result;        // GELU result (intermediate calculation)

    // Instantiate tanh block
    tanh_using_sigmoid tanh_inst (
        .clk(clk),
        .reset(reset),
        .x_in(tanh_input),
        .y_out(tanh_output)
    );

    // Compute x^3
    assign x_cube = (x_in * x_in * x_in) >>> 5; // Q3.5 * Q3.5 * Q3.5 -> Q3.5

    // Compute input to tanh: SQRT_2_PI * (x + COEFF * x^3)
    assign tanh_input = (SQRT_2_PI * (x_in + ((COEFF * x_cube) >>> 5))) >>> 5; // Q3.5 -> Q3.5

    // Scale tanh_output (Q0.7) to Q3.5
    always @(*) begin
        scaled_tanh = tanh_output >>> 2; // Convert Q0.7 to Q3.5 (shift left by 2 bits)
    end

    // Compute GELU: 0.5 * x * (1 + scaled_tanh)
    always @(*) begin
            result = (x_in * (32 + scaled_tanh)) >>> 5; // Q3.5 * Q3.5 -> Q3.5
            y_out = result >>> 1; // Divide by 2
    end

endmodule

activation_functions/gelu/lut_based_gelu.v
module gelu_lut (
    input clk,
    input reset,
    input signed [7:0] x_in,  // Q3.5 input (-4 to 4)
    output reg signed [7:0] y_out    // Q3.5 output (-4 to 4)
);

     reg signed [7:0] LUT [255:0];

    //registering output
    always @(posedge clk or negedge reset) begin
      if(~reset) begin
        y_out <= 0;
      end
      else begin
        y_out <= LUT['sd128+x_in];
      end
    end 


    always @(posedge clk or negedge reset) begin
      LUT[0]<=0;
      LUT[1]<=0;
      LUT[2]<=0;
      LUT[3]<=0;
      LUT[4]<=0;
      LUT[5]<=0;
      LUT[6]<=0;
      LUT[7]<=0;
      LUT[8]<=0;
      LUT[9]<=0;
      LUT[10]<=0;
      LUT[11]<=0;
      LUT[12]<=0;
      LUT[13]<=0;
      LUT[14]<=0;
      LUT[15]<=0;
      LUT[16]<=0;
      LUT[17]<=0;
      LUT[18]<=0;
      LUT[19]<=0;
      LUT[20]<=0;
      LUT[21]<=0;
      LUT[22]<=0;
      LUT[23]<=0;
      LUT[24]<=0;
      LUT[25]<=0;
      LUT[26]<=0;
      LUT[27]<=0;
      LUT[28]<=0;
      LUT[29]<=0;
      LUT[30]<=0;
      LUT[31]<=0;
      LUT[32]<=0;
      LUT[33]<=0;
      LUT[34]<=0;
      LUT[35]<=0;
      LUT[36]<=0;
      LUT[37]<=0;
      LUT[38]<=0;
      LUT[39]<=0;
      LUT[40]<=0;
      LUT[41]<=0;
      LUT[42]<=0;
      LUT[43]<=0;
      LUT[44]<=0;
      LUT[45]<=0;
      LUT[46]<=0;
      LUT[47]<=0;
      LUT[48]<=0;
      LUT[49]<=-1;
      LUT[50]<=-1;
      LUT[51]<=-1;
      LUT[52]<=-1;
      LUT[53]<=-1;
      LUT[54]<=-1;
      LUT[55]<=-1;
      LUT[56]<=-1;
      LUT[57]<=-1;
      LUT[58]<=-1;
      LUT[59]<=-1;
      LUT[60]<=-1;
      LUT[61]<=-1;
      LUT[62]<=-1;
      LUT[63]<=-1;
      LUT[64]<=-1;
      LUT[65]<=-2;
      LUT[66]<=-2;
      LUT[67]<=-2;
      LUT[68]<=-2;
      LUT[69]<=-2;
      LUT[70]<=-2;
      LUT[71]<=-2;
      LUT[72]<=-2;
      LUT[73]<=-2;
      LUT[74]<=-2;
      LUT[75]<=-3;
      LUT[76]<=-3;
      LUT[77]<=-3;
      LUT[78]<=-3;
      LUT[79]<=-3;
      LUT[80]<=-3;
      LUT[81]<=-3;
      LUT[82]<=-3;
      LUT[83]<=-4;
      LUT[84]<=-4;
      LUT[85]<=-4;
      LUT[86]<=-4;
      LUT[87]<=-4;
      LUT[88]<=-4;
      LUT[89]<=-4;
      LUT[90]<=-4;
      LUT[91]<=-5;
      LUT[92]<=-5;
      LUT[93]<=-5;
      LUT[94]<=-5;
      LUT[95]<=-5;
      LUT[96]<=-5;
      LUT[97]<=-5;
      LUT[98]<=-5;
      LUT[99]<=-5;
      LUT[100]<=-5;
      LUT[101]<=-5;
      LUT[102]<=-5;
      LUT[103]<=-5;
      LUT[104]<=-5;
      LUT[105]<=-5;
      LUT[106]<=-5;
      LUT[107]<=-5;
      LUT[108]<=-5;
      LUT[109]<=-5;
      LUT[110]<=-5;
      LUT[111]<=-5;
      LUT[112]<=-5;
      LUT[113]<=-5;
      LUT[114]<=-5;
      LUT[115]<=-4;
      LUT[116]<=-4;
      LUT[117]<=-4;
      LUT[118]<=-4;
      LUT[119]<=-4;
      LUT[120]<=-3;
      LUT[121]<=-3;
      LUT[122]<=-3;
      LUT[123]<=-2;
      LUT[124]<=-2;
      LUT[125]<=-1;
      LUT[126]<=-1;
      LUT[127]<=0;
      LUT[128]<=0;
      LUT[129]<=1;
      LUT[130]<=1;
      LUT[131]<=2;
      LUT[132]<=2;
      LUT[133]<=3;
      LUT[134]<=3;
      LUT[135]<=4;
      LUT[136]<=5;
      LUT[137]<=5;
      LUT[138]<=6;
      LUT[139]<=7;
      LUT[140]<=8;
      LUT[141]<=9;
      LUT[142]<=9;
      LUT[143]<=10;
      LUT[144]<=11;
      LUT[145]<=12;
      LUT[146]<=13;
      LUT[147]<=14;
      LUT[148]<=15;
      LUT[149]<=16;
      LUT[150]<=17;
      LUT[151]<=18;
      LUT[152]<=19;
      LUT[153]<=20;
      LUT[154]<=21;
      LUT[155]<=22;
      LUT[156]<=23;
      LUT[157]<=24;
      LUT[158]<=25;
      LUT[159]<=26;
      LUT[160]<=27;
      LUT[161]<=28;
      LUT[162]<=29;
      LUT[163]<=30;
      LUT[164]<=31;
      LUT[165]<=32;
      LUT[166]<=34;
      LUT[167]<=35;
      LUT[168]<=36;
      LUT[169]<=37;
      LUT[170]<=38;
      LUT[171]<=39;
      LUT[172]<=40;
      LUT[173]<=41;
      LUT[174]<=43;
      LUT[175]<=44;
      LUT[176]<=45;
      LUT[177]<=46;
      LUT[178]<=47;
      LUT[179]<=48;
      LUT[180]<=49;
      LUT[181]<=50;
      LUT[182]<=52;
      LUT[183]<=53;
      LUT[184]<=54;
      LUT[185]<=55;
      LUT[186]<=56;
      LUT[187]<=57;
      LUT[188]<=58;
      LUT[189]<=59;
      LUT[190]<=60;
      LUT[191]<=61;
      LUT[192]<=63;
      LUT[193]<=64;
      LUT[194]<=65;
      LUT[195]<=66;
      LUT[196]<=67;
      LUT[197]<=68;
      LUT[198]<=69;
      LUT[199]<=70;
      LUT[200]<=71;
      LUT[201]<=72;
      LUT[202]<=73;
      LUT[203]<=74;
      LUT[204]<=75;
      LUT[205]<=76;
      LUT[206]<=77;
      LUT[207]<=78;
      LUT[208]<=80;
      LUT[209]<=81;
      LUT[210]<=82;
      LUT[211]<=83;
      LUT[212]<=84;
      LUT[213]<=85;
      LUT[214]<=86;
      LUT[215]<=87;
      LUT[216]<=88;
      LUT[217]<=89;
      LUT[218]<=90;
      LUT[219]<=91;
      LUT[220]<=92;
      LUT[221]<=93;
      LUT[222]<=94;
      LUT[223]<=95;
      LUT[224]<=96;
      LUT[225]<=97;
      LUT[226]<=98;
      LUT[227]<=99;
      LUT[228]<=100;
      LUT[229]<=101;
      LUT[230]<=102;
      LUT[231]<=103;
      LUT[232]<=104;
      LUT[233]<=105;
      LUT[234]<=106;
      LUT[235]<=107;
      LUT[236]<=108;
      LUT[237]<=109;
      LUT[238]<=110;
      LUT[239]<=111;
      LUT[240]<=112;
      LUT[241]<=113;
      LUT[242]<=114;
      LUT[243]<=115;
      LUT[244]<=116;
      LUT[245]<=117;
      LUT[246]<=118;
      LUT[247]<=119;
      LUT[248]<=120;
      LUT[249]<=121;
      LUT[250]<=122;
      LUT[251]<=123;
      LUT[252]<=124;
      LUT[253]<=125;
      LUT[254]<=126;
      LUT[255]<=127;
      LUT[255]<=127;
    end

endmodule

activation_functions/gelu/piecewise_linear_gelu.v
module gelu_piecewise (
    input clk,
    input reset,
    input signed [7:0] x_in,  // Q3.5 input (-4 to 4)
    output reg signed [7:0] y_out // Q0.7 output (-128 to 127)
);

    // Constants for the piecewise linear approximation (using shifts and adds)
    //for range -2.5 to -0.5 
    localparam signed [7:0] SHIFT_1 = 4;   
    localparam signed [7:0] OFFSET_1 = -8'd1;

    localparam signed [7:0] SHIFT_2 = 2;    
    localparam signed [7:0] OFFSET_2 = -8'd5;  

    always @(posedge clk or negedge reset) begin
        if (~reset) begin
            y_out <= 8'd0;  // Reset to 0
        end else begin
            // Piecewise function for tanh approximation
            if (x_in <= -80) begin //x<-2.5
                y_out <= 0; 
            end else if (x_in < -16) begin //x< -0.5
                y_out <= OFFSET_1 - ((x_in + 80) >>> SHIFT_1); // Use shift to approximate slope
            end else if (x_in < 0) begin
                y_out <= ((x_in + 16) >>> SHIFT_2) + OFFSET_2; // Use shift to approximate slope
            end else begin
                y_out <= x_in;  // x>0
            end
        end
    end
endmodule

activation_functions/gelu/gelu_tb.v
module test_gelu;
    reg signed [7:0] x;
    wire signed [7:0] y_piecewise, y_lut, y_using_tanh;
    integer i;
    reg reset;
    reg clk;

    gelu_piecewise instance_piecewise (
        .x_in(x),
        .y_out(y_piecewise),
        .clk(clk),
        .reset(reset)
    );

    gelu_lut instance_lut (
        .x_in(x),
        .y_out(y_lut),
        .clk(clk),
        .reset(reset)
    );

    gelu_using_tanh instance_using_tanh (
        .x_in(x),
        .y_out(y_using_tanh),
        .clk(clk),
        .reset(reset)
    );


   //clock generation
   initial begin
    clk = 0;
    forever begin #0.5 clk = ~clk; end
   end   
   

    initial begin
      $dumpfile("test_tanh.vcd");
      $dumpvars(0,test_gelu);

      $display("Begin Reset");
      reset = 0; 
      repeat(2)@(posedge clk);
      reset = 1;
      $display("End reset");

      $display("Testing Tanh Module:");
      $display("  x\t\tLUT\t\tPieceWise Linear\t\t");
      @(negedge clk)
      for (i = 0; i < 256; i = i + 1) begin
          x = (i - 128); // Test inputs: -128, -96, ..., 127
          @(negedge clk)
          $display("%d\t\t%d\t\t%d\t\t", x, y_lut, y_piecewise);
      end 
        $finish;
    end

endmodule

activation_functions/gelu/test_tanh.vcd
$date
	Tue Dec  3 17:53:12 2024
$end
$version
	Icarus Verilog
$end
$timescale
	1s
$end
$scope module test_gelu $end
$var wire 8 ! y_using_tanh [7:0] $end
$var wire 8 " y_piecewise [7:0] $end
$var wire 8 # y_lut [7:0] $end
$var reg 1 $ clk $end
$var reg 1 % reset $end
$var reg 8 & x [7:0] $end
$var integer 32 ' i [31:0] $end
$scope module instance_lut $end
$var wire 1 $ clk $end
$var wire 1 % reset $end
$var wire 8 ( x_in [7:0] $end
$var reg 8 ) y_out [7:0] $end
$upscope $end
$scope module instance_piecewise $end
$var wire 1 $ clk $end
$var wire 1 % reset $end
$var wire 8 * x_in [7:0] $end
$var reg 8 + y_out [7:0] $end
$upscope $end
$scope module instance_using_tanh $end
$var wire 1 $ clk $end
$var wire 1 % reset $end
$var wire 8 , x_in [7:0] $end
$var wire 8 - x_cube [7:0] $end
$var wire 8 . tanh_output [7:0] $end
$var wire 8 / tanh_input [7:0] $end
$var reg 8 0 result [7:0] $end
$var reg 8 1 scaled_tanh [7:0] $end
$var reg 8 2 y_out [7:0] $end
$scope module tanh_inst $end
$var wire 1 $ clk $end
$var wire 1 % reset $end
$var wire 8 3 x_in [7:0] $end
$var wire 8 4 y_s [7:0] $end
$var wire 8 5 tanh_temp [7:0] $end
$var wire 8 6 sigmoid_out [7:0] $end
$var wire 9 7 scaled_sigmoid [8:0] $end
$var wire 8 8 scaled_input [7:0] $end
$var reg 8 9 y_out [7:0] $end
$scope module u1 $end
$var wire 1 $ clk $end
$var wire 1 % reset $end
$var wire 8 : x_in [7:0] $end
$var reg 8 ; y_out [7:0] $end
$var reg 8 < y_s [7:0] $end
$upscope $end
$upscope $end
$upscope $end
$upscope $end
$enddefinitions $end
#0
$dumpvars
bx <
b0 ;
bx0 :
b10000000 9
bx0 8
b0 7
b0 6
b10000000 5
b10000000 4
bx 3
bx 2
b11100000 1
bx 0
bx /
b10000000 .
bx -
bx ,
bx +
bx *
b0 )
bx (
bx '
bx &
0%
0$
b0 #
bx "
bx !
$end
#1
b0 "
b0 +
1$
#2
0$
#3
bx 1
bx .
bx 9
bx 4
bx 5
bx #
bx )
bx0 7
bx 6
bx ;
bx "
bx +
1%
1$
#4
b1110101 <
b11111000 8
b11111000 :
b11111100 /
b11111100 3
b0 -
b10000000 &
b10000000 (
b10000000 *
b10000000 ,
b0 '
0$
#5
b11000110 !
b11000110 2
b10001100 0
b11111101 1
b11110101 .
b11110101 9
b11110101 4
b11110101 5
b11101010 7
b1110101 6
b1110101 ;
b0 #
b0 )
b0 "
b0 +
1$
#6
b11111100 -
b10000001 &
b10000001 (
b10000001 *
b10000001 ,
b1 '
0$
#7
1$
#8
b1111001 <
b11111010 8
b11111010 :
b11111101 /
b11111101 3
b10001101 0
b0 -
b10000010 &
b10000010 (
b10000010 *
b10000010 ,
b10 '
0$
#9
b11000100 !
b11000100 2
b10001001 0
b11111110 1
b11111001 .
b11111001 9
b11111001 4
b11111001 5
b11110010 7
b1111001 6
b1111001 ;
1$
#10
b1111001 <
b11111010 8
b11111010 :
b11000101 !
b11000101 2
b10001010 0
b11111100 -
b11111101 /
b11111101 3
b10000011 &
b10000011 (
b10000011 *
b10000011 ,
b11 '
0$
#11
1$
#12
b10000001 <
b11111110 8
b11111110 :
b10001011 0
b10 -
b11111111 /
b11111111 3
b10000100 &
b10000100 (
b10000100 *
b10000100 ,
b100 '
0$
#13
b11000010 !
b11000010 2
b10000100 0
b0 1
b1 .
b1 9
b1 4
b1 5
b100000010 7
b10000001 6
b10000001 ;
1$
#14
b10000101 0
b11111111 -
b10000101 &
b10000101 (
b10000101 *
b10000101 ,
b101 '
0$
#15
1$
#16
b11000011 !
b11000011 2
b10000110 0
b11111110 -
b10000110 &
b10000110 (
b10000110 *
b10000110 ,
b110 '
0$
#17
1$
#18
b10000101 <
b0 8
b0 :
b10000111 0
b0 /
b0 3
b10000111 &
b10000111 (
b10000111 *
b10000111 ,
b111 '
0$
#19
b11000001 !
b11000001 2
b10000011 0
b1 1
b101 .
b101 9
b101 4
b101 5
b100001010 7
b10000101 6
b10000101 ;
1$
#20
b10001101 <
b100 8
b100 :
b11000010 !
b11000010 2
b10000100 0
b0 -
b10 /
b10 3
b10001000 &
b10001000 (
b10001000 *
b10001000 ,
b1000 '
0$
#21
b111110 !
b111110 2
b1111100 0
b11 1
b1101 .
b1101 9
b1101 4
b1101 5
b100011010 7
b10001101 6
b10001101 ;
1$
#22
b10010001 <
b110 8
b110 :
b1111101 0
b10 -
b11 /
b11 3
b10001001 &
b10001001 (
b10001001 *
b10001001 ,
b1001 '
0$
#23
b111101 !
b111101 2
b1111010 0
b100 1
b10001 .
b10001 9
b10001 4
b10001 5
b100100010 7
b10010001 6
b10010001 ;
1$
#24
b1111011 0
b11111111 -
b10001010 &
b10001010 (
b10001010 *
b10001010 ,
b1010 '
0$
#25
1$
#26
b111110 !
b111110 2
b1111100 0
b11111101 -
b10001011 &
b10001011 (
b10001011 *
b10001011 ,
b1011 '
0$
#27
1$
#28
b1110101 <
b11111000 8
b11111000 :
b1111101 0
b11111110 -
b11111100 /
b11111100 3
b10001100 &
b10001100 (
b10001100 *
b10001100 ,
b1100 '
0$
#29
b11001011 !
b11001011 2
b10010110 0
b11111101 1
b11110101 .
b11110101 9
b11110101 4
b11110101 5
b11101010 7
b1110101 6
b1110101 ;
1$
#30
b1111101 <
b11111100 8
b11111100 :
b10010111 0
b0 -
b11111110 /
b11111110 3
b10001101 &
b10001101 (
b10001101 *
b10001101 ,
b1101 '
0$
#31
b11001000 !
b11001000 2
b10010000 0
b11111111 1
b11111101 .
b11111101 9
b11111101 4
b11111101 5
b11111010 7
b1111101 6
b1111101 ;
1$
#32
b10010001 0
b11111101 -
b10001110 &
b10001110 (
b10001110 *
b10001110 ,
b1110 '
0$
#33
1$
#34
b11001001 !
b11001001 2
b10010010 0
b10001111 &
b10001111 (
b10001111 *
b10001111 ,
b1111 '
0$
#35
1$
#36
b10000101 <
b0 8
b0 :
b10010011 0
b0 -
b0 /
b0 3
b10010000 &
b10010000 (
b10010000 *
b10010000 ,
b10000 '
0$
#37
b11000110 !
b11000110 2
b10001100 0
b1 1
b101 .
b101 9
b101 4
b101 5
b100001010 7
b10000101 6
b10000101 ;
1$
#38
b10000101 <
b0 8
b0 :
b10001101 0
b11111101 -
b0 /
b0 3
b10010001 &
b10010001 (
b10010001 *
b10010001 ,
b10001 '
0$
#39
1$
#40
b10001001 <
b10 8
b10 :
b11000111 !
b11000111 2
b10001110 0
b11111110 -
b1 /
b1 3
b10010010 &
b10010010 (
b10010010 *
b10010010 ,
b10010 '
0$
#41
b11000101 !
b11000101 2
b10001011 0
b10 1
b1001 .
b1001 9
b1001 4
b1001 5
b100010010 7
b10001001 6
b10001001 ;
1$
#42
b10001101 <
b100 8
b100 :
b11000110 !
b11000110 2
b10001100 0
b10 -
b10 /
b10 3
b10010011 &
b10010011 (
b10010011 *
b10010011 ,
b10011 '
0$
#43
b11000100 !
b11000100 2
b10001000 0
b11 1
b1101 .
b1101 9
b1101 4
b1101 5
b100011010 7
b10001101 6
b10001101 ;
1$
#44
b10010001 <
b110 8
b110 :
b10001001 0
b11 /
b11 3
b10010100 &
b10010100 (
b10010100 *
b10010100 ,
b10100 '
0$
#45
b11000011 !
b11000011 2
b10000110 0
b100 1
b10001 .
b10001 9
b10001 4
b10001 5
b100100010 7
b10010001 6
b10010001 ;
1$
#46
b10010001 <
b110 8
b110 :
b10000111 0
b11111101 -
b11 /
b11 3
b10010101 &
b10010101 (
b10010101 *
b10010101 ,
b10101 '
0$
#47
1$
#48
b1110101 <
b11111000 8
b11111000 :
b11000100 !
b11000100 2
b10001000 0
b11111100 -
b11111100 /
b11111100 3
b10010110 &
b10010110 (
b10010110 *
b10010110 ,
b10110 '
0$
#49
b11001111 !
b11001111 2
b10011111 0
b11111101 1
b11110101 .
b11110101 9
b11110101 4
b11110101 5
b11101010 7
b1110101 6
b1110101 ;
1$
#50
b1111001 <
b11111010 8
b11111010 :
b11010000 !
b11010000 2
b10100000 0
b0 -
b11111101 /
b11111101 3
b10010111 &
b10010111 (
b10010111 *
b10010111 ,
b10111 '
0$
#51
b11001110 !
b11001110 2
b10011101 0
b11111110 1
b11111001 .
b11111001 9
b11111001 4
b11111001 5
b11110010 7
b1111001 6
b1111001 ;
1$
#52
b1111101 <
b11111100 8
b11111100 :
b11001111 !
b11001111 2
b10011110 0
b11111110 /
b11111110 3
b10011000 &
b10011000 (
b10011000 *
b10011000 ,
b11000 '
0$
#53
b11001101 !
b11001101 2
b10011011 0
b11111111 1
b11111101 .
b11111101 9
b11111101 4
b11111101 5
b11111010 7
b1111101 6
b1111101 ;
1$
#54
b1111101 <
b11111100 8
b11111100 :
b11001110 !
b11001110 2
b10011100 0
b11111100 -
b11111110 /
b11111110 3
b10011001 &
b10011001 (
b10011001 *
b10011001 ,
b11001 '
0$
#55
1$
#56
b10000001 <
b11111110 8
b11111110 :
b10011101 0
b11111101 -
b11111111 /
b11111111 3
b10011010 &
b10011010 (
b10011010 *
b10011010 ,
b11010 '
0$
#57
b11001101 !
b11001101 2
b10011010 0
b0 1
b1 .
b1 9
b1 4
b1 5
b100000010 7
b10000001 6
b10000001 ;
1$
#58
b10001001 <
b10 8
b10 :
b10011011 0
b11 -
b1 /
b1 3
b10011011 &
b10011011 (
b10011011 *
b10011011 ,
b11011 '
0$
#59
b11001010 !
b11001010 2
b10010100 0
b10 1
b1001 .
b1001 9
b1001 4
b1001 5
b100010010 7
b10001001 6
b10001001 ;
1$
#60
b10010101 0
b11111110 -
b10011100 &
b10011100 (
b10011100 *
b10011100 ,
b11100 '
0$
#61
1$
#62
b11001011 !
b11001011 2
b10010110 0
b10011101 &
b10011101 (
b10011101 *
b10011101 ,
b11101 '
0$
#63
1$
#64
b10010001 <
b110 8
b110 :
b10010111 0
b11 -
b11 /
b11 3
b10011110 &
b10011110 (
b10011110 *
b10011110 ,
b11110 '
0$
#65
b11001000 !
b11001000 2
b10010001 0
b100 1
b10001 .
b10001 9
b10001 4
b10001 5
b100100010 7
b10010001 6
b10010001 ;
1$
#66
b10010001 <
b110 8
b110 :
b11001001 !
b11001001 2
b10010010 0
b11111110 -
b11 /
b11 3
b10011111 &
b10011111 (
b10011111 *
b10011111 ,
b11111 '
0$
#67
1$
#68
b1111001 <
b11111010 8
b11111010 :
b11001010 !
b11001010 2
b10010100 0
b0 -
b11111101 /
b11111101 3
b10100000 &
b10100000 (
b10100000 *
b10100000 ,
b100000 '
0$
#69
b11010011 !
b11010011 2
b10100110 0
b11111110 1
b11111001 .
b11111001 9
b11111001 4
b11111001 5
b11110010 7
b1111001 6
b1111001 ;
1$
#70
b11111111 -
b10100001 &
b10100001 (
b10100001 *
b10100001 ,
b100001 '
0$
#71
1$
#72
b10100111 0
b11111100 -
b10100010 &
b10100010 (
b10100010 *
b10100010 ,
b100010 '
0$
#73
1$
#74
b1111101 <
b11111100 8
b11111100 :
b11010100 !
b11010100 2
b10101000 0
b11111111 -
b11111110 /
b11111110 3
b10100011 &
b10100011 (
b10100011 *
b10100011 ,
b100011 '
0$
#75
b11010010 !
b11010010 2
b10100101 0
b11111111 1
b11111101 .
b11111101 9
b11111101 4
b11111101 5
b11111010 7
b1111101 6
b1111101 ;
1$
#76
b10000101 <
b0 8
b0 :
b11010011 !
b11010011 2
b10100110 0
b10 -
b0 /
b0 3
b10100100 &
b10100100 (
b10100100 *
b10100100 ,
b100100 '
0$
#77
b11010000 !
b11010000 2
b10100001 0
b1 1
b101 .
b101 9
b101 4
b101 5
b100001010 7
b10000101 6
b10000101 ;
1$
#78
b11010001 !
b11010001 2
b10100010 0
b10100101 &
b10100101 (
b10100101 *
b10100101 ,
b100101 '
0$
#79
1$
#80
b10001001 <
b10 8
b10 :
b10100011 0
b1 /
b1 3
b10100110 &
b10100110 (
b10100110 *
b10100110 ,
b100110 '
0$
#81
b11010000 !
b11010000 2
b10100000 0
b10 1
b1001 .
b1001 9
b1001 4
b1001 5
b100010010 7
b10001001 6
b10001001 ;
1$
#82
b10001101 <
b100 8
b100 :
b10100001 0
b1 -
b10 /
b10 3
b10100111 &
b10100111 (
b10100111 *
b10100111 ,
b100111 '
0$
#83
b11001111 !
b11001111 2
b10011110 0
b11 1
b1101 .
b1101 9
b1101 4
b1101 5
b100011010 7
b10001101 6
b10001101 ;
1$
#84
b10010001 <
b110 8
b110 :
b10011111 0
b0 -
b11 /
b11 3
b10101000 &
b10101000 (
b10101000 *
b10101000 ,
b101000 '
0$
#85
b11001110 !
b11001110 2
b10011101 0
b100 1
b10001 .
b10001 9
b10001 4
b10001 5
b100100010 7
b10010001 6
b10010001 ;
1$
#86
b10010001 <
b110 8
b110 :
b11001111 !
b11001111 2
b10011110 0
b11111101 -
b11 /
b11 3
b10101001 &
b10101001 (
b10101001 *
b10101001 ,
b101001 '
0$
#87
1$
#88
b1110101 <
b11111000 8
b11111000 :
b10011111 0
b11 -
b11111100 /
b11111100 3
b10101010 &
b10101010 (
b10101010 *
b10101010 ,
b101010 '
0$
#89
b11011001 !
b11011001 2
b10110010 0
b11111101 1
b11110101 .
b11110101 9
b11110101 4
b11110101 5
b11101010 7
b1110101 6
b1110101 ;
1$
#90
b1111001 <
b11111010 8
b11111010 :
b0 -
b11111101 /
b11111101 3
b10101011 &
b10101011 (
b10101011 *
b10101011 ,
b101011 '
0$
#91
b11011000 !
b11011000 2
b10110000 0
b11111110 1
b11111001 .
b11111001 9
b11111001 4
b11111001 5
b11110010 7
b1111001 6
b1111001 ;
1$
#92
b1111001 <
b11111010 8
b11111010 :
b10110001 0
b11111110 -
b11111101 /
b11111101 3
b10101100 &
b10101100 (
b10101100 *
b10101100 ,
b101100 '
0$
#93
1$
#94
b10000001 <
b11111110 8
b11111110 :
b11011001 !
b11011001 2
b10110010 0
b11 -
b11111111 /
b11111111 3
b10101101 &
b10101101 (
b10101101 *
b10101101 ,
b101101 '
0$
#95
b11010110 !
b11010110 2
b10101101 0
b0 1
b1 .
b1 9
b1 4
b1 5
b100000010 7
b10000001 6
b10000001 ;
1$
#96
b11010111 !
b11010111 2
b10101110 0
b1 -
b10101110 &
b10101110 (
b10101110 *
b10101110 ,
b101110 '
0$
#97
1$
#98
b10000101 <
b0 8
b0 :
b10101111 0
b0 -
b0 /
b0 3
b10101111 &
b10101111 (
b10101111 *
b10101111 ,
b101111 '
0$
#99
b11010110 !
b11010110 2
b10101100 0
b1 1
b101 .
b101 9
b101 4
b101 5
b100001010 7
b10000101 6
b10000101 ;
1$
#100
b10001001 <
b10 8
b10 :
b10101101 0
b1 /
b1 3
b10110000 &
b10110000 (
b10110000 *
b10110000 ,
b110000 '
0$
#101
b11010101 !
b11010101 2
b10101011 0
b10 1
b1001 .
b1001 9
b1001 4
b1001 5
b100010010 7
b10001001 6
b10001001 ;
1$
#102
b10001101 <
b100 8
b100 :
b11010110 !
b11010110 2
b10101100 0
b10 /
b10 3
b10110001 &
b10110001 (
b10110001 *
b10110001 ,
b110001 '
0$
#103
b11010100 !
b11010100 2
b10101001 0
b11 1
b1101 .
b1101 9
b1101 4
b1101 5
b11111111 #
b11111111 )
b100011010 7
b10001101 6
b10001101 ;
b11111111 "
b11111111 +
1$
