activation_functions/sigmoid/piecewise_linear.v
module sigmoid_piecewise (
    input clk,
    input reset,
    input signed [7:0] x_in,  // Q3.5 input (-4 to 4)
    output reg [7:0] y_out    // Q0.8 output (0 to 1)
);

    // Precomputed constants (Q0.8 format for slopes and offsets)
    // Now the slopes are scaled as powers of 2 to avoid multiplication
    // Each slope is represented as shift constants

    // Slope for -4 to -2 (a = 0.03125 -> shift by 5)
    localparam signed [7:0] SHIFT_1 = 1;    
    localparam signed [7:0] OFFSET_1 = 8'd5;  // Offset for -4 to -2 (b = 0.0 -> Q0.8 = 5)

    // Slope for -2 to -1 (a = 0.125 -> shift by 3)
    localparam signed [7:0] SHIFT_2 = 0;    
    localparam signed [7:0] OFFSET_2 = 8'd32;  // Offset for -2 to -1 (b = 0.125 -> Q0.8 = 32)

    // Slope for -1 to 1 (a = 0.25 -> shift by 2)
    localparam signed [7:0] SHIFT_3 = 1;   
    localparam signed [7:0] OFFSET_3 = 8'd69;  // Offset for -1 to 1 (b = 0.375 -> Q0.8 = 96)

    // Slope for 1 to 2 (a = 0.125 -> shift by 3)
    localparam signed [7:0] SHIFT_4 = 0;    
    localparam signed [7:0] OFFSET_4 = 8'd187; // Offset for 1 to 2 (b = 0.625 -> Q0.8 = 160)

    // Slope for 2 to 4 (a = 0.03125 -> shift by 5)
    localparam signed [7:0] SHIFT_5 = 1;    
    localparam signed [7:0] OFFSET_5 = 8'd225; // Offset for 2 to 4 (b = 0.75 -> Q0.8 = 192)
   
    reg [7:0] y_s;

    //registering output
    always @(posedge clk or negedge reset) begin
      if(~reset) begin
        y_out <= 0;
      end
      else begin
        y_out <= y_s;
      end
    end 

    always @(*) begin
        if (x_in <= -128) begin
            y_s = 8'd0;  // Output saturates to 0 for x <= -4
        end else if (x_in >= 127) begin
            y_s = 8'd255; // Output saturates to 1 for x >= 4
        end else if (x_in < -64) begin  // Segment 1: -4 to -2
            y_s = ((x_in + 128) >>> SHIFT_1) + OFFSET_1;
        end else if (x_in < -32) begin  // Segment 2: -2 to -1
            y_s = ((x_in + 64) >>> SHIFT_2) + OFFSET_2;
        end else if (x_in < 32) begin  // Segment 3: -1 to 1
            y_s = ((x_in + 32) <<< SHIFT_3) + OFFSET_3;
        end else if (x_in < 64) begin  // Segment 4: 1 to 2
            y_s = ((x_in - 32) >>> SHIFT_4) + OFFSET_4;
        end else begin  // Segment 5: 2 to 4
            y_s = ((x_in - 64) >>> SHIFT_5) + OFFSET_5;
        end
    end
endmodule

activation_functions/tanh/tanh_using_sigmoid.v
module tanh_using_sigmoid (
    input clk,
    input reset,
    input signed [7:0] x_in,      // Q3.5 input
    output reg signed [7:0] y_out    // Q0.7 output
);
    wire signed [7:0] scaled_input;  // Q3.5 scaled input
    wire signed [7:0] sigmoid_out;  // Q0.8 output of sigmoid
    wire signed [8:0] scaled_sigmoid; // Q1.8 intermediate scaling
    wire signed [7:0] tanh_temp;     // Q0.8 temporary result

    wire signed [7:0] y_s;

    // Scale input (x_in * 2)
    assign scaled_input = x_in <<< 1; // Multiply by 2, maintain Q3.5

    // Pass scaled_input to sigmoid
    sigmoid_piecewise u1 (
        .x_in(scaled_input),
        .clk(clk),
        .reset(reset), 
        .y_out(sigmoid_out)
    );

    // Scale sigmoid output (sigmoid_out * 2) -> Q1.8
    assign scaled_sigmoid = {sigmoid_out, 1'b0}; // Multiply by 2 (Q0.8 to Q1.8)

    // Subtract 1 to shift the range [-1, 1]
    assign tanh_temp = scaled_sigmoid[8:1] - 8'd128; // Convert to Q0.7 and subtract 1

    // Assign final result
    assign y_s = tanh_temp;

    //register the output
    always @(posedge clk or negedge reset) begin
      if(~reset) begin
        y_out <= 0;
      end
      else begin
        if(x_in <= -64) begin
          y_out <= -8'd128;
        end else if(x_in >= 64) begin
          y_out <= 8'd127;
        end
        else begin
          y_out <= y_s;
        end
      end
    end 

endmodule

activation_functions/tanh/lut_based_tanh.v
module tanh_lut (
    input clk,
    input reset,
    input signed [7:0] x_in,  // Q3.5 input (-4 to 4)
    output reg signed [7:0] y_out    // Q0.7 output (-1 to 1)
);

     reg signed [7:0] LUT [255:0];

    //registering output
    always @(posedge clk or negedge reset) begin
      if(~reset) begin
        y_out <= 0;
      end
      else begin
        y_out <= LUT['sd128+x_in];
      end
    end 


    always @(posedge clk or negedge reset) begin
      LUT[0]<= -128;
      LUT[1]<= -128;
      LUT[2]<= -128;
      LUT[3]<= -128;
      LUT[4]<= -128;
      LUT[5]<= -128;
      LUT[6]<= -128;
      LUT[7]<= -128;
      LUT[8]<= -128;
      LUT[9]<= -128;
      LUT[10]<= -128;
      LUT[11]<= -128;
      LUT[12]<= -128;
      LUT[13]<= -128;
      LUT[14]<= -128;
      LUT[15]<= -128;
      LUT[16]<= -128;
      LUT[17]<= -128;
      LUT[18]<= -128;
      LUT[19]<= -128;
      LUT[20]<= -128;
      LUT[21]<= -128;
      LUT[22]<= -128;
      LUT[23]<= -128;
      LUT[24]<= -128;
      LUT[25]<= -128;
      LUT[26]<= -128;
      LUT[27]<= -128;
      LUT[28]<= -128;
      LUT[29]<= -127;
      LUT[30]<= -127;
      LUT[31]<= -127;
      LUT[32]<= -127;
      LUT[33]<= -127;
      LUT[34]<= -127;
      LUT[35]<= -127;
      LUT[36]<= -127;
      LUT[37]<= -127;
      LUT[38]<= -127;
      LUT[39]<= -127;
      LUT[40]<= -127;
      LUT[41]<= -127;
      LUT[42]<= -127;
      LUT[43]<= -127;
      LUT[44]<= -127;
      LUT[45]<= -127;
      LUT[46]<= -126;
      LUT[47]<= -126;
      LUT[48]<= -126;
      LUT[49]<= -126;
      LUT[50]<= -126;
      LUT[51]<= -126;
      LUT[52]<= -126;
      LUT[53]<= -126;
      LUT[54]<= -126;
      LUT[55]<= -125;
      LUT[56]<= -125;
      LUT[57]<= -125;
      LUT[58]<= -125;
      LUT[59]<= -125;
      LUT[60]<= -124;
      LUT[61]<= -124;
      LUT[62]<= -124;
      LUT[63]<= -124;
      LUT[64]<= -123;
      LUT[65]<= -123;
      LUT[66]<= -123;
      LUT[67]<= -122;
      LUT[68]<= -122;
      LUT[69]<= -122;
      LUT[70]<= -121;
      LUT[71]<= -121;
      LUT[72]<= -120;
      LUT[73]<= -120;
      LUT[74]<= -120;
      LUT[75]<= -119;
      LUT[76]<= -118;
      LUT[77]<= -118;
      LUT[78]<= -117;
      LUT[79]<= -117;
      LUT[80]<= -116;
      LUT[81]<= -115;
      LUT[82]<= -114;
      LUT[83]<= -113;
      LUT[84]<= -113;
      LUT[85]<= -112;
      LUT[86]<= -111;
      LUT[87]<= -110;
      LUT[88]<= -109;
      LUT[89]<= -107;
      LUT[90]<= -106;
      LUT[91]<= -105;
      LUT[92]<= -104;
      LUT[93]<= -102;
      LUT[94]<= -101;
      LUT[95]<= -99;
      LUT[96]<= -97;
      LUT[97]<= -96;
      LUT[98]<= -94;
      LUT[99]<= -92;
      LUT[100]<= -90;
      LUT[101]<= -88;
      LUT[102]<= -86;
      LUT[103]<= -84;
      LUT[104]<= -81;
      LUT[105]<= -79;
      LUT[106]<= -76;
      LUT[107]<= -74;
      LUT[108]<= -71;
      LUT[109]<= -68;
      LUT[110]<= -65;
      LUT[111]<= -62;
      LUT[112]<= -59;
      LUT[113]<= -56;
      LUT[114]<= -53;
      LUT[115]<= -49;
      LUT[116]<= -46;
      LUT[117]<= -42;
      LUT[118]<= -39;
      LUT[119]<= -35;
      LUT[120]<= -31;
      LUT[121]<= -28;
      LUT[122]<= -24;
      LUT[123]<= -20;
      LUT[124]<= -16;
      LUT[125]<= -12;
      LUT[126]<= -8;
      LUT[127]<= -4;
      LUT[128]<= 0;
      LUT[129]<= 4;
      LUT[130]<= 8;
      LUT[131]<= 12;
      LUT[132]<= 16;
      LUT[133]<= 20;
      LUT[134]<= 24;
      LUT[135]<= 28;
      LUT[136]<= 31;
      LUT[137]<= 35;
      LUT[138]<= 39;
      LUT[139]<= 42;
      LUT[140]<= 46;
      LUT[141]<= 49;
      LUT[142]<= 53;
      LUT[143]<= 56;
      LUT[144]<= 59;
      LUT[145]<= 62;
      LUT[146]<= 65;
      LUT[147]<= 68;
      LUT[148]<= 71;
      LUT[149]<= 74;
      LUT[150]<= 76;
      LUT[151]<= 79;
      LUT[152]<= 81;
      LUT[153]<= 84;
      LUT[154]<= 86;
      LUT[155]<= 88;
      LUT[156]<= 90;
      LUT[157]<= 92;
      LUT[158]<= 94;
      LUT[159]<= 96;
      LUT[160]<= 97;
      LUT[161]<= 99;
      LUT[162]<= 101;
      LUT[163]<= 102;
      LUT[164]<= 104;
      LUT[165]<= 105;
      LUT[166]<= 106;
      LUT[167]<= 107;
      LUT[168]<= 109;
      LUT[169]<= 110;
      LUT[170]<= 111;
      LUT[171]<= 112;
      LUT[172]<= 113;
      LUT[173]<= 113;
      LUT[174]<= 114;
      LUT[175]<= 115;
      LUT[176]<= 116;
      LUT[177]<= 117;
      LUT[178]<= 117;
      LUT[179]<= 118;
      LUT[180]<= 118;
      LUT[181]<= 119;
      LUT[182]<= 120;
      LUT[183]<= 120;
      LUT[184]<= 120;
      LUT[185]<= 121;
      LUT[186]<= 121;
      LUT[187]<= 122;
      LUT[188]<= 122;
      LUT[189]<= 122;
      LUT[190]<= 123;
      LUT[191]<= 123;
      LUT[192]<= 123;
      LUT[193]<= 124;
      LUT[194]<= 124;
      LUT[195]<= 124;
      LUT[196]<= 124;
      LUT[197]<= 125;
      LUT[198]<= 125;
      LUT[199]<= 125;
      LUT[200]<= 125;
      LUT[201]<= 125;
      LUT[202]<= 126;
      LUT[203]<= 126;
      LUT[204]<= 126;
      LUT[205]<= 126;
      LUT[206]<= 126;
      LUT[207]<= 126;
      LUT[208]<= 126;
      LUT[209]<= 126;
      LUT[210]<= 126;
      LUT[211]<= 127;
      LUT[212]<= 127;
      LUT[213]<= 127;
      LUT[214]<= 127;
      LUT[215]<= 127;
      LUT[216]<= 127;
      LUT[217]<= 127;
      LUT[218]<= 127;
      LUT[219]<= 127;
      LUT[220]<= 127;
      LUT[221]<= 127;
      LUT[222]<= 127;
      LUT[223]<= 127;
      LUT[224]<= 127;
      LUT[225]<= 127;
      LUT[226]<= 127;
      LUT[227]<= 127;
      LUT[228]<= 127;
      LUT[229]<= 127;
      LUT[230]<= 127;
      LUT[231]<= 127;
      LUT[232]<= 127;
      LUT[233]<= 127;
      LUT[234]<= 127;
      LUT[235]<= 127;
      LUT[236]<= 127;
      LUT[237]<= 127;
      LUT[238]<= 127;
      LUT[239]<= 127;
      LUT[240]<= 127;
      LUT[241]<= 127;
      LUT[242]<= 127;
      LUT[243]<= 127;
      LUT[244]<= 127;
      LUT[245]<= 127;
      LUT[246]<= 127;
      LUT[247]<= 127;
      LUT[248]<= 127;
      LUT[249]<= 127;
      LUT[250]<= 127;
      LUT[251]<= 127;
      LUT[252]<= 127;
      LUT[253]<= 127;
      LUT[254]<= 127;
      LUT[255]<= 127;
    end

endmodule

activation_functions/tanh/piecewise_linear_tanh.v
module tanh_piecewise (
    input clk,
    input reset,
    input signed [7:0] x_in,  // Q3.5 input (-4 to 4)
    output reg signed [7:0] y_out // Q0.7 output (-128 to 127)
);

    // Constants for the piecewise linear approximation (using shifts and adds)
    
    // For the range -3 to -2
    localparam signed [7:0] SHIFT_1 = 4;   
    localparam signed [7:0] OFFSET_1 = -8'd128;

    // For the range -2 to -1
    localparam signed [7:0] SHIFT_2 = 0;    
    localparam signed [7:0] OFFSET_2 = -8'd123;  

    // For the range -1 to 1
    localparam signed [7:0] SHIFT_3 = 1;    
    localparam signed [7:0] OFFSET_3 = -8'd97;  
 

    // For the range 1 to 2
    localparam signed [7:0] SHIFT_4 = 0;    
    localparam signed [7:0] OFFSET_4 = 8'd97;
   
    // For the range 2 to 3
    localparam signed [7:0] SHIFT_5 = 4;    
    localparam signed [7:0] OFFSET_5 = 8'd123;  
 
    localparam signed [7:0] OFFSET_6 = 8'd127; 

    always @(posedge clk or posedge reset) begin
        if (~reset) begin
            y_out <= 8'd0;  // Reset to 0
        end else begin
            // Piecewise function for tanh approximation
            if (x_in <= -96) begin
                y_out <= OFFSET_1; 
            end else if (x_in < -64) begin
                y_out <= ((x_in + 128) >>> SHIFT_1) + OFFSET_1; // Use shift to approximate slope
            end else if (x_in < -32) begin
                y_out <= ((x_in + 64) >>> SHIFT_2) + OFFSET_2; // Use shift to approximate slope
            end else if (x_in < 0) begin
                y_out <= ((x_in + 32) <<< SHIFT_3) + ((x_in + 32) >>> SHIFT_3) + OFFSET_3; // Use shift to approximate slope
            end else if (x_in < 32) begin
                y_out <= ((x_in) <<< SHIFT_3) + ((x_in + 32) >>> SHIFT_3); // Use shift to approximate slope
            end else if (x_in < 64) begin
                y_out <= ((x_in - 32) >>> SHIFT_4) + OFFSET_4; // Use shift to approximate slope
            end else if (x_in < 96) begin
                y_out <= ((x_in - 64) >>> SHIFT_5) + OFFSET_5; // Use shift to approximate slope
            end else begin
                y_out <= OFFSET_6;  // Default to 1 if x > 3
            end
        end
    end
endmodule

activation_functions/tanh/tanh_tb.v
module test_tanh;
    reg signed [7:0] x;
    wire signed [7:0] y_piecewise, y_lut, y_sigmoid;
    integer i;
    reg reset;
    reg clk;

    tanh_piecewise instance_piecewise (
        .x_in(x),
        .y_out(y_piecewise),
        .clk(clk),
        .reset(reset)
    );

    tanh_lut instance_lut (
        .x_in(x),
        .y_out(y_lut),
        .clk(clk),
        .reset(reset)
    );

    tanh_using_sigmoid instance_using_sigmoid (
        .x_in(x),
        .y_out(y_sigmoid),
        .clk(clk),
        .reset(reset)
    );


   //clock generation
   initial begin
    clk = 0;
    forever begin #0.5 clk = ~clk; end
   end   
   

    initial begin
      $dumpfile("test_tanh.vcd");
      $dumpvars(0,test_tanh);

      $display("Begin Reset");
      reset = 0; 
      repeat(2)@(posedge clk);
      reset = 1;
      $display("End reset");

      $display("Testing Tanh Module:");
      $display("  x\t\tLUT\t\tPieceWise Linear\tusing sigmoid");
      @(negedge clk)
      for (i = 0; i < 256; i = i + 1) begin
          x = (i - 128); // Test inputs: -128, -96, ..., 127
          @(negedge clk)
          $display("%d\t\t%d\t\t%d\t\t%d\t\t", x, y_lut, y_piecewise,y_sigmoid);
      end 
        $finish;
    end
endmodule

activation_functions/tanh/test_tanh.vcd
$date
	Tue Dec  3 22:59:20 2024
$end
$version
	Icarus Verilog
$end
$timescale
	1s
$end
$scope module test_tanh $end
$var wire 8 ! y_sigmoid [7:0] $end
$var wire 8 " y_piecewise [7:0] $end
$var wire 8 # y_lut [7:0] $end
$var reg 1 $ clk $end
$var reg 1 % reset $end
$var reg 8 & x [7:0] $end
$var integer 32 ' i [31:0] $end
$scope module instance_lut $end
$var wire 1 $ clk $end
$var wire 1 % reset $end
$var wire 8 ( x_in [7:0] $end
$var reg 8 ) y_out [7:0] $end
$upscope $end
$scope module instance_piecewise $end
$var wire 1 $ clk $end
$var wire 1 % reset $end
$var wire 8 * x_in [7:0] $end
$var reg 8 + y_out [7:0] $end
$upscope $end
$scope module instance_using_sigmoid $end
$var wire 1 $ clk $end
$var wire 1 % reset $end
$var wire 8 , x_in [7:0] $end
$var wire 8 - y_s [7:0] $end
$var wire 8 . tanh_temp [7:0] $end
$var wire 8 / sigmoid_out [7:0] $end
$var wire 9 0 scaled_sigmoid [8:0] $end
$var wire 8 1 scaled_input [7:0] $end
$var reg 8 2 y_out [7:0] $end
$scope module u1 $end
$var wire 1 $ clk $end
$var wire 1 % reset $end
$var wire 8 3 x_in [7:0] $end
$var reg 8 4 y_out [7:0] $end
$var reg 8 5 y_s [7:0] $end
$upscope $end
$upscope $end
$upscope $end
$enddefinitions $end
#0
$dumpvars
bx 5
b0 4
bx0 3
b10000000 2
bx0 1
b0 0
b0 /
b10000000 .
b10000000 -
bx ,
bx +
bx *
b0 )
bx (
bx '
bx &
0%
0$
b0 #
bx "
b10000000 !
$end
#1
b0 "
b0 +
1$
#2
0$
#3
bx !
bx 2
bx -
bx .
bx #
bx )
bx0 0
bx /
bx 4
b1111111 "
b1111111 +
1%
1$
#4
b10000101 5
b10000000 !
b10000000 2
b0 1
b0 3
b10000000 &
b10000000 (
b10000000 *
b10000000 ,
b0 '
0$
#5
b101 -
b101 .
b100001010 0
b10000101 /
b10000101 4
b10000000 #
b10000000 )
b10000000 "
b10000000 +
1$
#6
b10001001 5
b10 1
b10 3
b10000001 &
b10000001 (
b10000001 *
b10000001 ,
b1 '
0$
#7
b1001 -
b1001 .
b100010010 0
b10001001 /
b10001001 4
1$
#8
b10001101 5
b100 1
b100 3
b10000010 &
b10000010 (
b10000010 *
b10000010 ,
b10 '
0$
#9
b1101 -
b1101 .
b100011010 0
b10001101 /
b10001101 4
1$
#10
b10010001 5
b110 1
b110 3
b10000011 &
b10000011 (
b10000011 *
b10000011 ,
b11 '
0$
#11
b10001 -
b10001 .
b100100010 0
b10010001 /
b10010001 4
1$
#12
b10010101 5
b1000 1
b1000 3
b10000100 &
b10000100 (
b10000100 *
b10000100 ,
b100 '
0$
#13
b10101 -
b10101 .
b100101010 0
b10010101 /
b10010101 4
1$
#14
b10011001 5
b1010 1
b1010 3
b10000101 &
b10000101 (
b10000101 *
b10000101 ,
b101 '
0$
#15
b11001 -
b11001 .
b100110010 0
b10011001 /
b10011001 4
1$
#16
b10011101 5
b1100 1
b1100 3
b10000110 &
b10000110 (
b10000110 *
b10000110 ,
b110 '
0$
#17
b11101 -
b11101 .
b100111010 0
b10011101 /
b10011101 4
1$
#18
b10100001 5
b1110 1
b1110 3
b10000111 &
b10000111 (
b10000111 *
b10000111 ,
b111 '
0$
#19
b100001 -
b100001 .
b101000010 0
b10100001 /
b10100001 4
1$
#20
b10100101 5
b10000 1
b10000 3
b10001000 &
b10001000 (
b10001000 *
b10001000 ,
b1000 '
0$
#21
b100101 -
b100101 .
b101001010 0
b10100101 /
b10100101 4
1$
#22
b10101001 5
b10010 1
b10010 3
b10001001 &
b10001001 (
b10001001 *
b10001001 ,
b1001 '
0$
#23
b101001 -
b101001 .
b101010010 0
b10101001 /
b10101001 4
1$
#24
b10101101 5
b10100 1
b10100 3
b10001010 &
b10001010 (
b10001010 *
b10001010 ,
b1010 '
0$
#25
b101101 -
b101101 .
b101011010 0
b10101101 /
b10101101 4
1$
#26
b10110001 5
b10110 1
b10110 3
b10001011 &
b10001011 (
b10001011 *
b10001011 ,
b1011 '
0$
#27
b110001 -
b110001 .
b101100010 0
b10110001 /
b10110001 4
1$
#28
b10110101 5
b11000 1
b11000 3
b10001100 &
b10001100 (
b10001100 *
b10001100 ,
b1100 '
0$
#29
b110101 -
b110101 .
b101101010 0
b10110101 /
b10110101 4
1$
#30
b10111001 5
b11010 1
b11010 3
b10001101 &
b10001101 (
b10001101 *
b10001101 ,
b1101 '
0$
#31
b111001 -
b111001 .
b101110010 0
b10111001 /
b10111001 4
1$
#32
b10111101 5
b11100 1
b11100 3
b10001110 &
b10001110 (
b10001110 *
b10001110 ,
b1110 '
0$
#33
b111101 -
b111101 .
b101111010 0
b10111101 /
b10111101 4
1$
#34
b11000001 5
b11110 1
b11110 3
b10001111 &
b10001111 (
b10001111 *
b10001111 ,
b1111 '
0$
#35
b1000001 -
b1000001 .
b110000010 0
b11000001 /
b11000001 4
1$
#36
b10111011 5
b100000 1
b100000 3
b10010000 &
b10010000 (
b10010000 *
b10010000 ,
b10000 '
0$
#37
b111011 -
b111011 .
b101110110 0
b10111011 /
b10111011 4
1$
#38
b10111101 5
b100010 1
b100010 3
b10010001 &
b10010001 (
b10010001 *
b10010001 ,
b10001 '
0$
#39
b111101 -
b111101 .
b101111010 0
b10111101 /
b10111101 4
1$
#40
b10111111 5
b100100 1
b100100 3
b10010010 &
b10010010 (
b10010010 *
b10010010 ,
b10010 '
0$
#41
b111111 -
b111111 .
b101111110 0
b10111111 /
b10111111 4
1$
#42
b11000001 5
b100110 1
b100110 3
b10010011 &
b10010011 (
b10010011 *
b10010011 ,
b10011 '
0$
#43
b1000001 -
b1000001 .
b110000010 0
b11000001 /
b11000001 4
1$
#44
b11000011 5
b101000 1
b101000 3
b10010100 &
b10010100 (
b10010100 *
b10010100 ,
b10100 '
0$
#45
b1000011 -
b1000011 .
b110000110 0
b11000011 /
b11000011 4
1$
#46
b11000101 5
b101010 1
b101010 3
b10010101 &
b10010101 (
b10010101 *
b10010101 ,
b10101 '
0$
#47
b1000101 -
b1000101 .
b110001010 0
b11000101 /
b11000101 4
1$
#48
b11000111 5
b101100 1
b101100 3
b10010110 &
b10010110 (
b10010110 *
b10010110 ,
b10110 '
0$
#49
b1000111 -
b1000111 .
b110001110 0
b11000111 /
b11000111 4
1$
#50
b11001001 5
b101110 1
b101110 3
b10010111 &
b10010111 (
b10010111 *
b10010111 ,
b10111 '
0$
#51
b1001001 -
b1001001 .
b110010010 0
b11001001 /
b11001001 4
1$
#52
b11001011 5
b110000 1
b110000 3
b10011000 &
b10011000 (
b10011000 *
b10011000 ,
b11000 '
0$
#53
b1001011 -
b1001011 .
b110010110 0
b11001011 /
b11001011 4
1$
#54
b11001101 5
b110010 1
b110010 3
b10011001 &
b10011001 (
b10011001 *
b10011001 ,
b11001 '
0$
#55
b1001101 -
b1001101 .
b110011010 0
b11001101 /
b11001101 4
1$
#56
b11001111 5
b110100 1
b110100 3
b10011010 &
b10011010 (
b10011010 *
b10011010 ,
b11010 '
0$
#57
b1001111 -
b1001111 .
b110011110 0
b11001111 /
b11001111 4
1$
#58
b11010001 5
b110110 1
b110110 3
b10011011 &
b10011011 (
b10011011 *
b10011011 ,
b11011 '
0$
#59
b1010001 -
b1010001 .
b110100010 0
b11010001 /
b11010001 4
1$
#60
b11010011 5
b111000 1
b111000 3
b10011100 &
b10011100 (
b10011100 *
b10011100 ,
b11100 '
0$
#61
b1010011 -
b1010011 .
b110100110 0
b11010011 /
b11010011 4
1$
#62
b11010101 5
b111010 1
b111010 3
b10011101 &
b10011101 (
b10011101 *
b10011101 ,
b11101 '
0$
#63
b1010101 -
b1010101 .
b10000001 #
b10000001 )
b110101010 0
b11010101 /
b11010101 4
1$
#64
b11010111 5
b111100 1
b111100 3
b10011110 &
b10011110 (
b10011110 *
b10011110 ,
b11110 '
0$
#65
b1010111 -
b1010111 .
b110101110 0
b11010111 /
b11010111 4
1$
#66
b11011001 5
b111110 1
b111110 3
b10011111 &
b10011111 (
b10011111 *
b10011111 ,
b11111 '
0$
#67
b1011001 -
b1011001 .
b110110010 0
b11011001 /
b11011001 4
1$
#68
b11100001 5
b1000000 1
b1000000 3
b10100000 &
b10100000 (
b10100000 *
b10100000 ,
b100000 '
0$
#69
b1100001 -
b1100001 .
b111000010 0
b11100001 /
b11100001 4
1$
#70
b11100010 5
b1000010 1
b1000010 3
b10100001 &
b10100001 (
b10100001 *
b10100001 ,
b100001 '
0$
#71
b1100010 -
b1100010 .
b111000100 0
b11100010 /
b11100010 4
b10000010 "
b10000010 +
1$
#72
b11100011 5
b1000100 1
b1000100 3
b10100010 &
b10100010 (
b10100010 *
b10100010 ,
b100010 '
0$
#73
b1100011 -
b1100011 .
b111000110 0
b11100011 /
b11100011 4
1$
#74
b11100100 5
b1000110 1
b1000110 3
b10100011 &
b10100011 (
b10100011 *
b10100011 ,
b100011 '
0$
#75
b1100100 -
b1100100 .
b111001000 0
b11100100 /
b11100100 4
1$
#76
b11100101 5
b1001000 1
b1001000 3
b10100100 &
b10100100 (
b10100100 *
b10100100 ,
b100100 '
0$
#77
b1100101 -
b1100101 .
b111001010 0
b11100101 /
b11100101 4
1$
#78
b11100110 5
b1001010 1
b1001010 3
b10100101 &
b10100101 (
b10100101 *
b10100101 ,
b100101 '
0$
#79
b1100110 -
b1100110 .
b111001100 0
b11100110 /
b11100110 4
1$
#80
b11100111 5
b1001100 1
b1001100 3
b10100110 &
b10100110 (
b10100110 *
b10100110 ,
b100110 '
0$
#81
b1100111 -
b1100111 .
b111001110 0
b11100111 /
b11100111 4
1$
#82
b11101000 5
b1001110 1
b1001110 3
b10100111 &
b10100111 (
b10100111 *
b10100111 ,
b100111 '
0$
#83
b1101000 -
b1101000 .
b111010000 0
b11101000 /
b11101000 4
1$
#84
b11101001 5
b1010000 1
b1010000 3
b10101000 &
b10101000 (
b10101000 *
b10101000 ,
b101000 '
0$
#85
b1101001 -
b1101001 .
b111010010 0
b11101001 /
b11101001 4
1$
#86
b11101010 5
b1010010 1
b1010010 3
b10101001 &
b10101001 (
b10101001 *
b10101001 ,
b101001 '
0$
#87
b1101010 -
b1101010 .
b111010100 0
b11101010 /
b11101010 4
1$
#88
b11101011 5
b1010100 1
b1010100 3
b10101010 &
b10101010 (
b10101010 *
b10101010 ,
b101010 '
0$
#89
b1101011 -
b1101011 .
b111010110 0
b11101011 /
b11101011 4
1$
#90
b11101100 5
b1010110 1
b1010110 3
b10101011 &
b10101011 (
b10101011 *
b10101011 ,
b101011 '
0$
#91
b1101100 -
b1101100 .
b111011000 0
b11101100 /
b11101100 4
1$
#92
b11101101 5
b1011000 1
b1011000 3
b10101100 &
b10101100 (
b10101100 *
b10101100 ,
b101100 '
0$
#93
b1101101 -
b1101101 .
b111011010 0
b11101101 /
b11101101 4
1$
#94
b11101110 5
b1011010 1
b1011010 3
b10101101 &
b10101101 (
b10101101 *
b10101101 ,
b101101 '
0$
#95
b1101110 -
b1101110 .
b111011100 0
b11101110 /
b11101110 4
1$
#96
b11101111 5
b1011100 1
b1011100 3
b10101110 &
b10101110 (
b10101110 *
b10101110 ,
b101110 '
0$
#97
b1101111 -
b1101111 .
b111011110 0
b11101111 /
b11101111 4
b10000010 #
b10000010 )
1$
#98
b11110000 5
b1011110 1
b1011110 3
b10101111 &
b10101111 (
b10101111 *
b10101111 ,
b101111 '
0$
#99
b1110000 -
b1110000 .
b111100000 0
b11110000 /
b11110000 4
1$
#100
b11110001 5
b1100000 1
b1100000 3
b10110000 &
b10110000 (
b10110000 *
b10110000 ,
b110000 '
0$
#101
b1110001 -
b1110001 .
b111100010 0
b11110001 /
b11110001 4
b10000011 "
b10000011 +
1$
#102
b11110010 5
b1100010 1
b1100010 3
b10110001 &
b10110001 (
b10110001 *
b10110001 ,
b110001 '
0$
#103
b1110010 -
b1110010 .
b111100100 0
b11110010 /
b11110010 4
1$
#104
b11110011 5
b1100100 1
b1100100 3
b10110010 &
b10110010 (
b10110010 *
b10110010 ,
b110010 '
0$
#105
b1110011 -
b1110011 .
b111100110 0
b11110011 /
b11110011 4
1$
#106
b11110100 5
b1100110 1
b1100110 3
b10110011 &
b10110011 (
b10110011 *
b10110011 ,
b110011 '
0$
#107
b1110100 -
b1110100 .
b111101000 0
b11110100 /
b11110100 4
1$
#108
b11110101 5
b1101000 1
b1101000 3
b10110100 &
b10110100 (
b10110100 *
b10110100 ,
b110100 '
0$
#109
b1110101 -
b1110101 .
b111101010 0
b11110101 /
b11110101 4
1$
#110
b11110110 5
b1101010 1
b1101010 3
b10110101 &
b10110101 (
b10110101 *
b10110101 ,
b110101 '
0$
#111
b1110110 -
b1110110 .
b111101100 0
b11110110 /
b11110110 4
1$
#112
b11110111 5
b1101100 1
b1101100 3
b10110110 &
b10110110 (
b10110110 *
b10110110 ,
b110110 '
0$
#113
b1110111 -
b1110111 .
b111101110 0
b11110111 /
b11110111 4
1$
#114
b11111000 5
b1101110 1
b1101110 3
b10110111 &
b10110111 (
b10110111 *
b10110111 ,
b110111 '
0$
#115
b1111000 -
b1111000 .
b10000011 #
b10000011 )
b111110000 0
b11111000 /
b11111000 4
1$
#116
b11111001 5
b1110000 1
b1110000 3
b10111000 &
b10111000 (
b10111000 *
b10111000 ,
b111000 '
0$
#117
b1111001 -
b1111001 .
b111110010 0
b11111001 /
b11111001 4
1$
#118
b11111010 5
b1110010 1
b1110010 3
b10111001 &
b10111001 (
b10111001 *
b10111001 ,
b111001 '
0$
#119
b1111010 -
b1111010 .
b111110100 0
b11111010 /
b11111010 4
1$
#120
b11111011 5
b1110100 1
b1110100 3
b10111010 &
b10111010 (
b10111010 *
b10111010 ,
b111010 '
0$
#121
b1111011 -
b1111011 .
b111110110 0
b11111011 /
b11111011 4
1$
#122
b11111100 5
b1110110 1
b1110110 3
b10111011 &
b10111011 (
b10111011 *
b10111011 ,
b111011 '
0$
#123
b1111100 -
b1111100 .
b111111000 0
b11111100 /
b11111100 4
1$
#124
b11111101 5
b1111000 1
b1111000 3
b10111100 &
b10111100 (
b10111100 *
b10111100 ,
b111100 '
0$
#125
b1111101 -
b1111101 .
b111111010 0
b11111101 /
b11111101 4
b10000100 #
b10000100 )
1$
#126
b11111110 5
b1111010 1
b1111010 3
b10111101 &
b10111101 (
b10111101 *
b10111101 ,
b111101 '
0$
#127
b1111110 -
b1111110 .
b111111100 0
b11111110 /
b11111110 4
1$
#128
b11111111 5
b1111100 1
b1111100 3
b10111110 &
b10111110 (
b10111110 *
b10111110 ,
b111110 '
0$
#129
b1111111 -
b1111111 .
b111111110 0
b11111111 /
b11111111 4
1$
#130
b0 5
b1111110 1
b1111110 3
b10111111 &
b10111111 (
b10111111 *
b10111111 ,
b111111 '
0$
#131
b10000000 -
b10000000 .
b0 0
b0 /
b0 4
1$
#132
b10000000 1
b10000000 3
b11000000 &
b11000000 (
b11000000 *
b11000000 ,
b1000000 '
0$
#133
b10000101 #
b10000101 )
b10000101 "
b10000101 +
1$
#134
b110 5
b10000010 1
b10000010 3
b11000001 &
b11000001 (
b11000001 *
b11000001 ,
b1000001 '
0$
#135
b10000110 !
b10000110 2
b10000110 -
b10000110 .
b1100 0
b110 /
b110 4
b10000110 "
b10000110 +
1$
#136
b111 5
b10000100 1
b10000100 3
b11000010 &
b11000010 (
b11000010 *
b11000010 ,
b1000010 '
0$
