activation_functions/tanh/lut_based_tanh.v
module tanh_lut (
    input clk,
    input reset,
    input signed [7:0] x_in,  // Q3.5 input (-4 to 4)
    output reg signed [7:0] y_out    // Q0.7 output (-1 to 1)
);

     reg signed [7:0] LUT [255:0];

    //registering output
    always @(posedge clk or negedge reset) begin
      if(~reset) begin
        y_out <= 0;
      end
      else begin
        y_out <= LUT['sd128+x_in];
      end
    end 


    always @(posedge clk or negedge reset) begin
      LUT[0] <= -128;
      LUT[1] <= -128;
      LUT[2] <= -128;
      LUT[3] <= -128;
      LUT[4] <= -128;
      LUT[5] <= -128;
      LUT[6] <= -128;
      LUT[7] <= -128;
      LUT[8] <= -128;
      LUT[9] <= -128;
      LUT[10] <= -128;
      LUT[11] <= -128;
      LUT[12] <= -128;
      LUT[13] <= -128;
      LUT[14] <= -128;
      LUT[15] <= -128;
      LUT[16] <= -128;
      LUT[17] <= -128;
      LUT[18] <= -128;
      LUT[19] <= -128;
      LUT[20] <= -128;
      LUT[21] <= -128;
      LUT[22] <= -128;
      LUT[23] <= -128;
      LUT[24] <= -128;
      LUT[25] <= -128;
      LUT[26] <= -128;
      LUT[27] <= -128;
      LUT[28] <= -128;
      LUT[29] <= -127;
      LUT[30] <= -127;
      LUT[31] <= -127;
      LUT[32] <= -127;
      LUT[33] <= -127;
      LUT[34] <= -127;
      LUT[35] <= -127;
      LUT[36] <= -127;
      LUT[37] <= -127;
      LUT[38] <= -127;
      LUT[39] <= -127;
      LUT[40] <= -127;
      LUT[41] <= -127;
      LUT[42] <= -127;
      LUT[43] <= -127;
      LUT[44] <= -127;
      LUT[45] <= -126;
      LUT[46] <= -126;
      LUT[47] <= -126;
      LUT[48] <= -126;
      LUT[49] <= -126;
      LUT[50] <= -126;
      LUT[51] <= -126;
      LUT[52] <= -126;
      LUT[53] <= -126;
      LUT[54] <= -125;
      LUT[55] <= -125;
      LUT[56] <= -125;
      LUT[57] <= -125;
      LUT[58] <= -125;
      LUT[59] <= -124;
      LUT[60] <= -124;
      LUT[61] <= -124;
      LUT[62] <= -124;
      LUT[63] <= -123;
      LUT[64] <= -123;
      LUT[65] <= -123;
      LUT[66] <= -122;
      LUT[67] <= -122;
      LUT[68] <= -122;
      LUT[69] <= -121;
      LUT[70] <= -121;
      LUT[71] <= -120;
      LUT[72] <= -120;
      LUT[73] <= -120;
      LUT[74] <= -119;
      LUT[75] <= -118;
      LUT[76] <= -118;
      LUT[77] <= -117;
      LUT[78] <= -117;
      LUT[79] <= -116;
      LUT[80] <= -115;
      LUT[81] <= -114;
      LUT[82] <= -113;
      LUT[83] <= -113;
      LUT[84] <= -112;
      LUT[85] <= -111;
      LUT[86] <= -110;
      LUT[87] <= -109;
      LUT[88] <= -107;
      LUT[89] <= -106;
      LUT[90] <= -105;
      LUT[91] <= -104;
      LUT[92] <= -102;
      LUT[93] <= -101;
      LUT[94] <= -99;
      LUT[95] <= -97;
      LUT[96] <= -96;
      LUT[97] <= -94;
      LUT[98] <= -92;
      LUT[99] <= -90;
      LUT[100] <= -88;
      LUT[101] <= -86;
      LUT[102] <= -84;
      LUT[103] <= -81;
      LUT[104] <= -79;
      LUT[105] <= -76;
      LUT[106] <= -74;
      LUT[107] <= -71;
      LUT[108] <= -68;
      LUT[109] <= -65;
      LUT[110] <= -62;
      LUT[111] <= -59;
      LUT[112] <= -56;
      LUT[113] <= -53;
      LUT[114] <= -49;
      LUT[115] <= -46;
      LUT[116] <= -42;
      LUT[117] <= -39;
      LUT[118] <= -35;
      LUT[119] <= -31;
      LUT[120] <= -28;
      LUT[121] <= -24;
      LUT[122] <= -20;
      LUT[123] <= -16;
      LUT[124] <= -12;
      LUT[125] <= -8;
      LUT[126] <= -4;
      LUT[127] <= 0;
      LUT[128] <= 4;
      LUT[129] <= 8;
      LUT[130] <= 12;
      LUT[131] <= 16;
      LUT[132] <= 20;
      LUT[133] <= 24;
      LUT[134] <= 28;
      LUT[135] <= 31;
      LUT[136] <= 35;
      LUT[137] <= 39;
      LUT[138] <= 42;
      LUT[139] <= 46;
      LUT[140] <= 49;
      LUT[141] <= 53;
      LUT[142] <= 56;
      LUT[143] <= 59;
      LUT[144] <= 62;
      LUT[145] <= 65;
      LUT[146] <= 68;
      LUT[147] <= 71;
      LUT[148] <= 74;
      LUT[149] <= 76;
      LUT[150] <= 79;
      LUT[151] <= 81;
      LUT[152] <= 84;
      LUT[153] <= 86;
      LUT[154] <= 88;
      LUT[155] <= 90;
      LUT[156] <= 92;
      LUT[157] <= 94;
      LUT[158] <= 96;
      LUT[159] <= 97;
      LUT[160] <= 99;
      LUT[161] <= 101;
      LUT[162] <= 102;
      LUT[163] <= 104;
      LUT[164] <= 105;
      LUT[165] <= 106;
      LUT[166] <= 107;
      LUT[167] <= 109;
      LUT[168] <= 110;
      LUT[169] <= 111;
      LUT[170] <= 112;
      LUT[171] <= 113;
      LUT[172] <= 113;
      LUT[173] <= 114;
      LUT[174] <= 115;
      LUT[175] <= 116;
      LUT[176] <= 117;
      LUT[177] <= 117;
      LUT[178] <= 118;
      LUT[179] <= 118;
      LUT[180] <= 119;
      LUT[181] <= 120;
      LUT[182] <= 120;
      LUT[183] <= 120;
      LUT[184] <= 121;
      LUT[185] <= 121;
      LUT[186] <= 122;
      LUT[187] <= 122;
      LUT[188] <= 122;
      LUT[189] <= 123;
      LUT[190] <= 123;
      LUT[191] <= 123;
      LUT[192] <= 124;
      LUT[193] <= 124;
      LUT[194] <= 124;
      LUT[195] <= 124;
      LUT[196] <= 125;
      LUT[197] <= 125;
      LUT[198] <= 125;
      LUT[199] <= 125;
      LUT[200] <= 125;
      LUT[201] <= 126;
      LUT[202] <= 126;
      LUT[203] <= 126;
      LUT[204] <= 126;
      LUT[205] <= 126;
      LUT[206] <= 126;
      LUT[207] <= 126;
      LUT[208] <= 126;
      LUT[209] <= 126;
      LUT[210] <= 127;
      LUT[211] <= 127;
      LUT[212] <= 127;
      LUT[213] <= 127;
      LUT[214] <= 127;
      LUT[215] <= 127;
      LUT[216] <= 127;
      LUT[217] <= 127;
      LUT[218] <= 127;
      LUT[219] <= 127;
      LUT[220] <= 127;
      LUT[221] <= 127;
      LUT[222] <= 127;
      LUT[223] <= 127;
      LUT[224] <= 127;
      LUT[225] <= 127;
      LUT[226] <= 127;
      LUT[227] <= 127;
      LUT[228] <= 127;
      LUT[229] <= 127;
      LUT[230] <= 127;
      LUT[231] <= 127;
      LUT[232] <= 127;
      LUT[233] <= 127;
      LUT[234] <= 127;
      LUT[235] <= 127;
      LUT[236] <= 127;
      LUT[237] <= 127;
      LUT[238] <= 127;
      LUT[239] <= 127;
      LUT[240] <= 127;
      LUT[241] <= 127;
      LUT[242] <= 127;
      LUT[243] <= 127;
      LUT[244] <= 127;
      LUT[245] <= 127;
      LUT[246] <= 127;
      LUT[247] <= 127;
      LUT[248] <= 127;
      LUT[249] <= 127;
      LUT[250] <= 127;
      LUT[251] <= 127;
      LUT[252] <= 127;
      LUT[253] <= 127;
      LUT[254] <= 127;
      LUT[255] <= 127;
    end

endmodule

activation_functions/tanh/piecewise_linear_tanh.v
module tanh_piecewise (
    input clk,
    input reset,
    input signed [7:0] x_in,  // Q3.5 input (-4 to 4)
    output reg signed [7:0] y_out // Q0.7 output (-128 to 127)
);

    // Constants for the piecewise linear approximation (using shifts and adds)
    
    // For the range -3 to -2
    localparam signed [7:0] SHIFT_1 = 4;   
    localparam signed [7:0] OFFSET_1 = -8'd128;

    // For the range -2 to -1
    localparam signed [7:0] SHIFT_2 = 1;    
    localparam signed [7:0] OFFSET_2 = -8'd123;  

    // For the range -1 to 1
    localparam signed [7:0] SHIFT_3 = 1;    
    localparam signed [7:0] OFFSET_3 = -8'd97;  
 

    // For the range 1 to 2
    localparam signed [7:0] SHIFT_4 = 1;    
    localparam signed [7:0] OFFSET_4 = 8'd97;
   
    // For the range 2 to 3
    localparam signed [7:0] SHIFT_5 = 4;    
    localparam signed [7:0] OFFSET_5 = 8'd123;  
 
    localparam signed [7:0] OFFSET_6 = 8'd127; 

    always @(posedge clk or posedge reset) begin
        if (~reset) begin
            y_out <= 8'd0;  // Reset to 0
        end else begin
            // Piecewise function for tanh approximation
            if (x_in <= -96) begin
                y_out <= OFFSET_1; 
            end else if (x_in < -64) begin
                y_out <= ((x_in + 128) >>> SHIFT_1) + OFFSET_1; // Use shift to approximate slope
            end else if (x_in < -32) begin
                y_out <= ((x_in + 64) >>> SHIFT_2) + OFFSET_2; // Use shift to approximate slope
            end else if (x_in < 0) begin
                y_out <= ((x_in + 32) <<< SHIFT_3) + OFFSET_3; // Use shift to approximate slope
            end else if (x_in < 32) begin
                y_out <= ((x_in) <<< SHIFT_3); // Use shift to approximate slope
            end else if (x_in < 64) begin
                y_out <= ((x_in - 32) >>> SHIFT_4) + OFFSET_4; // Use shift to approximate slope
            end else if (x_in < 96) begin
                y_out <= ((x_in - 64) >>> SHIFT_5) + OFFSET_5; // Use shift to approximate slope
            end else begin
                y_out <= OFFSET_6;  // Default to 1 if x > 3
            end
        end
    end
endmodule

activation_functions/tanh/tanh_tb.v
module test_tanh;
    reg signed [7:0] x;
    wire signed [7:0] y_piecewise, y_lut;
    integer i;
    reg reset;
    reg clk;

    tanh_piecewise instance_piecewise (
        .x_in(x),
        .y_out(y_piecewise),
        .clk(clk),
        .reset(reset)
    );

    tanh_lut instance_lut (
        .x_in(x),
        .y_out(y_lut),
        .clk(clk),
        .reset(reset)
    );


   //clock generation
   initial begin
    clk = 0;
    forever begin #0.5 clk = ~clk; end
   end   
   

    initial begin
      $dumpfile("test_tanh.vcd");
      $dumpvars(0,test_tanh);

      $display("Begin Reset");
      reset = 0; 
      repeat(2)@(posedge clk);
      reset = 1;
      $display("End reset");

      $display("Testing Tanh Module:");
      $display("  x\t\tLUT\t\tPieceWise Linear");
      @(negedge clk)
      for (i = 0; i < 256; i = i + 1) begin
          x = (i - 128); // Test inputs: -128, -96, ..., 127
          @(negedge clk)
          $display("%d\t\t%d\t\t%d\t\t", x, y_lut, y_piecewise);
      end 
        $finish;
    end
endmodule

activation_functions/tanh/test_tanh.vcd
$date
	Sun Dec  1 20:31:14 2024
$end
$version
	Icarus Verilog
$end
$timescale
	1s
$end
$scope module test_tanh $end
$var wire 8 ! y_piecewise [7:0] $end
$var wire 8 " y_lut [7:0] $end
$var reg 1 # clk $end
$var reg 1 $ reset $end
$var reg 8 % x [7:0] $end
$var integer 32 & i [31:0] $end
$scope module instance_lut $end
$var wire 1 # clk $end
$var wire 1 $ reset $end
$var wire 8 ' x_in [7:0] $end
$var reg 8 ( y_out [7:0] $end
$upscope $end
$scope module instance_piecewise $end
$var wire 1 # clk $end
$var wire 1 $ reset $end
$var wire 8 ) x_in [7:0] $end
$var reg 8 * y_out [7:0] $end
$upscope $end
$upscope $end
$enddefinitions $end
#0
$dumpvars
bx *
bx )
b0 (
bx '
bx &
bx %
0$
0#
b0 "
bx !
$end
#1
b0 !
b0 *
1#
#2
0#
#3
bx "
bx (
b1111111 !
b1111111 *
1$
1#
#4
b10000000 %
b10000000 '
b10000000 )
b0 &
0#
#5
b10000000 "
b10000000 (
b10000000 !
b10000000 *
1#
#6
b10000001 %
b10000001 '
b10000001 )
b1 &
0#
#7
1#
#8
b10000010 %
b10000010 '
b10000010 )
b10 &
0#
#9
1#
#10
b10000011 %
b10000011 '
b10000011 )
b11 &
0#
#11
1#
#12
b10000100 %
b10000100 '
b10000100 )
b100 &
0#
#13
1#
#14
b10000101 %
b10000101 '
b10000101 )
b101 &
0#
#15
1#
#16
b10000110 %
b10000110 '
b10000110 )
b110 &
0#
#17
1#
#18
b10000111 %
b10000111 '
b10000111 )
b111 &
0#
#19
1#
#20
b10001000 %
b10001000 '
b10001000 )
b1000 &
0#
#21
1#
#22
b10001001 %
b10001001 '
b10001001 )
b1001 &
0#
#23
1#
#24
b10001010 %
b10001010 '
b10001010 )
b1010 &
0#
#25
1#
#26
b10001011 %
b10001011 '
b10001011 )
b1011 &
0#
#27
1#
#28
b10001100 %
b10001100 '
b10001100 )
b1100 &
0#
#29
1#
#30
b10001101 %
b10001101 '
b10001101 )
b1101 &
0#
#31
1#
#32
b10001110 %
b10001110 '
b10001110 )
b1110 &
0#
#33
1#
#34
b10001111 %
b10001111 '
b10001111 )
b1111 &
0#
#35
1#
#36
b10010000 %
b10010000 '
b10010000 )
b10000 &
0#
#37
1#
#38
b10010001 %
b10010001 '
b10010001 )
b10001 &
0#
#39
1#
#40
b10010010 %
b10010010 '
b10010010 )
b10010 &
0#
#41
1#
#42
b10010011 %
b10010011 '
b10010011 )
b10011 &
0#
#43
1#
#44
b10010100 %
b10010100 '
b10010100 )
b10100 &
0#
#45
1#
#46
b10010101 %
b10010101 '
b10010101 )
b10101 &
0#
#47
1#
#48
b10010110 %
b10010110 '
b10010110 )
b10110 &
0#
#49
1#
#50
b10010111 %
b10010111 '
b10010111 )
b10111 &
0#
#51
1#
#52
b10011000 %
b10011000 '
b10011000 )
b11000 &
0#
#53
1#
#54
b10011001 %
b10011001 '
b10011001 )
b11001 &
0#
#55
1#
#56
b10011010 %
b10011010 '
b10011010 )
b11010 &
0#
#57
1#
#58
b10011011 %
b10011011 '
b10011011 )
b11011 &
0#
#59
1#
#60
b10011100 %
b10011100 '
b10011100 )
b11100 &
0#
#61
1#
#62
b10011101 %
b10011101 '
b10011101 )
b11101 &
0#
#63
b10000001 "
b10000001 (
1#
#64
b10011110 %
b10011110 '
b10011110 )
b11110 &
0#
#65
1#
#66
b10011111 %
b10011111 '
b10011111 )
b11111 &
0#
#67
1#
#68
b10100000 %
b10100000 '
b10100000 )
b100000 &
0#
#69
1#
#70
b10100001 %
b10100001 '
b10100001 )
b100001 &
0#
#71
b10000010 !
b10000010 *
1#
#72
b10100010 %
b10100010 '
b10100010 )
b100010 &
0#
#73
1#
#74
b10100011 %
b10100011 '
b10100011 )
b100011 &
0#
#75
1#
#76
b10100100 %
b10100100 '
b10100100 )
b100100 &
0#
#77
1#
#78
b10100101 %
b10100101 '
b10100101 )
b100101 &
0#
#79
1#
#80
b10100110 %
b10100110 '
b10100110 )
b100110 &
0#
#81
1#
#82
b10100111 %
b10100111 '
b10100111 )
b100111 &
0#
#83
1#
#84
b10101000 %
b10101000 '
b10101000 )
b101000 &
0#
#85
1#
#86
b10101001 %
b10101001 '
b10101001 )
b101001 &
0#
#87
1#
#88
b10101010 %
b10101010 '
b10101010 )
b101010 &
0#
#89
1#
#90
b10101011 %
b10101011 '
b10101011 )
b101011 &
0#
#91
1#
#92
b10101100 %
b10101100 '
b10101100 )
b101100 &
0#
#93
1#
#94
b10101101 %
b10101101 '
b10101101 )
b101101 &
0#
#95
b10000010 "
b10000010 (
1#
#96
b10101110 %
b10101110 '
b10101110 )
b101110 &
0#
#97
1#
#98
b10101111 %
b10101111 '
b10101111 )
b101111 &
0#
#99
1#
#100
b10110000 %
b10110000 '
b10110000 )
b110000 &
0#
#101
b10000011 !
b10000011 *
1#
#102
b10110001 %
b10110001 '
b10110001 )
b110001 &
0#
#103
1#
#104
b10110010 %
b10110010 '
b10110010 )
b110010 &
0#
#105
1#
#106
b10110011 %
b10110011 '
b10110011 )
b110011 &
0#
#107
1#
#108
b10110100 %
b10110100 '
b10110100 )
b110100 &
0#
#109
1#
#110
b10110101 %
b10110101 '
b10110101 )
b110101 &
0#
#111
1#
#112
b10110110 %
b10110110 '
b10110110 )
b110110 &
0#
#113
b10000011 "
b10000011 (
1#
#114
b10110111 %
b10110111 '
b10110111 )
b110111 &
0#
#115
1#
#116
b10111000 %
b10111000 '
b10111000 )
b111000 &
0#
#117
1#
#118
b10111001 %
b10111001 '
b10111001 )
b111001 &
0#
#119
1#
#120
b10111010 %
b10111010 '
b10111010 )
b111010 &
0#
#121
1#
#122
b10111011 %
b10111011 '
b10111011 )
b111011 &
0#
#123
b10000100 "
b10000100 (
1#
#124
b10111100 %
b10111100 '
b10111100 )
b111100 &
0#
#125
1#
#126
b10111101 %
b10111101 '
b10111101 )
b111101 &
0#
#127
1#
#128
b10111110 %
b10111110 '
b10111110 )
b111110 &
0#
#129
1#
#130
b10111111 %
b10111111 '
b10111111 )
b111111 &
0#
#131
b10000101 "
b10000101 (
1#
#132
b11000000 %
b11000000 '
b11000000 )
b1000000 &
0#
#133
b10000101 !
b10000101 *
1#
#134
b11000001 %
b11000001 '
b11000001 )
b1000001 &
0#
#135
1#
#136
b11000010 %
b11000010 '
b11000010 )
b1000010 &
0#
#137
b10000110 "
b10000110 (
b10000110 !
b10000110 *
1#
#138
b11000011 %
b11000011 '
b11000011 )
b1000011 &
0#
#139
1#
#140
b11000100 %
b11000100 '
b11000100 )
b1000100 &
0#
#141
b10000111 !
b10000111 *
1#
#142
b11000101 %
b11000101 '
b11000101 )
b1000101 &
0#
#143
b10000111 "
b10000111 (
1#
#144
b11000110 %
b11000110 '
b11000110 )
b1000110 &
0#
#145
b10001000 !
b10001000 *
1#
#146
b11000111 %
b11000111 '
b11000111 )
b1000111 &
0#
#147
b10001000 "
b10001000 (
1#
#148
b11001000 %
b11001000 '
b11001000 )
b1001000 &
0#
#149
b10001001 !
b10001001 *
1#
#150
b11001001 %
b11001001 '
b11001001 )
b1001001 &
0#
#151
1#
#152
b11001010 %
b11001010 '
b11001010 )
b1001010 &
0#
#153
b10001001 "
b10001001 (
b10001010 !
b10001010 *
1#
#154
b11001011 %
b11001011 '
b11001011 )
b1001011 &
0#
#155
b10001010 "
b10001010 (
1#
#156
b11001100 %
b11001100 '
b11001100 )
b1001100 &
0#
#157
b10001011 !
b10001011 *
1#
#158
b11001101 %
b11001101 '
b11001101 )
b1001101 &
0#
#159
b10001011 "
b10001011 (
1#
#160
b11001110 %
b11001110 '
b11001110 )
b1001110 &
0#
#161
b10001100 !
b10001100 *
1#
#162
b11001111 %
b11001111 '
b11001111 )
b1001111 &
0#
#163
b10001100 "
b10001100 (
1#
#164
b11010000 %
b11010000 '
b11010000 )
b1010000 &
0#
#165
b10001101 "
b10001101 (
b10001101 !
b10001101 *
1#
#166
b11010001 %
b11010001 '
b11010001 )
b1010001 &
0#
#167
b10001110 "
b10001110 (
1#
#168
b11010010 %
b11010010 '
b11010010 )
b1010010 &
0#
#169
b10001111 "
b10001111 (
b10001110 !
b10001110 *
1#
#170
b11010011 %
b11010011 '
b11010011 )
b1010011 &
0#
#171
1#
#172
b11010100 %
b11010100 '
b11010100 )
b1010100 &
0#
#173
b10010000 "
b10010000 (
b10001111 !
b10001111 *
1#
#174
b11010101 %
b11010101 '
b11010101 )
b1010101 &
0#
#175
b10010001 "
b10010001 (
1#
#176
b11010110 %
b11010110 '
b11010110 )
b1010110 &
0#
#177
b10010010 "
b10010010 (
b10010000 !
b10010000 *
1#
#178
b11010111 %
b11010111 '
b11010111 )
b1010111 &
0#
#179
b10010011 "
b10010011 (
1#
#180
b11011000 %
b11011000 '
b11011000 )
b1011000 &
0#
#181
b10010101 "
b10010101 (
b10010001 !
b10010001 *
1#
#182
b11011001 %
b11011001 '
b11011001 )
b1011001 &
0#
#183
b10010110 "
b10010110 (
1#
#184
b11011010 %
b11011010 '
b11011010 )
b1011010 &
0#
#185
b10010111 "
b10010111 (
b10010010 !
b10010010 *
1#
#186
b11011011 %
b11011011 '
b11011011 )
b1011011 &
0#
#187
b10011000 "
b10011000 (
1#
#188
b11011100 %
b11011100 '
b11011100 )
b1011100 &
0#
#189
b10011010 "
b10011010 (
b10010011 !
b10010011 *
1#
#190
b11011101 %
b11011101 '
b11011101 )
b1011101 &
0#
#191
b10011011 "
b10011011 (
1#
#192
b11011110 %
b11011110 '
b11011110 )
b1011110 &
0#
#193
b10011101 "
b10011101 (
b10010100 !
b10010100 *
1#
#194
b11011111 %
b11011111 '
b11011111 )
b1011111 &
0#
#195
b10011111 "
b10011111 (
1#
#196
b11100000 %
b11100000 '
b11100000 )
b1100000 &
0#
#197
b10100000 "
b10100000 (
b10011111 !
b10011111 *
1#
#198
b11100001 %
b11100001 '
b11100001 )
b1100001 &
0#
#199
b10100010 "
b10100010 (
b10100001 !
b10100001 *
1#
#200
b11100010 %
b11100010 '
b11100010 )
b1100010 &
0#
#201
b10100100 "
b10100100 (
b10100011 !
b10100011 *
1#
#202
b11100011 %
b11100011 '
b11100011 )
b1100011 &
0#
#203
b10100110 "
b10100110 (
b10100101 !
b10100101 *
1#
#204
b11100100 %
b11100100 '
b11100100 )
b1100100 &
0#
#205
b10101000 "
b10101000 (
b10100111 !
b10100111 *
1#
#206
b11100101 %
b11100101 '
b11100101 )
b1100101 &
0#
#207
b10101010 "
b10101010 (
b10101001 !
b10101001 *
1#
#208
b11100110 %
b11100110 '
b11100110 )
b1100110 &
0#
#209
b10101100 "
b10101100 (
b10101011 !
b10101011 *
1#
#210
b11100111 %
b11100111 '
b11100111 )
b1100111 &
0#
#211
b10101111 "
b10101111 (
b10101101 !
b10101101 *
1#
#212
b11101000 %
b11101000 '
b11101000 )
b1101000 &
0#
#213
b10110001 "
b10110001 (
b10101111 !
b10101111 *
1#
#214
b11101001 %
b11101001 '
b11101001 )
b1101001 &
0#
#215
b10110100 "
b10110100 (
b10110001 !
b10110001 *
1#
#216
b11101010 %
b11101010 '
b11101010 )
b1101010 &
0#
#217
b10110110 "
b10110110 (
b10110011 !
b10110011 *
1#
#218
b11101011 %
b11101011 '
b11101011 )
b1101011 &
0#
#219
b10111001 "
b10111001 (
b10110101 !
b10110101 *
1#
#220
b11101100 %
b11101100 '
b11101100 )
b1101100 &
0#
#221
b10111100 "
b10111100 (
b10110111 !
b10110111 *
1#
#222
b11101101 %
b11101101 '
b11101101 )
b1101101 &
0#
#223
b10111111 "
b10111111 (
b10111001 !
b10111001 *
1#
#224
b11101110 %
b11101110 '
b11101110 )
b1101110 &
0#
#225
b11000010 "
b11000010 (
b10111011 !
b10111011 *
1#
#226
b11101111 %
b11101111 '
b11101111 )
b1101111 &
0#
#227
b11000101 "
b11000101 (
b10111101 !
b10111101 *
1#
#228
b11110000 %
b11110000 '
b11110000 )
b1110000 &
0#
#229
b11001000 "
b11001000 (
b10111111 !
b10111111 *
1#
#230
b11110001 %
b11110001 '
b11110001 )
b1110001 &
0#
#231
b11001011 "
b11001011 (
b11000001 !
b11000001 *
1#
#232
b11110010 %
b11110010 '
b11110010 )
b1110010 &
0#
#233
b11001111 "
b11001111 (
b11000011 !
b11000011 *
1#
#234
b11110011 %
b11110011 '
b11110011 )
b1110011 &
0#
#235
b11010010 "
b11010010 (
b11000101 !
b11000101 *
1#
#236
b11110100 %
b11110100 '
b11110100 )
b1110100 &
0#
#237
b11010110 "
b11010110 (
b11000111 !
b11000111 *
1#
#238
b11110101 %
b11110101 '
b11110101 )
b1110101 &
0#
#239
b11011001 "
b11011001 (
b11001001 !
b11001001 *
1#
#240
b11110110 %
b11110110 '
b11110110 )
b1110110 &
0#
#241
b11011101 "
b11011101 (
b11001011 !
b11001011 *
1#
#242
b11110111 %
b11110111 '
b11110111 )
b1110111 &
0#
#243
b11100001 "
b11100001 (
b11001101 !
b11001101 *
1#
#244
b11111000 %
b11111000 '
b11111000 )
b1111000 &
0#
#245
b11100100 "
b11100100 (
b11001111 !
b11001111 *
1#
#246
b11111001 %
b11111001 '
b11111001 )
b1111001 &
0#
#247
b11101000 "
b11101000 (
b11010001 !
b11010001 *
1#
#248
b11111010 %
b11111010 '
b11111010 )
b1111010 &
0#
#249
b11101100 "
b11101100 (
b11010011 !
b11010011 *
1#
#250
b11111011 %
b11111011 '
b11111011 )
b1111011 &
0#
#251
b11110000 "
b11110000 (
b11010101 !
b11010101 *
1#
#252
b11111100 %
b11111100 '
b11111100 )
b1111100 &
0#
#253
b11110100 "
b11110100 (
b11010111 !
b11010111 *
1#
#254
b11111101 %
b11111101 '
b11111101 )
b1111101 &
0#
#255
b11111000 "
b11111000 (
b11011001 !
b11011001 *
1#
#256
b11111110 %
b11111110 '
b11111110 )
b1111110 &
0#
#257
b11111100 "
b11111100 (
b11011011 !
b11011011 *
1#
#258
b11111111 %
b11111111 '
b11111111 )
b1111111 &
0#
#259
b0 "
b0 (
b11011101 !
b11011101 *
1#
#260
b0 %
b0 '
b0 )
b10000000 &
0#
#261
b100 "
b100 (
b0 !
b0 *
1#
#262
b1 %
b1 '
b1 )
b10000001 &
0#
#263
b1000 "
b1000 (
b10 !
b10 *
1#
#264
b10 %
b10 '
b10 )
b10000010 &
0#
#265
b1100 "
b1100 (
b100 !
b100 *
1#
#266
b11 %
b11 '
b11 )
b10000011 &
0#
#267
b10000 "
b10000 (
b110 !
b110 *
1#
#268
b100 %
b100 '
b100 )
b10000100 &
0#
#269
b10100 "
b10100 (
b1000 !
b1000 *
1#
#270
b101 %
b101 '
b101 )
b10000101 &
0#
#271
b11000 "
b11000 (
b1010 !
b1010 *
1#
#272
b110 %
b110 '
b110 )
b10000110 &
0#
#273
b11100 "
b11100 (
b1100 !
b1100 *
1#
#274
b111 %
b111 '
b111 )
b10000111 &
0#
#275
b11111 "
b11111 (
b1110 !
b1110 *
1#
#276
b1000 %
b1000 '
b1000 )
b10001000 &
0#
#277
b100011 "
b100011 (
b10000 !
b10000 *
1#
#278
b1001 %
b1001 '
b1001 )
b10001001 &
0#
#279
b100111 "
b100111 (
b10010 !
b10010 *
1#
#280
b1010 %
b1010 '
b1010 )
b10001010 &
0#
#281
b101010 "
b101010 (
b10100 !
b10100 *
1#
#282
b1011 %
b1011 '
b1011 )
b10001011 &
0#
#283
b101110 "
b101110 (
b10110 !
b10110 *
1#
#284
b1100 %
b1100 '
b1100 )
b10001100 &
0#
#285
b110001 "
b110001 (
b11000 !
b11000 *
1#
#286
b1101 %
b1101 '
b1101 )
b10001101 &
0#
#287
b110101 "
b110101 (
b11010 !
b11010 *
1#
#288
b1110 %
b1110 '
b1110 )
b10001110 &
0#
#289
b111000 "
b111000 (
b11100 !
b11100 *
1#
#290
b1111 %
b1111 '
b1111 )
b10001111 &
0#
#291
b111011 "
b111011 (
b11110 !
b11110 *
1#
#292
b10000 %
b10000 '
b10000 )
b10010000 &
0#
#293
b111110 "
b111110 (
b100000 !
b100000 *
1#
#294
b10001 %
b10001 '
b10001 )
b10010001 &
0#
#295
b1000001 "
b1000001 (
b100010 !
b100010 *
1#
#296
b10010 %
b10010 '
b10010 )
b10010010 &
0#
#297
b1000100 "
b1000100 (
b100100 !
b100100 *
1#
#298
b10011 %
b10011 '
b10011 )
b10010011 &
0#
#299
b1000111 "
b1000111 (
b100110 !
b100110 *
1#
#300
b10100 %
b10100 '
b10100 )
b10010100 &
0#
#301
b1001010 "
b1001010 (
b101000 !
b101000 *
1#
#302
b10101 %
b10101 '
b10101 )
b10010101 &
0#
#303
b1001100 "
b1001100 (
b101010 !
b101010 *
1#
#304
b10110 %
b10110 '
b10110 )
b10010110 &
0#
#305
b1001111 "
b1001111 (
b101100 !
b101100 *
1#
#306
b10111 %
b10111 '
b10111 )
b10010111 &
0#
#307
b1010001 "
b1010001 (
b101110 !
b101110 *
1#
#308
b11000 %
b11000 '
b11000 )
b10011000 &
0#
#309
b1010100 "
b1010100 (
b110000 !
b110000 *
1#
#310
b11001 %
b11001 '
b11001 )
b10011001 &
0#
#311
b1010110 "
b1010110 (
b110010 !
b110010 *
1#
#312
b11010 %
b11010 '
b11010 )
b10011010 &
0#
#313
b1011000 "
b1011000 (
b110100 !
b110100 *
1#
#314
b11011 %
b11011 '
b11011 )
b10011011 &
0#
#315
b1011010 "
b1011010 (
b110110 !
b110110 *
1#
#316
b11100 %
b11100 '
b11100 )
b10011100 &
0#
#317
b1011100 "
b1011100 (
b111000 !
b111000 *
1#
#318
b11101 %
b11101 '
b11101 )
b10011101 &
0#
#319
b1011110 "
b1011110 (
b111010 !
b111010 *
1#
#320
b11110 %
b11110 '
b11110 )
b10011110 &
0#
#321
b1100000 "
b1100000 (
b111100 !
b111100 *
1#
#322
b11111 %
b11111 '
b11111 )
b10011111 &
0#
#323
b1100001 "
b1100001 (
b111110 !
b111110 *
1#
#324
b100000 %
b100000 '
b100000 )
b10100000 &
0#
#325
b1100011 "
b1100011 (
b1100001 !
b1100001 *
1#
#326
b100001 %
b100001 '
b100001 )
b10100001 &
0#
#327
b1100101 "
b1100101 (
1#
#328
b100010 %
b100010 '
b100010 )
b10100010 &
0#
#329
b1100110 "
b1100110 (
b1100010 !
b1100010 *
1#
#330
b100011 %
b100011 '
b100011 )
b10100011 &
0#
#331
b1101000 "
b1101000 (
1#
#332
b100100 %
b100100 '
b100100 )
b10100100 &
0#
#333
b1101001 "
b1101001 (
b1100011 !
b1100011 *
1#
#334
b100101 %
b100101 '
b100101 )
b10100101 &
0#
#335
b1101010 "
b1101010 (
1#
#336
b100110 %
b100110 '
b100110 )
b10100110 &
0#
#337
b1101011 "
b1101011 (
b1100100 !
b1100100 *
1#
#338
b100111 %
b100111 '
b100111 )
b10100111 &
0#
#339
b1101101 "
b1101101 (
1#
#340
b101000 %
b101000 '
b101000 )
b10101000 &
0#
#341
b1101110 "
b1101110 (
b1100101 !
b1100101 *
1#
#342
b101001 %
b101001 '
b101001 )
b10101001 &
0#
#343
b1101111 "
b1101111 (
1#
#344
b101010 %
b101010 '
b101010 )
b10101010 &
0#
#345
b1110000 "
b1110000 (
b1100110 !
b1100110 *
1#
#346
b101011 %
b101011 '
b101011 )
b10101011 &
0#
#347
b1110001 "
b1110001 (
1#
#348
b101100 %
b101100 '
b101100 )
b10101100 &
0#
#349
b1100111 !
b1100111 *
1#
#350
b101101 %
b101101 '
b101101 )
b10101101 &
0#
#351
b1110010 "
b1110010 (
1#
#352
b101110 %
b101110 '
b101110 )
b10101110 &
0#
#353
b1110011 "
b1110011 (
b1101000 !
b1101000 *
1#
